Workbook
Name \0: #REF!
Name \0: #REF!
Name \0: #REF!
Name \0: #REF!
Name \0: #REF!
Name \0: #REF!
Name \0: #REF!
Name \0: #REF!
Name \0: #REF!
Name \0: #REF!
Name \a: #REF!
Name \a: #REF!
Name \a: #REF!
Name \a: #REF!
Name \a: #REF!
Name \a: #REF!
Name \a: #REF!
Name \a: #REF!
Name \a: #REF!
Name \a: #REF!
Name \b: #N/A
Name \C: #REF!
Name \C: #REF!
Name \C: #REF!
Name \C: #REF!
Name \C: #REF!
Name \C: #REF!
Name \C: #REF!
Name \C: #REF!
Name \C: #REF!
Name \C: #REF!
Name \l: #REF!
Name \l: #REF!
Name \l: #REF!
Name \l: #REF!
Name \l: #REF!
Name \l: #REF!
Name \l: #REF!
Name \l: #REF!
Name \l: #REF!
Name \l: #REF!
Name \o: #REF!
Name \o: #REF!
Name \o: #REF!
Name \o: #REF!
Name \o: #REF!
Name \o: #REF!
Name \o: #REF!
Name \o: #REF!
Name \o: #REF!
Name \o: #REF!
Name \p: #REF!
Name \p: #REF!
Name \p: #REF!
Name \p: #REF!
Name \p: #REF!
Name \p: #REF!
Name \p: #REF!
Name \p: #REF!
Name \S: #REF!

Sheet Civil BOQ (LD Patel R1)
A1: Form A-1 Schedule of Quantities & Prices
A2: Sr.No | B2: Description | C2: UOM | D2: Quantity | E2: Rate | F2: Total Amount
A3: 1 | B3: Excavation and Backfilling
B4: Rate includes removal of all kinds of vegetation, small shrubs etc. Dewatering water to be let out of the building area through proper pipes & channels if required. The contractor at his own expenses shall water very well, ram and thoroughly, consolidate the bottom of all excavations & ground before the construction of foundation/footing/plinth beam, filling in basement floor or other work is commenced. The rate for excavation shall include for shoring sides or trenches with approved timber/steel accessories wherever necessary to prevent sides from falling including bailing or pumping out of water if necessary and include If there are any shrubs, bushes, trees, roots of the trees to be removed for min depth 5’0”. Lift & lead outside campus are to be considered to suit the local regulations. Contour level to be taken jointly with the Project Manager and prior written approval be taken before starting any excavation/ filling at every 3 / 5 mt grids for arriving at the actual quantity. Measurements for filling will be taken for consolidated thickness only .Cost to include all and necessary royalty and other permission charges required to execute the works. Unless noted otherwise measurements shall be considered to the edge of PCC only. | F4: =D4*E4 -> 0
B5: General Excavation by mechanical means in all types of soil including dense soil, disintegrated/ weathered / soft rock / Medium Rock including necessary manual excavation for dressing the edges & levelling, all leads and lifts, necessary soil stabilization pre excavation, protection etc in all types of soil except hard rock as specified and directed. The rate shall include the necessary surface preparation required for the Excavation and to its related works as specified and directed. Rate to include carting away of excavated material outside the site. Note: PCC area shall be considered for measurement Rate to include the dressing of excavated surface to be handed over from General excavation contractor to the required level. (Working space & provision of slopes if required for execution shall not be paid separately). | F5: =IF(D5="QRO",0,D5*E5) -> 0
A6: 1.1 | B6: Excavation in soil at all depth | C6: Cum | D6: ='Excavation Qty for BOQ'!I11 -> 20000.884 | E6: 495 | F6: =IF(D6="QRO",0,D6*E6) -> 9900437.6
B7: Same as item No - 1 above but in hard rock/ boulders (Un-poclainable) by chiselling/wedging up to the required level & depth including all leads and lifts, and carting away excavated material outside the site as directed, de-watering of both ground and surface water as specified. Blasting is not allowed. Note:PCC area shall be considered for measurement (Working space & provision of slopes if required for execution shall not be paid separately. Mode of measurement shall be by joint measurements/ levels before and after excavation). | F7: =IF(D7="QRO",0,D7*E7) -> 0
A8: 1.2 | B8: Excavation in Hard rock at all depth | C8: Cum | D8: ='Excavation Qty for BOQ'!I12 -> 2222.3204 | E8: 750 | F8: =IF(D8="QRO",0,D8*E8) -> 1666740.3
A9: 1.3 | B9: Manual Excavation | C9: Cum | D9: QRO | E9: 945 | F9: =IF(D9="QRO",0,D9*E9) -> 0
B10: Backfilling with approved good quality earth in plinths, below grade slab, behind retaining wall etc. in layers not exceeding depths mentioned below, breaking clods, watering, compacting each layer with vibratory compactor (Vibratory Roller/Compactor capacity i.e. 8 to 10 Tonne) and at inaccessible places with 2 Ton Roller/Plate Compactor to achieve required proctor density mentioned below with optimum moisture content as mentioned below; dressing up embankments; if required, bailing/pumping out of water to keep site dry while backfilling; rate to includes conveyance of all materials, labour, machinery etc. complete as per direction of the EIC to his entire satisfaction. The rate is inclusive of Dewatering. Notes: (1) Field compaction: 98% for Plinth area and 95% for other areas (2) Layers thickness of filling: 150mm compacted in Plinth area filling and 200mm compacted in other filling areas (3) Field density tests: 1 test / 5 Sq.m. for each layer in plinth filling area and 1 test / 50 Sq.m. in other filling area by Sand replacement method as per IS 2720 Part 28 (Latest revision) (4) The measurement shall be for the net compacted volume of filling done. Block levels at intervals of 5 X 5 m or as directed by the Engineer shall be jointly recorded for the measurement purpose, before the start of filling. The acceptance criteria for backfilling works like formation levels, method of compaction, optimum moisture content variation etc. Complete. Please refer Tender Document, Preamble to BOQ, Standard Conditions of Contract, All annexures attached in Tender Document etc. as these all shall be considered in Rates Quoted in BOQ. Mode of Measurement - Actual Filling Area in Cum | F10: =IF(D10="QRO",0,D10*E10) -> 0
A11: 1.5 | B11: With selected excavated material available within plot. | C11: Cum | D11: ='Excavation Qty for BOQ'!I17 -> 9621.071 | E11: 425 | F11: =IF(D11="QRO",0,D11*E11) -> 4088955.2
A12: 1.6 | B12: With approved quality of earth brought from outside | C12: Cum | D12: QRO | E12: 460 | F12: =IF(D12="QRO",0,D12*E12) -> 0
B13: Providing and applying anti termite treatment using approved chemical, conforming to IS 6313 part II (Latest Revision) and approved Method Statement using chemical at 5ltr/sqm of application area or as per manufacture recommendation that shall create a chemical barrier under and around the foundation pits, along external perimeter of building, surroundings of pipes, conduits, etc.; all complete and conforming to specifications and/ or as per approved manufacturer's instructions/recommendation, initial level supervision and application by manufacturer's approved agency with a guarantee of 10 years by Manufacturer and Contractor, all to the satisfaction of the EIC. (Plinth area in plan at ground level shall be measured as per IS 3861). Commencement of work shall be done as per approved method statement. Area at plinth level will be considered for payment.. (Rates include material+labour,tranportation+wastage etc) | F13: =IF(D13="QRO",0,D13*E13) -> 0
A14: 1.7 | B14: Anti Termite | C14: Sqm | D14: =Excavation!I14 -> 2077.24 | E14: 130 | F14: =IF(D14="QRO",0,D14*E14) -> 270041.2
A15: 1.8 | B15: Providing and applying two component coal-tar based epoxy protective coating of approved manufacture to be applied externally on concrete surfaces directly in contact with soil, following manufactures specification as directed by EIC Mode of Measurment:Actual Area of Application | C15: Sqm | D15: QRO | F15: =IF(D15="QRO",0,D15*E15) -> 0
B16: Providing and laying in position minimum 230mm thick Soling, base preparation by Mechanical compaction, using deccan trap basalt hand broken / Rubble for void filling, murrum for binding including watering,packing,compaction etc. in under floor, foundation, pavement, roads, steps, ramps, soak pit and other similar locations, hand set vertically in regular lines, interstices filled in with smaller stone chips including watering and Compaction / consolidating & finishing to the required levels and lines etc with mechanical rammer / manual compaction etc. complete as directed by EIC and as mentioned in Specification and drawing, etc Complete. (Binding layer shall be of metal, sand or murrum which shall be part of Rate quoted). Please refer Tender Document, Preamble to BOQ, Standard Conditions of Contract, All annexures attached in Tender Document etc. as these all shall be considered in Rates Quoted in BOQ.(Rates include material+labour,tranportation+wastage etc) | F16: =IF(D16="QRO",0,D16*E16) -> 0
A17: 1.9 | B17: Soling | C17: Cum | D17: QRO | E17: 500.4 | F17: =IF(D17="QRO",0,D17*E17) -> 0
B18: Excavation Total | F18: =SUM(F4:F17) -> 15926174
F19: =IF(D19="QRO",0,D19*E19) -> 0
A20: 2 | B20: RCC
A21: 2.1 | B21: READY MIX CONCRETE / CONTROLLED CONCRETE | F21: =IF(D21="QRO",0,D21*E21) -> 0
B22: Providing, batching, mixing, transporting through transit mixers, pumping and laying Reinforced Cement Concrete of specified grade at all levels and heights, elevations, projections, surfaces specified below using ordinary Portland cement of grade 53 from approved manufacturer, river sand/manufactured sand, 20mm and down size coarse aggregates, necessary admixtures approved by Consultants/as specified in the contract document, including all leads and lifts, pumping using line pump or boom placer, vibrating/ compaction, scaffolding wherever necessary, curing, treatment of construction joints, necessary co-ordination for Post tensioning works if any etc. complete as directed by the EIC, excluding cost of shuttering and centering. The cost shall include any additional enhancers required to make the concrete more durable or to achieve the strength as per instruction of structural consultant. All necessary treatment to honey combed areas, uneven concrete surfaces shall be made proper as per the structural consultant without any extra cost | F22: =IF(D22="QRO",0,D22*E22) -> 0
B23: (Design mix shall be as approved by the Structural Consultant / Employers representative.) | F23: =IF(D23="QRO",0,D23*E23) -> 0
B24: Note: RMC to be outsourced | F24: =IF(D24="QRO",0,D24*E24) -> 0
B25: Providing and laying specified Grade concrete for P.C.C. of specified thick wherever specified using Manufactured sand, 20mm and downsize metal including base preparation, Compaction, levelling, all leads and lifts, curing and shuttering if necessary etc., Complete | F25: =IF(D25="QRO",0,D25*E25) -> 0
A26: 2.1.1 | B26: M15-PCC | C26: Cum | D26: ='Concrete & Steel Summary'!D84 -> 683.614 | E26: 7146.1 | F26: =IF(D26="QRO",0,D26*E26) -> 4885174
A27: 2.1.2 | B27: M20-PCC | C27: Cum | D27: QRO | E27: 7515.25 | F27: =IF(D27="QRO",0,D27*E27) -> 0
A28: 2.1.3 | B28: M10- Lean Mix | C28: Cum | D28: QRO | E28: 6776.95 | F28: =IF(D28="QRO",0,D28*E28) -> 0
B29: Providing and laying 0f M20 grade concrete for Plum concrete wherever specified using manufactured sand, 40mm and down size metal and boulders of 150mm (proportion 60: 40 for boulder : Concrete ) of approved design mix including sub grade preparation, levelling, surface preparation, all leads and lifts, rough finishing at the top surface, curing and shuttering if necessary etc. | F29: =IF(D29="QRO",0,D29*E29) -> 0
A30: 2.1.4 | B30: Plum Concrete | C30: Cum | D30: ='Excavation Qty for BOQ'!I20 -> 108.0832 | E30: 5520.69 | F30: =IF(D30="QRO",0,D30*E30) -> 596693.84
B31: Providing and Laying approved design mix of concrete for Reinforced Cement Concrete (RCC) work confirming to IS 456 and as specified in drawing and technical specifications. Rate shall include the following :- Handling and transportation, labour, plant & tools, mechanical mixing, placing to required location by hoisting and / or pumping, lubrication of concrete pump line and mechnical vibration, compaction, finishing, curing by any means like by portable water and / or curing compound etc. scaffolding, dewatering, if any hacking of concrete surface wherever required etc. post concrete laitance and slurry removal, making concrete form finish complete at all floors, height and levels as directed by EIC. Forming projections, sinking of floors for sumps wherever directed, forming opening or niches, opening for services and providing dowel bars and also co-ordinating with other agencies for laying conduits, boxes, pipes, clamps etc. as directed at site and making sure they do not get damaged or chocked during concreting. Forming construction joints / expansion strips as directed by the EIC including keys, slopes, falls, temporary stops etc. complete. Any approved make admixture confirming to IS 9103, the contractor may use in order to enhance the workability / properties, any cost towards making concrete water-tight and crack free shall be the part of the item and no extra claim shall be entertained to achieve the same. This rate shall exclude the cost of formwork, shuttering and steel reinforcement. The cost of the testing has to borne by the concractor and no extra claim will be entertained on this account. Location :- Raft/ Foundation
A32: 2.1.5 | B32: M50 from outsourced RMC plant. | C32: Cum | D32: ='Concrete & Steel Summary'!D66 -> 6165.605 | E32: 10238.45 | F32: =IF(D32="QRO",0,D32*E32) -> 63126239
B34: Providing and Laying approved design mix of concrete for Reinforced Cement Concrete (RCC) work confirming to IS 456 and as specified in drawing and technical specifications. Rate shall include the following :- Handling and transportation, labour, plant & tools, mechanical mixing, placing to required location by hoisting and / or pumping, lubrication of concrete pump line and mechnical vibration, compaction, finishing, curing by any means like by portable water and / or curing compound etc. scaffolding, dewatering, if any hacking of concrete surface wherever required etc. post concrete laitance and slurry removal, making concrete form finish complete at all floors, height and levels as directed by EIC. Forming projections, sinking of floors for sumps wherever directed, forming opening or niches, opening for services and providing dowel bars and also co-ordinating with other agencies for laying conduits, boxes, pipes, clamps etc. as directed at site and making sure they do not get damaged or chocked during concreting. Forming construction joints / expansion strips as directed by the EIC including keys, slopes, falls, temporary stops etc. complete. Any approved make admixture confirming to IS 9103, the contractor may use in order to enhance the workability / properties, any cost towards making concrete water-tight and crack free shall be the part of the item and no extra claim shall be entertained to achieve the same. This rate shall exclude the cost of formwork, shuttering and steel reinforcement. The cost of the testing has to borne by the concractor and no extra claim will be entertained on this account. Columns may be free standing or integrated with shear / lift walls, they may be floating on or hanging from beams, rectangular, T shaped, L shaped or square columns, pedestral or stup columns, composite columns, butteress for retaining wall of different sizes and shapes at various levels / heights.
A35: 2.1.5 | B35: Column | F35: =IF(D35="QRO",0,D35*E35) -> 0
B36: M60 | C36: Cum | D36: QRO | E36: 10584.6 | F36: =IF(D36="QRO",0,D36*E36) -> 0
B37: M50 | C37: Cum | D37: ='Concrete & Steel Summary'!D70 -> 9560.372 | E37: =E32 -> 10238.45 | F37: =IF(D37="QRO",0,D37*E37) -> 97883391
B38: M40 | C38: Cum | D38: QRO | E38: 9600.2 | F38: =IF(D38="QRO",0,D38*E38) -> 0
A39: 2.1.6 | B39: Retaining Wall
B40: M50 | C40: Cum | D40: ='Concrete & Steel Summary'!D67 -> 336.4548 | E40: =E37 -> 10238.45 | F40: =IF(D40="QRO",0,D40*E40) -> 3444775.6
A41: 2.1.7 | B41: UGT, OHT, LMR, Swimming Pool and Parapet Wall
B42: M30 | C42: Cum | D42: QRO | E42: 8956.2 | F42: =IF(D42="QRO",0,D42*E42) -> 0
B43: M40 | C43: Cum | D43: QRO | E43: =E38 -> 9600.2
B44: M50 | C44: Cum | D44: ='Concrete & Steel Summary'!D68+'Concrete & Steel Summary'!D74+'Concrete & Steel Summary'!D75+'Concrete & Steel Summary'!D76+'Concrete & Steel Summary'!D77+'Concrete & Steel Summary'!D78 -> 1001.9178 | E44: =E37 -> 10238.45
A45: 2.1.8 | B45: Slab
B46: M30 (Basement Grade Slab) | C46: Cum | D46: ='Concrete & Steel Summary'!D69 -> 631.37944 | E46: =E42 -> 8956.2 | F46: =IF(D46="QRO",0,D46*E46) -> 5654760.5
B47: M40 | C47: Cum | D47: ='Concrete & Steel Summary'!D73 -> 7613.6441 | E47: =E43 -> 9600.2 | F47: =IF(D47="QRO",0,D47*E47) -> 73092506
B48: M50 | C48: Cum | D48: QRO | E48: =E37 -> 10238.45
A49: 2.1.9 | B49: Beams
B50: M30 | C50: Cum | D50: QRO | E50: =E42 -> 8956.2 | F50: =IF(D50="QRO",0,D50*E50) -> 0
B51: M40 | C51: Cum | D51: ='Concrete & Steel Summary'!D72 -> 3946.5937 | E51: =E47 -> 9600.2 | F51: =IF(D51="QRO",0,D51*E51) -> 37888089
B52: M50 | C52: Cum | D52: QRO | E52: =E48 -> 10238.45 | F52: =IF(D52="QRO",0,D52*E52) -> 0
A53: 2.1.10 | B53: RMC Staircase, NS Wall | C53: Cum | F53: =IF(D53="QRO",0,D53*E53) -> 0
B54: M30 | C54: Cum | D54: QRO | E54: =E50 -> 8956.2 | F54: =IF(D54="QRO",0,D54*E54) -> 0
B55: M40 | C55: Cum | D55: ='Concrete & Steel Summary'!D71+'Concrete & Steel Summary'!D79 -> 2118.9888 | E55: =E51 -> 9600.2 | F55: =IF(D55="QRO",0,D55*E55) -> 20342716
B56: M50 | C56: Cum | D56: QRO | E56: =E52 -> 10238.45 | F56: =IF(D56="QRO",0,D56*E56) -> 0
A57: 2.1.11 | B57: Do as above but for CC -M-50 site mixed concrete using concrete mixer | C57: Cum | D57: QRO | F57: =IF(D57="QRO",0,D57*E57) -> 0
A58: 2.1.12 | B58: Do as above but for CC -M-40 site mixed concrete using concrete mixer | C58: Cum | D58: QRO | F58: =IF(D58="QRO",0,D58*E58) -> 0
A59: 2.1.13 | B59: Do as above but for CC -M-30 site mixed concrete using concrete mixer | C59: Cum | D59: QRO | F59: =IF(D59="QRO",0,D59*E59) -> 0
A60: 2.1.14 | B60: Do as above but for CC -M-20 site mixed concrete using concrete mixer | C60: Cum | D60: QRO | F60: =IF(D60="QRO",0,D60*E60) -> 0
A61: 2.1.15 | B61: Do as above but for CC -M-15 site mixed concrete using concrete mixer | C61: Cum | D61: QRO | F61: =IF(D61="QRO",0,D61*E61) -> 0
A62: 2.1.16 | B62: Do as above but for CC -M-10 site mixed concrete using concrete mixer | C62: Cum | D62: QRO | F62: =IF(D62="QRO",0,D62*E62) -> 0
A63: 2.2 | B63: Providing & laying 75mm thk Vacuum de-watered Trimix Flooring in M-25 grade of concrete with 12mm micro AR glass fibers (KDM FIBER or equivalent) at 85 gms per 50 kg cement, on RCC slab base at all floors and levels . The concrete shall consist of Min 325 Kg of cement per cubic meter of concrete shall be poured in the panels (size to be approx. 4.0 X 2.4 mts in alternate pattern) and vibrated with poker vibrator, followed by double beam screed vibrator. Excess water at top surface of the vibrated concrete shall be removed by Vacuum De-watering system as per the specifications to reduce final water cement ratio. Non metallic hardener as per site condition dry shake at the rate of 4.5 Kg per Sq. mt.or as specified by the manufacturer shall be spread and then the surface shall be trowelled with a power trowel to get desired final smooth finish. Grooves / Joints at the periphery of each panel shall be formed after immediate final setting of concrete with mechanized saw cut to depth of 1/3 rd thickness of the Trimix floor and shall be 3 to 4 mm wide using non metallic Hardener of approved make. These grooved shall be filled with elastomeric sealant (Bituminous / polysulphide as specified) etc. complete as per drawings & specifications and as directed by the EIC. The floor shall be cured for a period of seven days by ponding water. The acceptance criteria for trimix works shall be as per technical specification and Approved method Statement. | C63: Sqm | D63: =Tremix!E7 -> 8722.6 | E63: 1204.84 | F63: =IF(D63="QRO",0,D63*E63) -> 10509337
A64: 2.3 | B64: Formwork | F64: =IF(D64="QRO",0,D64*E64) -> 0
B65: Providing, fabricating & erecting aluminium system form work at all levels and places wherever needed / specified including striking / deshuttering, cleaning, transporting and storing at all heights. All shuttering including columns, Shear Walls, core walls, curved walls, walls, curved slabs & beams, sunshades, fins facia, beam sides, drip mould, beam bottoms, suspended slab & beam, pergolas, stair cases & landing. Rate shall also be inclusive of providing necessary provision for external grooves provision shall be given as per the Approved GFC drawing , internal skirting arrangement as required by drawings. Including Grouting for tie rods in mivan shuttering shall be with GP2 internally as well as externally for the depth of entire thickness of RCC member as per manufacture specification approved by consultants. Only the surface area of the form work to be measured. | F65: =IF(D65="QRO",0,D65*E65) -> 0
B66: Aluminium Shuttering brought to the site shall be Brand New. The approved vendor for Aluminium Shuttering are 1) Storm, 2) MFE, 3)Kum Kang. If control plans for staggered concreting the additional stuttering shall be planned in construction Joint area. Inclined shall be provided for wall thickness more than 200mm Note: QA/QC1. Mock up approval is required well in advance for aluminium formwork finish prior to actual work starts. 2. Grouting of tie rod holes required for entire thickness of RCC member instead. | F66: =IF(D66="QRO",0,D66*E66) -> 0
A67: 2.3.1 | B67: Al. Shuttering for Columns, Beams, Slabs, structural & non structural walls staircases, chajjas etc. | C67: Sqm | D67: ='Shuttering Summary'!C4 -> 119624.04 | E67: 640 | F67: =IF(D67="QRO",0,D67*E67) -> 76559388
A68: 2.3.2 | B68: Reckli/ Moulding charges over and above the cost of shuttering works | C68: Sqm | D68: QRO | E68: 1150 | F68: =IF(D68="QRO",0,D68*E68) -> 0
A69: 2.3.4 | B69: CONVENTIONAL SHUTTERING : Providing, fabricating and erecting form work at all levels and places and profiles wherever needed/specified as per drawing including striking with 12mm Brand new Plastic coated, marine resistant waterproof ply/Smooth finished MS plates with adjustable steel props of acceptable Staging system and with sufficient bracing as approved by consultant. M.S. plates shall be considered for foundation only. Cost to include designing of proper form work and staging system to suit the requirements, Submission of design calculations and shop drawings for approval, sealing the joints with heavy duty brown self adhesive tape, aligning to line and levels including M.S. Ties, PVC Spacer, Providing openings/ cutouts/ pockets, necessary co-ordination and arrangement for Post Tensioning works if any, applying deshuttering chemical, Deshuttering as approved by the consultant etc., complete at all levels, double/triple heights, profiles, elevations/surfaces. Rate shall also be inclusive for packing tie rod holes with GP2 or other approved chemicals. Note : Only plan area shall be considered. No extra shall be paid for Side shuttering of Drop panel/column capitals. 3) Shuttering & deshuttering sequence shall be 100% ,80% & 40% from the slab to be cast respectively. The cost of shuttering includes all slopes as per details provided in the architectural drawings. Note: Tie rods shall not be used for entire thickness of water retaining structures and retaining wall . Alternatively gugu rods shall be used which breaks through and through hole. | C69: Sqm | D69: ='Shuttering Summary'!C3 -> 51310.247 | E69: 750 | F69: =IF(D69="QRO",0,D69*E69) -> 38482686
A70: 2.4 | B70: Reinforcement Steel
B71: Providing, supplying & fixing in position Fe 500 reinforcement steel for RCC work with high yield strength ribbed cold twisted tor steel (HSD) bar of various diameters and grade of steel as specified below conforming to IS specification including cutting, providing, supplying & bending, hoisting, and placing in position according to drawings and binding the reinforcement with galvanized annealed binding wire of double fold of 18 gauge and providing concrete cover blocks/PVC Cover Blocks required with strength equal to respective concrete grades. as required/instructed for placing the reinforcements in position and for maintaining the cover specified and/or according to relevant IS. | F71: =IF(D71="QRO",0,D71*E71) -> 0
B72: Note : Unless noted otherwise the measurements is accordance with IS 2502. However reinforcement shall be measured only in lengths of bars as actually placed in position on standard weight basis, no allowance being made in the weight for rolling margin. Authorized laps and splices only will be measured. Chairs of any shape & profile, Spacer bar of any shape & profile, cover block, wastage and binding wire will not be measured and shall be included in the quoted rates. Quoted rate shall be deemed to have considered the above stipulation. Quoted rate to include lead, unloading, lift, placing at all levels and as directed. | F72: =IF(D72="QRO",0,D72*E72) -> 0
A73: 2.4.1 | B73: Reinforcement Steel | C73: MT | D73: ='Concrete & Steel Summary'!I60 -> 4042.0087 | E73: 73999.65 | F73: =IF(D73="QRO",0,D73*E73) -> 2.9910723e+08
B74: Providing and fixing Mechanical Splicing using threaded coupler to the reinforcement bars of specified dia and grade using high yield strength standard couplers of specially produced steel to join ribbed bearing bars machine cut end to end. Cost to include necessary supply of threaded couplers of various diameters, reducers wherever required, transportation, coupling at site by mechanical means, threading of reinforcement bars at ends, erection at site, testing of random samples, testing at site, protection of threaded ends using PVC covers etc.., complete. Cost to include necessary testing of joints at site using ultrasonic methods required by Consultants at intervals. | F74: =IF(D74="QRO",0,D74*E74) -> 0
A75: a | B75: Y40 | C75: Nos | D75: QRO | E75: 220 | F75: =IF(D75="QRO",0,D75*E75) -> 0
A76: b | B76: Y32 | C76: Nos | D76: QRO | E76: 160 | F76: =IF(D76="QRO",0,D76*E76) -> 0
A77: c | B77: Y25 | C77: Nos | D77: QRO | E77: 105 | F77: =IF(D77="QRO",0,D77*E77) -> 0
A78: d | B78: Y20 | C78: Nos | D78: QRO | E78: 80 | F78: =IF(D78="QRO",0,D78*E78) -> 0
B79: RCC Total | F79: =SUM(F21:F78) -> 7.3157298e+08
A81: 3 | B81: Masonry works
B82: Providing, supplying & fixing in position , receive, unload, Inspect / Test in Accredited by NABL & approved laboratory & Construct AAC block of various thickness, level as per drawing, compressive strength of block shall be minimum 4.0 N/mm2 Grade 1 with density 551 to 650 kg/m3 and Water absorption less than 20%. Fixing of block shall be in adhesive with thickness as per adhesive manufacturer's specification and also providing RCC stiffener (patli) beam of wall width x 100 mm at about 1.2m C/C with 4 nos. 8 mm die Tor bars and 8 mm dia links at 300 c/c in cement concrete of grade M 15, required formwork, curing complete with raking out joints if required, curing, doing independent double legged scaffolding, all complete as per specifications etc. at all heights, depths lift and leads and also for all shape & sizes as directed by EIC to his entire satisfaction. (Patli beam including reinforcement is part of the item). Ends of reinforcement steels in patli beam has to be anchored in RCC, including anchoring of reinforcement to min. 75mm using FOSROC Lock Fix / HILTI or Equivalent grout by the means of angle cleat with dash fastener. Patli mentioned is applicable for all thickness masonry wall. If applicable Vertical Stiffeners (Mullion Columns) minimum M-15 grade to be provided every 4m of 100mm thick wall (precast mullions are also allowed). Providing DPC layer of 50mm thk Provision and making of Control joints & its treatment as per manufacturer's Specification which shall be approved . RCC-Masonry junction should be filled with the same non-shrinking polymer mortar and 150mm wide GI expanded metal mesh shall be fixed as per approved work procedure. Please refer Tender Document, Preamble to BOQ, Standard Conditions of Contract, Technical Specifications, All annexures attached in Tender Document etc. as these all shall be considered in Rates Quoted in BOQ. 1. Lintel for Door & Window opening shall be as per the drawing or as specified. 3. Sill for Windows shall be minimum 75 mm thick with nominal reinforcement, bearing for the sill shall be minimum 200mm or nearest RCC. (Rates include material+labour,tranportation+wastage etc) | F82: =IF(D82="QRO",0,D82*E82) -> 0
A83: 3.1 | B83: 230mm thick AAC block | C83: Sqm | D83: QRO | F83: =IF(D83="QRO",0,D83*E83) -> 0
A84: =A83+0.1 -> 3.2 | B84: 200mm thick AAC block | C84: Sqm | D84: QRO | F84: =IF(D84="QRO",0,D84*E84) -> 0
A85: =A84+0.1 -> 3.3 | B85: 150mm thick AAC block | C85: Sqm | D85: ='Blockwork & Plaster & Painting'!G3 -> 13162.24 | E85: 1728.32 | F85: =IF(D85="QRO",0,D85*E85) -> 22748563
A86: =A85+0.1 -> 3.4 | B86: 100mm thick AAC block | C86: Sqm | D86: QRO | F86: =IF(D86="QRO",0,D86*E86) -> 0
B87: Block Work Total | F87: =SUM(F82:F86) -> 22748563
A89: 4 | B89: Internal Plaster
B90: Providing and applying rough Back-coat plastering of required thickness to RCC / masonry walls in CM 1:4 as a backing coat plaster with chat coat for fixing of tiles, granite slabs, marbles etc., at all levels. The work shall include hacking on RCC & Block work & Providing and fixing of 150 mm wide GI plaster mesh of Arpitha or equivalent approved make with nominal thickness of individual thread 0.35mm with a Zinc coating of 120 gms. per Sq.m. at the junctions of masonry & RCC work, plastering the mesh in CM 1:2 including tying in position with suitable nails/screws etc., hack aid chemical compound hacking to RCC surfaces, scraping, cleaning the surface, rounding of corners wherever required and specified, forming grooves wherever necessary, curing, cost of materials, labour, loading and unloading , transportation, necessary scaffolding, all other incidental charges with all leads and lifts, etc. complete as per drawings, specifications, etc. The work shall be carried out up to all heights & all floor levels and as per the directions of the Engineer In charge. The Quoted rate to include providing plastering & necessary patch works with GI / glass fiber Mesh in masonry walls over conduits/pipes etc. embedded in masonry and after final fixing of electrical Switch boxes & junction boxes to required line & levels with proper cleaning. Plastering sand shall be conforming to IS 1542 & ITP. Cement shall be OPC 43 grade or PPC which confirms to IS 269-2015 & IS 1489. plastering shall confirms to IS 1661. The acceptance criteria for plaster works shall be as per technical specification and Approved method Statement. Note: 1.plaster mesh nailing with washers shall be done at 600mm c/c staggered distance 2. mortar mixing shall be only mechanical Locations -All Floor Toilet and Kitchen Area | F90: =IF(D90="QRO",0,D90*E90) -> 0
A91: 4.1 | B91: Back Coat Plaster-10 to 12mm Thk | C91: Sqm | D91: ='Cost Sheet Tower'!G19 -> 23086.989 | E91: 569 | F91: =IF(D91="QRO",0,D91*E91) -> 13136497
A92: =+A91+0.1 -> 4.2 | B92: Back Coat Plaster-8 to 10mm Thk | C92: Sqm | D92: QRO | E92: 552 | F92: =IF(D92="QRO",0,D92*E92) -> 0
B93: Providing and applying of single coat cement sand plaster of required thickness Internal masonry/RCC Wall surface mixed mechanically (one bag mixture) including racking out junctions of masonry and concrete and other dissimilar materials, treated by pointing and grouting using non-shrinking compound, then providing 150 mm wide GI plaster mesh of Arpitha or equivalent approved make with nominal thickness of individual thread 0.35mm with a Zinc coating of 120 gms. per Sq.m. at the junctions of masonry & RCC work, hacking of 72 nos/sft closely for concrete surfaces & AAC blocks ,etc. Item also include plastering to window sills, RCC cornices, making wattas, drip moulds, grooves etc. curing, cleaning, scaffolding, etc. all complete no holes are allowed to be made in block work c. Plastering sand shall be conforming to IS 1542 & approved ITP. The acceptance criteria for plaster works shall be as per technical specification and Approved method Statement. Cement shall be OPC 43 grade or PPC which confirms to IS 269-2015 & IS 1489. plastering shall confirms to IS 1661 Note: 1.plaster mesh nailing with washers shall be done at 600mm c/c staggered distance | F93: =IF(D93="QRO",0,D93*E93) -> 0
A94: 4.2 | B94: Internal Plaster 10-12mm Thk-Wall | C94: Sqm | D94: ='Cost Sheet Tower'!G17 -> 5229.288 | E94: 599 | F94: =IF(D94="QRO",0,D94*E94) -> 3132343.5
A95: 4.3 | B95: Internal Plaster 10-12mm Thk-Ceiling | C95: Sqm | D95: QRO | E95: 607 | F95: =IF(D95="QRO",0,D95*E95) -> 0
A96: 4.4 | B96: Internal Plaster 12-15mm Thk | C96: Sqm | D96: QRO | E96: 641 | F96: =IF(D96="QRO",0,D96*E96) -> 0
B97: Providing and applying Gypsum plaster of required thickness on Masonry & RCC surface as per manufacturers' specifications (surface acceptable to the EIC must be achieved by the contractor), including surface preparation, providing and fixing 145 GSM Glass Fiber mesh with opening size 5mm x 5mm at junction of RCC and masonry surface also electrical conduit chasing surfaces, surface finish shall be in right angle and plumb. With all required consumables, labour, double legged scaffolding, shifting of material, cleaning and protecting till the handing over of site to the respective agency, all complete to entire satisfaction of the EIC. Note: 1) Mixing to be carried out by mechanical / electrical stirrer only. 2) Physical and chemical tests of Gypsum shall be carried out for the first lot as per IS 2542, 2547 (latest revision) | F97: =IF(D97="QRO",0,D97*E97) -> 0
A98: 4.5 | B98: Gypsum Plaster 6 to 8mm Thk Location- All floors Internal Walls | C98: Sqm | D98: QRO | E98: 400.42 | F98: =IF(D98="QRO",0,D98*E98) -> 0
A99: 4.6 | B99: Gypsum Plaster avg 12mm Thk Wall | C99: Sqm | D99: ='Cost Sheet Tower'!G35 -> 51990.327 | E99: 452.09 | F99: =IF(D99="QRO",0,D99*E99) -> 23504307
A100: 4.7 | B100: 8mm thk Gypsum Plaster Ceiling | C100: Sqm | D100: ='Cost Sheet Tower'!G36 -> 22443.66 | E100: 413.34 | F100: =IF(D100="QRO",0,D100*E100) -> 9276862.4
B101: Internal Plaster Total | F101: =SUM(F90:F100) -> 49050010
A103: 5 | B103: External Plaster
B104: Providing and applying average 25 mm thick double coat "Cement River Sand" mixed with integral waterproofing compound and cellulose / polypropylene fibres and graded sand, first coat to be avg. 15 mm thick with 1:6 ratio and second coat to be avg 10 mm with 1:4 ratio thick as per recommendations of the approved manufacturer in both coats, and sand face finished or as required to receive specified architectural external finish, to correct line, plumb and level to external faces of walls, soffits / ceiling if any, including raking of joints, treated by pointing and grouting using non-shrinking compound mixed mortar and further grouted with fresh cleaned square cut aggregate at junction, then providing 150 mm wide 18 gauge GI chicken mesh at treated junctions of masonry work fixed with U Clamps and then apply a scratch coat plaster to create sound durable key for receiving plaster. Level Pads to be provided at periodical intervals. Min. curing period for both first coat and second coat shall be 7 days. Rate to include independent double legged Steel / H Frame scaffolding etc. Item also include plastering to precast concrete window sills, RCC cornices, making wattas, drip moulds, pattas, grooves etc.,curing as per manufacturer specification, cleaning, etc. all complete to the approval of the EIC. the work to be carried out strictly in line with approved method statement and technical Specification and as directed by EIC within tolerance limit. Note: 1) PPC cement to be used and river sand with maximum deleterious content not more than 5% by weight during source approval of sand, maximum silt content not more than 7% by volume during routine test on site. 2) Mixing of cement, sand etc. should be with the help of mechanical mixer only, NO manual mixing is allowed on site. 3) Plaster cubes of size 70.6 x 70.6 mm to be casted and cured as per manufacturer's specification and tested on 28 days, frequency as per approved 4) Any long term / short term crack appears on the plastered wall after completion of work or while executing painting activity that should be rectified by contractor on his own cost. Location : External walls | F104: =IF(D104="QRO",0,D104*E104) -> 0
...

Sheet Civil BOQ (Punit Rates R2)
A1: Form A-1 Schedule of Quantities & Prices
A2: Sr.No | B2: Description | C2: UOM | D2: Quantity | E2: Rate | F2: Total Amount
A3: 1 | B3: Excavation and Backfilling
B4: Rate includes removal of all kinds of vegetation, small shrubs etc. Dewatering water to be let out of the building area through proper pipes & channels if required. The contractor at his own expenses shall water very well, ram and thoroughly, consolidate the bottom of all excavations & ground before the construction of foundation/footing/plinth beam, filling in basement floor or other work is commenced. The rate for excavation shall include for shoring sides or trenches with approved timber/steel accessories wherever necessary to prevent sides from falling including bailing or pumping out of water if necessary and include If there are any shrubs, bushes, trees, roots of the trees to be removed for min depth 5’0”. Lift & lead outside campus are to be considered to suit the local regulations. Contour level to be taken jointly with the Project Manager and prior written approval be taken before starting any excavation/ filling at every 3 / 5 mt grids for arriving at the actual quantity. Measurements for filling will be taken for consolidated thickness only .Cost to include all and necessary royalty and other permission charges required to execute the works. Unless noted otherwise measurements shall be considered to the edge of PCC only. | F4: =D4*E4 -> 0
B5: General Excavation by mechanical means in all types of soil including dense soil, disintegrated/ weathered / soft rock / Medium Rock including necessary manual excavation for dressing the edges & levelling, all leads and lifts, necessary soil stabilization pre excavation, protection etc in all types of soil except hard rock as specified and directed. The rate shall include the necessary surface preparation required for the Excavation and to its related works as specified and directed. Rate to include carting away of excavated material outside the site. Note: PCC area shall be considered for measurement Rate to include the dressing of excavated surface to be handed over from General excavation contractor to the required level. (Working space & provision of slopes if required for execution shall not be paid separately). | F5: =IF(D5="QRO",0,D5*E5) -> 0
A6: 1.1 | B6: Excavation in soil at all depth with in the plot | C6: Cum | D6: =D12 -> 9621.071 | E6: 250 | F6: =IF(D6="QRO",0,D6*E6) -> 2405267.8
B7: Excavation in soil at all depth outside the plot | C7: Cum | D7: ='Excavation Qty for BOQ'!I11-D6 -> 10379.813 | E7: 752.27 | F7: =IF(D7="QRO",0,D7*E7) -> 7808422
B8: Same as item No - 1 above but in hard rock/ boulders (Un-poclainable) by chiselling/wedging up to the required level & depth including all leads and lifts, and carting away excavated material outside the site as directed, de-watering of both ground and surface water as specified. Blasting is not allowed. Note:PCC area shall be considered for measurement (Working space & provision of slopes if required for execution shall not be paid separately. Mode of measurement shall be by joint measurements/ levels before and after excavation). | F8: =IF(D8="QRO",0,D8*E8) -> 0
A9: 1.2 | B9: Excavation in Hard rock at all depth | C9: Cum | D9: ='Excavation Qty for BOQ'!I12 -> 2222.3204 | E9: 1069.22 | F9: =IF(D9="QRO",0,D9*E9) -> 2376149.5
A10: 1.3 | B10: Manual Excavation | C10: Cum | D10: QRO | E10: 2770 | F10: =IF(D10="QRO",0,D10*E10) -> 0
B11: Backfilling with approved good quality earth in plinths, below grade slab, behind retaining wall etc. in layers not exceeding depths mentioned below, breaking clods, watering, compacting each layer with vibratory compactor (Vibratory Roller/Compactor capacity i.e. 8 to 10 Tonne) and at inaccessible places with 2 Ton Roller/Plate Compactor to achieve required proctor density mentioned below with optimum moisture content as mentioned below; dressing up embankments; if required, bailing/pumping out of water to keep site dry while backfilling; rate to includes conveyance of all materials, labour, machinery etc. complete as per direction of the EIC to his entire satisfaction. The rate is inclusive of Dewatering. Notes: (1) Field compaction: 98% for Plinth area and 95% for other areas (2) Layers thickness of filling: 150mm compacted in Plinth area filling and 200mm compacted in other filling areas (3) Field density tests: 1 test / 5 Sq.m. for each layer in plinth filling area and 1 test / 50 Sq.m. in other filling area by Sand replacement method as per IS 2720 Part 28 (Latest revision) (4) The measurement shall be for the net compacted volume of filling done. Block levels at intervals of 5 X 5 m or as directed by the Engineer shall be jointly recorded for the measurement purpose, before the start of filling. The acceptance criteria for backfilling works like formation levels, method of compaction, optimum moisture content variation etc. Complete. Please refer Tender Document, Preamble to BOQ, Standard Conditions of Contract, All annexures attached in Tender Document etc. as these all shall be considered in Rates Quoted in BOQ. Mode of Measurement - Actual Filling Area in Cum | F11: =IF(D11="QRO",0,D11*E11) -> 0
A12: 1.5 | B12: With selected excavated material available within plot. | C12: Cum | D12: ='Excavation Qty for BOQ'!I17 -> 9621.071 | E12: 166.2 | F12: =IF(D12="QRO",0,D12*E12) -> 1599022
A13: 1.6 | B13: With approved quality of earth brought from outside | C13: Cum | D13: QRO | E13: 770.06 | F13: =IF(D13="QRO",0,D13*E13) -> 0
B14: Providing and applying anti termite treatment using approved chemical, conforming to IS 6313 part II (Latest Revision) and approved Method Statement using chemical at 5ltr/sqm of application area or as per manufacture recommendation that shall create a chemical barrier under and around the foundation pits, along external perimeter of building, surroundings of pipes, conduits, etc.; all complete and conforming to specifications and/ or as per approved manufacturer's instructions/recommendation, initial level supervision and application by manufacturer's approved agency with a guarantee of 10 years by Manufacturer and Contractor, all to the satisfaction of the EIC. (Plinth area in plan at ground level shall be measured as per IS 3861). Commencement of work shall be done as per approved method statement. Area at plinth level will be considered for payment.. (Rates include material+labour,tranportation+wastage etc) | F14: =IF(D14="QRO",0,D14*E14) -> 0
A15: 1.7 | B15: Anti Termite | C15: Sqm | D15: =Excavation!I14 -> 2077.24 | E15: 96.95 | F15: =IF(D15="QRO",0,D15*E15) -> 201388.42
A16: 1.8 | B16: Providing and applying two component coal-tar based epoxy protective coating of approved manufacture to be applied externally on concrete surfaces directly in contact with soil, following manufactures specification as directed by EIC Mode of Measurment:Actual Area of Application | C16: Sqm | D16: QRO | F16: =IF(D16="QRO",0,D16*E16) -> 0
B17: Providing and laying in position minimum 230mm thick Soling, base preparation by Mechanical compaction, using deccan trap basalt hand broken / Rubble for void filling, murrum for binding including watering,packing,compaction etc. in under floor, foundation, pavement, roads, steps, ramps, soak pit and other similar locations, hand set vertically in regular lines, interstices filled in with smaller stone chips including watering and Compaction / consolidating & finishing to the required levels and lines etc with mechanical rammer / manual compaction etc. complete as directed by EIC and as mentioned in Specification and drawing, etc Complete. (Binding layer shall be of metal, sand or murrum which shall be part of Rate quoted). Please refer Tender Document, Preamble to BOQ, Standard Conditions of Contract, All annexures attached in Tender Document etc. as these all shall be considered in Rates Quoted in BOQ.(Rates include material+labour,tranportation+wastage etc) | F17: =IF(D17="QRO",0,D17*E17) -> 0
A18: 1.9 | B18: Soling | C18: Cum | D18: =(D53/0.2)*0.23 -> 726.08636 | E18: 2491.62 | F18: =IF(D18="QRO",0,D18*E18) -> 1809131.3
B19: Excavation Total | F19: =SUM(F4:F18) -> 16199381
F20: =IF(D20="QRO",0,D20*E20) -> 0
A21: 2 | B21: RCC
A22: 2.1 | B22: READY MIX CONCRETE / CONTROLLED CONCRETE | F22: =IF(D22="QRO",0,D22*E22) -> 0
B23: Providing, batching, mixing, transporting through transit mixers, pumping and laying Reinforced Cement Concrete of specified grade at all levels and heights, elevations, projections, surfaces specified below using ordinary Portland cement of grade 53 from approved manufacturer, river sand/manufactured sand, 20mm and down size coarse aggregates, necessary admixtures approved by Consultants/as specified in the contract document, including all leads and lifts, pumping using line pump or boom placer, vibrating/ compaction, scaffolding wherever necessary, curing, treatment of construction joints, necessary co-ordination for Post tensioning works if any etc. complete as directed by the EIC, excluding cost of shuttering and centering. The cost shall include any additional enhancers required to make the concrete more durable or to achieve the strength as per instruction of structural consultant. All necessary treatment to honey combed areas, uneven concrete surfaces shall be made proper as per the structural consultant without any extra cost | F23: =IF(D23="QRO",0,D23*E23) -> 0
B24: (Design mix shall be as approved by the Structural Consultant / Employers representative.) | F24: =IF(D24="QRO",0,D24*E24) -> 0
B25: Providing and laying specified Grade concrete for P.C.C. of specified thick wherever specified using Manufactured sand, 20mm and downsize metal including base preparation, Compaction, levelling, all leads and lifts, curing and shuttering if necessary etc., Complete | F25: =IF(D25="QRO",0,D25*E25) -> 0
A26: 2.1.1 | B26: M15-PCC Outsourced RMC plant. | C26: Cum | D26: ='Concrete & Steel Summary'!D84 -> 683.614 | E26: 8939.31 | F26: =IF(D26="QRO",0,D26*E26) -> 6111037.5
A27: 2.1.2 | B27: M20-PCC Outsourced RMC plant. | C27: Cum | D27: QRO | E27: 10175.44 | F27: =IF(D27="QRO",0,D27*E27) -> 0
A28: 2.1.3 | B28: M10- Lean Mix Outsourced RMC plant. | C28: Cum | D28: QRO | E28: 8033 | F28: =IF(D28="QRO",0,D28*E28) -> 0
B29: Providing and laying 0f M20 grade concrete for Plum concrete wherever specified using manufactured sand, 40mm and down size metal and boulders of 150mm (proportion 60: 40 for boulder : Concrete ) of approved design mix including sub grade preparation, levelling, surface preparation, all leads and lifts, rough finishing at the top surface, curing and shuttering if necessary etc. | F29: =IF(D29="QRO",0,D29*E29) -> 0
A30: 2.1.4 | B30: Plum Concrete Outsourced RMC plant. | C30: Cum | D30: ='Excavation Qty for BOQ'!I20 -> 108.0832 | E30: 7509.02 | F30: =IF(D30="QRO",0,D30*E30) -> 811598.91
B31: Providing and Laying approved design mix of concrete for Reinforced Cement Concrete (RCC) work confirming to IS 456 and as specified in drawing and technical specifications. Rate shall include the following :- Handling and transportation, labour, plant & tools, mechanical mixing, placing to required location by hoisting and / or pumping, lubrication of concrete pump line and mechnical vibration, compaction, finishing, curing by any means like by portable water and / or curing compound etc. scaffolding, dewatering, if any hacking of concrete surface wherever required etc. post concrete laitance and slurry removal, making concrete form finish complete at all floors, height and levels as directed by EIC. Forming projections, sinking of floors for sumps wherever directed, forming opening or niches, opening for services and providing dowel bars and also co-ordinating with other agencies for laying conduits, boxes, pipes, clamps etc. as directed at site and making sure they do not get damaged or chocked during concreting. Forming construction joints / expansion strips as directed by the EIC including keys, slopes, falls, temporary stops etc. complete. Any approved make admixture confirming to IS 9103, the contractor may use in order to enhance the workability / properties, any cost towards making concrete water-tight and crack free shall be the part of the item and no extra claim shall be entertained to achieve the same. This rate shall exclude the cost of formwork, shuttering and steel reinforcement. The cost of the testing has to borne by the concractor and no extra claim will be entertained on this account. Location :- Raft/ Foundation
A32: 2.1.5 | B32: M50 from Inhouse RMC plant. | C32: Cum | D32: ='Concrete & Steel Summary'!D66 -> 6165.605 | E32: =11531.51-300 -> 11231.51 | F32: =IF(D32="QRO",0,D32*E32) -> 69249054
A33: 2.1.6 | B33: M50 from Outsourced RMC plant. | C33: Cum | D33: QRO | E33: 11531.51 | G33: Basic Cement Rate
B34: Providing and Laying approved design mix of concrete for Reinforced Cement Concrete (RCC) work confirming to IS 456 and as specified in drawing and technical specifications. Rate shall include the following :- Handling and transportation, labour, plant & tools, mechanical mixing, placing to required location by hoisting and / or pumping, lubrication of concrete pump line and mechnical vibration, compaction, finishing, curing by any means like by portable water and / or curing compound etc. scaffolding, dewatering, if any hacking of concrete surface wherever required etc. post concrete laitance and slurry removal, making concrete form finish complete at all floors, height and levels as directed by EIC. Forming projections, sinking of floors for sumps wherever directed, forming opening or niches, opening for services and providing dowel bars and also co-ordinating with other agencies for laying conduits, boxes, pipes, clamps etc. as directed at site and making sure they do not get damaged or chocked during concreting. Forming construction joints / expansion strips as directed by the EIC including keys, slopes, falls, temporary stops etc. complete. Any approved make admixture confirming to IS 9103, the contractor may use in order to enhance the workability / properties, any cost towards making concrete water-tight and crack free shall be the part of the item and no extra claim shall be entertained to achieve the same. This rate shall exclude the cost of formwork, shuttering and steel reinforcement. The cost of the testing has to borne by the concractor and no extra claim will be entertained on this account. Columns may be free standing or integrated with shear / lift walls, they may be floating on or hanging from beams, rectangular, T shaped, L shaped or square columns, pedestral or stup columns, composite columns, butteress for retaining wall of different sizes and shapes at various levels / heights.
A35: 2.1.5 | B35: Column | F35: =IF(D35="QRO",0,D35*E35) -> 0
B36: M60 Inhouse RMC plant. | C36: Cum | D36: QRO | F36: =IF(D36="QRO",0,D36*E36) -> 0
B37: M60 Outsourced RMC plant. | C37: Cum | D37: QRO | F37: =IF(D37="QRO",0,D37*E37) -> 0
B38: M50 Inhouse RMC plant. | C38: Cum | D38: ='Concrete & Steel Summary'!D70 -> 9560.372 | E38: =11531.51-300 -> 11231.51 | F38: =IF(D38="QRO",0,D38*E38) -> 1.0737741e+08
B39: M50 Outsourced RMC plant. | C39: Cum | D39: QRO | E39: =11531.51 -> 11531.51
B40: M40 Inhouse RMC plant. | C40: Cum | D40: QRO | E40: =E41-300 -> 10404.48 | F40: =IF(D40="QRO",0,D40*E40) -> 0
B41: M40 Outsourced RMC plant. | C41: Cum | D41: QRO | E41: 10704.48
A42: 2.1.6 | B42: Retaining Wall
B43: M50 Inhouse RMC plant. | C43: Cum | D43: ='Concrete & Steel Summary'!D67 -> 336.4548 | E43: =E38 -> 11231.51 | F43: =IF(D43="QRO",0,D43*E43) -> 3778895.5
B44: M50 Outsourced RMC plant. | C44: Cum | D44: QRO | E44: =E43 -> 11231.51
A45: 2.1.7 | B45: UGT, OHT, LMR, Swimming Pool and Parapet Wall
B46: M30 Inhouse RMC plant. | C46: Cum | D46: QRO | E46: =E47-300 -> 9676.87 | F46: =IF(D46="QRO",0,D46*E46) -> 0
B47: M30 Outsourced RMC plant. | C47: Cum | D47: QRO | E47: 9976.87
B48: M40 Inhouse RMC plant. | C48: Cum | D48: QRO | E48: =E40 -> 10404.48
B49: M40 Outsourced RMC plant. | C49: Cum | D49: QRO | E49: =E41 -> 10704.48
B50: M50 Inhouse RMC plant. | C50: Cum | D50: ='Concrete & Steel Summary'!D68+'Concrete & Steel Summary'!D74+'Concrete & Steel Summary'!D75+'Concrete & Steel Summary'!D76+'Concrete & Steel Summary'!D77+'Concrete & Steel Summary'!D78 -> 1001.9178 | E50: =E38 -> 11231.51
B51: M50 Outsourced RMC plant. | C51: Cum | D51: QRO | E51: =E39 -> 11531.51
A52: 2.1.8 | B52: Slab
B53: M30 (Basement Grade Slab) Inhouse RMC plant. | C53: Cum | D53: ='Concrete & Steel Summary'!D69 -> 631.37944 | E53: =E46 -> 9676.87 | F53: =IF(D53="QRO",0,D53*E53) -> 6109776.8
B54: M30 (Basement Grade Slab) Outsourced RMC plant. | C54: Cum | D54: QRO | E54: =E47 -> 9976.87
B55: M40 Inhouse RMC plant. | C55: Cum | D55: ='Concrete & Steel Summary'!D73 -> 7613.6441 | E55: =E48 -> 10404.48 | F55: =IF(D55="QRO",0,D55*E55) -> 79216008
B56: M40 Outsourced RMC plant. | C56: Cum | D56: QRO | E56: =E49 -> 10704.48
B57: M50 Inhouse RMC plant. | C57: Cum | D57: QRO | E57: =E38 -> 11231.51
B58: M50 Outsourced RMC plant. | C58: Cum | D58: QRO | E58: =E51 -> 11531.51
A59: 2.1.9 | B59: Beams
B60: M30 Inhouse RMC plant. | C60: Cum | D60: QRO | E60: =E46 -> 9676.87 | F60: =IF(D60="QRO",0,D60*E60) -> 0
B61: M30 Outsourced RMC plant. | C61: Cum | D61: QRO | E61: =E47 -> 9976.87
B62: M40 Inhouse RMC plant. | C62: Cum | D62: ='Concrete & Steel Summary'!D72 -> 3946.5937 | E62: =E55 -> 10404.48 | F62: =IF(D62="QRO",0,D62*E62) -> 41062255
B63: M40 Outsourced RMC plant. | C63: Cum | D63: QRO | E63: =E56 -> 10704.48
B64: M50 Inhouse RMC plant. | C64: Cum | D64: QRO | E64: =E57 -> 11231.51 | F64: =IF(D64="QRO",0,D64*E64) -> 0
B65: M50 Outsourced RMC plant. | C65: Cum | D65: QRO | E65: =E58 -> 11531.51
A66: 2.1.10 | B66: RMC Staircase, NS Wall | C66: Cum | F66: =IF(D66="QRO",0,D66*E66) -> 0
B67: M30 Inhouse RMC plant. | C67: Cum | D67: QRO | E67: =E60 -> 9676.87 | F67: =IF(D67="QRO",0,D67*E67) -> 0
B68: M30 Outsourced RMC plant. | C68: Cum | D68: QRO | E68: =E61 -> 9976.87
B69: M40 Inhouse RMC plant. | C69: Cum | D69: ='Concrete & Steel Summary'!D71+'Concrete & Steel Summary'!D79 -> 2118.9888 | E69: =E62 -> 10404.48 | F69: =IF(D69="QRO",0,D69*E69) -> 22046977
B70: M40 Outsourced RMC plant. | C70: Cum | D70: QRO | E70: =E63 -> 10704.48
B71: M50 Inhouse RMC plant. | C71: Cum | D71: QRO | E71: =E64 -> 11231.51 | F71: =IF(D71="QRO",0,D71*E71) -> 0
B72: M50 Outsourced RMC plant.
A73: 2.2 | B73: Providing & laying 75mm thk Vacuum de-watered Trimix Flooring in M-25 grade of concrete with 12mm micro AR glass fibers (KDM FIBER or equivalent) at 85 gms per 50 kg cement, on RCC slab base at all floors and levels . The concrete shall consist of Min 325 Kg of cement per cubic meter of concrete shall be poured in the panels (size to be approx. 4.0 X 2.4 mts in alternate pattern) and vibrated with poker vibrator, followed by double beam screed vibrator. Excess water at top surface of the vibrated concrete shall be removed by Vacuum De-watering system as per the specifications to reduce final water cement ratio. Non metallic hardener as per site condition dry shake at the rate of 4.5 Kg per Sq. mt.or as specified by the manufacturer shall be spread and then the surface shall be trowelled with a power trowel to get desired final smooth finish. Grooves / Joints at the periphery of each panel shall be formed after immediate final setting of concrete with mechanized saw cut to depth of 1/3 rd thickness of the Trimix floor and shall be 3 to 4 mm wide using non metallic Hardener of approved make. These grooved shall be filled with elastomeric sealant (Bituminous / polysulphide as specified) etc. complete as per drawings & specifications and as directed by the EIC. The floor shall be cured for a period of seven days by ponding water. The acceptance criteria for trimix works shall be as per technical specification and Approved method Statement. | C73: Sqm | D73: =Tremix!E7 -> 8722.6 | E73: =1429.61 -> 1429.61 | F73: =IF(D73="QRO",0,D73*E73) -> 12469916
A74: 2.3 | B74: Formwork | F74: =IF(D74="QRO",0,D74*E74) -> 0
B75: Providing, fabricating & erecting aluminium system form work at all levels and places wherever needed / specified including striking / deshuttering, cleaning, transporting and storing at all heights. All shuttering including columns, Shear Walls, core walls, curved walls, walls, curved slabs & beams, sunshades, fins facia, beam sides, drip mould, beam bottoms, suspended slab & beam, pergolas, stair cases & landing. Rate shall also be inclusive of providing necessary provision for external grooves provision shall be given as per the Approved GFC drawing , internal skirting arrangement as required by drawings. Including Grouting for tie rods in mivan shuttering shall be with GP2 internally as well as externally for the depth of entire thickness of RCC member as per manufacture specification approved by consultants. Only the surface area of the form work to be measured. | F75: =IF(D75="QRO",0,D75*E75) -> 0
B76: Aluminium Shuttering brought to the site shall be Brand New. The approved vendor for Aluminium Shuttering are 1) Storm, 2) MFE, 3)Kum Kang. If control plans for staggered concreting the additional stuttering shall be planned in construction Joint area. Inclined shall be provided for wall thickness more than 200mm Note: QA/QC1. Mock up approval is required well in advance for aluminium formwork finish prior to actual work starts. 2. Grouting of tie rod holes required for entire thickness of RCC member instead. | F76: =IF(D76="QRO",0,D76*E76) -> 0
A77: 2.3.1 | B77: Al. Shuttering for Columns, Beams, Slabs, structural & non structural walls staircases, chajjas etc. | C77: Sqm | D77: ='Shuttering Summary'!C4 -> 119624.04 | E77: 705.96 | F77: =IF(D77="QRO",0,D77*E77) -> 84449790
A78: 2.3.2 | B78: Reckli/ Moulding charges over and above the cost of shuttering works | C78: Sqm | D78: QRO | E78: 1385 | F78: =IF(D78="QRO",0,D78*E78) -> 0
A79: 2.3.4 | B79: CONVENTIONAL SHUTTERING : Providing, fabricating and erecting form work at all levels and places and profiles wherever needed/specified as per drawing including striking with 12mm Brand new Plastic coated, marine resistant waterproof ply/Smooth finished MS plates with adjustable steel props of acceptable Staging system and with sufficient bracing as approved by consultant. M.S. plates shall be considered for foundation only. Cost to include designing of proper form work and staging system to suit the requirements, Submission of design calculations and shop drawings for approval, sealing the joints with heavy duty brown self adhesive tape, aligning to line and levels including M.S. Ties, PVC Spacer, Providing openings/ cutouts/ pockets, necessary co-ordination and arrangement for Post Tensioning works if any, applying deshuttering chemical, Deshuttering as approved by the consultant etc., complete at all levels, double/triple heights, profiles, elevations/surfaces. Rate shall also be inclusive for packing tie rod holes with GP2 or other approved chemicals. Note : Only plan area shall be considered. No extra shall be paid for Side shuttering of Drop panel/column capitals. 3) Shuttering & deshuttering sequence shall be 100% ,80% & 40% from the slab to be cast respectively. The cost of shuttering includes all slopes as per details provided in the architectural drawings. Note: Tie rods shall not be used for entire thickness of water retaining structures and retaining wall . Alternatively gugu rods shall be used which breaks through and through hole. | C79: Sqm | D79: ='Shuttering Summary'!C3 -> 51310.247 | E79: 832.39 | F79: =IF(D79="QRO",0,D79*E79) -> 42710137
A80: 2.4 | B80: Reinforcement Steel
B81: Providing, supplying & fixing in position Fe 500 reinforcement steel for RCC work with high yield strength ribbed cold twisted tor steel (HSD) bar of various diameters and grade of steel as specified below conforming to IS specification including cutting, providing, supplying & bending, hoisting, and placing in position according to drawings and binding the reinforcement with galvanized annealed binding wire of double fold of 18 gauge and providing concrete cover blocks/PVC Cover Blocks required with strength equal to respective concrete grades. as required/instructed for placing the reinforcements in position and for maintaining the cover specified and/or according to relevant IS. | F81: =IF(D81="QRO",0,D81*E81) -> 0
B82: Note : Unless noted otherwise the measurements is accordance with IS 2502. However reinforcement shall be measured only in lengths of bars as actually placed in position on standard weight basis, no allowance being made in the weight for rolling margin. Authorized laps and splices only will be measured. Chairs of any shape & profile, Spacer bar of any shape & profile, cover block, wastage and binding wire will not be measured and shall be included in the quoted rates. Quoted rate shall be deemed to have considered the above stipulation. Quoted rate to include lead, unloading, lift, placing at all levels and as directed. | F82: =IF(D82="QRO",0,D82*E82) -> 0
A83: 2.4.1 | B83: Reinforcement Steel | C83: MT | D83: ='Concrete & Steel Summary'!I60 -> 4042.0087 | E83: 89912.86 | F83: =IF(D83="QRO",0,D83*E83) -> 3.6342856e+08
B84: Providing and fixing Mechanical Splicing using threaded coupler to the reinforcement bars of specified dia and grade using high yield strength standard couplers of specially produced steel to join ribbed bearing bars machine cut end to end. Cost to include necessary supply of threaded couplers of various diameters, reducers wherever required, transportation, coupling at site by mechanical means, threading of reinforcement bars at ends, erection at site, testing of random samples, testing at site, protection of threaded ends using PVC covers etc.., complete. Cost to include necessary testing of joints at site using ultrasonic methods required by Consultants at intervals. | F84: =IF(D84="QRO",0,D84*E84) -> 0
A85: a | B85: Y40 | C85: Nos | D85: QRO | E85: 380.88 | F85: =IF(D85="QRO",0,D85*E85) -> 0
A86: b | B86: Y32 | C86: Nos | D86: QRO | E86: 325.48 | F86: =IF(D86="QRO",0,D86*E86) -> 0
A87: c | B87: Y25 | C87: Nos | D87: QRO | E87: 242.38 | F87: =IF(D87="QRO",0,D87*E87) -> 0
A88: d | B88: Y20 | C88: Nos | D88: QRO | E88: 207.75 | F88: =IF(D88="QRO",0,D88*E88) -> 0
B89: RCC Total | F89: =SUM(F22:F88) -> 8.3882142e+08
A91: 3 | B91: Masonry works
B92: Providing, supplying & fixing in position , receive, unload, Inspect / Test in Accredited by NABL & approved laboratory & Construct AAC block of various thickness, level as per drawing, compressive strength of block shall be minimum 4.0 N/mm2 Grade 1 with density 551 to 650 kg/m3 and Water absorption less than 20%. Fixing of block shall be in adhesive with thickness as per adhesive manufacturer's specification and also providing RCC stiffener (patli) beam of wall width x 100 mm at about 1.2m C/C with 4 nos. 8 mm die Tor bars and 8 mm dia links at 300 c/c in cement concrete of grade M 15, required formwork, curing complete with raking out joints if required, curing, doing independent double legged scaffolding, all complete as per specifications etc. at all heights, depths lift and leads and also for all shape & sizes as directed by EIC to his entire satisfaction. (Patli beam including reinforcement is part of the item). Ends of reinforcement steels in patli beam has to be anchored in RCC, including anchoring of reinforcement to min. 75mm using FOSROC Lock Fix / HILTI or Equivalent grout by the means of angle cleat with dash fastener. Patli mentioned is applicable for all thickness masonry wall. If applicable Vertical Stiffeners (Mullion Columns) minimum M-15 grade to be provided every 4m of 100mm thick wall (precast mullions are also allowed). Providing DPC layer of 50mm thk Provision and making of Control joints & its treatment as per manufacturer's Specification which shall be approved . RCC-Masonry junction should be filled with the same non-shrinking polymer mortar and 150mm wide GI expanded metal mesh shall be fixed as per approved work procedure. Please refer Tender Document, Preamble to BOQ, Standard Conditions of Contract, Technical Specifications, All annexures attached in Tender Document etc. as these all shall be considered in Rates Quoted in BOQ. 1. Lintel for Door & Window opening shall be as per the drawing or as specified. 3. Sill for Windows shall be minimum 75 mm thick with nominal reinforcement, bearing for the sill shall be minimum 200mm or nearest RCC. (Rates include material+labour,tranportation+wastage etc) | F92: =IF(D92="QRO",0,D92*E92) -> 0
A93: 3.1 | B93: 230mm thick AAC block | C93: Sqm | D93: QRO | F93: =IF(D93="QRO",0,D93*E93) -> 0
A94: =A93+0.1 -> 3.2 | B94: 200mm thick AAC block | C94: Sqm | D94: QRO | F94: =IF(D94="QRO",0,D94*E94) -> 0
A95: =A94+0.1 -> 3.3 | B95: 150mm thick AAC block | C95: Sqm | D95: ='Blockwork & Plaster & Painting'!G3 -> 13162.24 | E95: 1685.49 | F95: =IF(D95="QRO",0,D95*E95) -> 22184824
A96: =A95+0.1 -> 3.4 | B96: 100mm thick AAC block | C96: Sqm | D96: 200 | F96: =IF(D96="QRO",0,D96*E96) -> 0
B97: Block Work Total | F97: =SUM(F92:F96) -> 22184824
A99: 4 | B99: Internal Plaster
B100: Providing and applying rough Back-coat plastering of required thickness to RCC / masonry walls in CM 1:4 as a backing coat plaster with chat coat for fixing of tiles, granite slabs, marbles etc., at all levels. The work shall include hacking on RCC & Block work & Providing and fixing of 150 mm wide GI plaster mesh of Arpitha or equivalent approved make with nominal thickness of individual thread 0.35mm with a Zinc coating of 120 gms. per Sq.m. at the junctions of masonry & RCC work, plastering the mesh in CM 1:2 including tying in position with suitable nails/screws etc., hack aid chemical compound hacking to RCC surfaces, scraping, cleaning the surface, rounding of corners wherever required and specified, forming grooves wherever necessary, curing, cost of materials, labour, loading and unloading , transportation, necessary scaffolding, all other incidental charges with all leads and lifts, etc. complete as per drawings, specifications, etc. The work shall be carried out up to all heights & all floor levels and as per the directions of the Engineer In charge. The Quoted rate to include providing plastering & necessary patch works with GI / glass fiber Mesh in masonry walls over conduits/pipes etc. embedded in masonry and after final fixing of electrical Switch boxes & junction boxes to required line & levels with proper cleaning. Plastering sand shall be conforming to IS 1542 & ITP. Cement shall be OPC 43 grade or PPC which confirms to IS 269-2015 & IS 1489. plastering shall confirms to IS 1661. The acceptance criteria for plaster works shall be as per technical specification and Approved method Statement. Note: 1.plaster mesh nailing with washers shall be done at 600mm c/c staggered distance 2. mortar mixing shall be only mechanical Locations -All Floor Toilet and Kitchen Area | F100: =IF(D100="QRO",0,D100*E100) -> 0
A101: 4.1 | B101: Back Coat Plaster-10 to 12mm Thk | C101: Sqm | D101: ='Cost Sheet Tower'!G19 -> 23086.989 | E101: 552.62 | F101: =IF(D101="QRO",0,D101*E101) -> 12758332
A102: =+A101+0.1 -> 4.2 | B102: Back Coat Plaster-8 to 10mm Thk | C102: Sqm | D102: QRO | E102: 513.84 | F102: =IF(D102="QRO",0,D102*E102) -> 0
...

Sheet Excavation Qty for BOQ
A1: Excavation, Backfilling & ATT
A2: Sr. No. | B2: Work/ Item Description | C2: Concrete Grade | D2: Nos | E2: Length M | F2: Width M | G2: Depth M | H2: Area Sq M | I2: Volume Cu M | J2: Rate | K2: Amount
A3: A | B3: Excavation
B4: Excavation in Soil - Plinth Area (Bldg Area) | D4: 1 | G4: 7.5 | H4: 2077.24 | I4: =PRODUCT(D4:H4) -> 15579.3 | K4: =I4*J4 -> 0
B5: Excavation in Soil - Plinth Area (Podium Area) | D5: 1 | G5: =5.9-1.8 -> 4.1 | H5: 1340.75 | I5: =PRODUCT(D5:H5) -> 5497.075 | K5: =I5*J5 -> 0
B6: Excavation - UG Tank Soil | D6: 1 | G6: 0.9 | H6: 281.75 | I6: =PRODUCT(D6:H6) -> 253.575 | K6: =I6*J6 -> 0
B7: Excavation - Lift Pit Soil | D7: 1 | G7: 2 | H7: =40.08*2 -> 80.16 | I7: =PRODUCT(D7:H7) -> 160.32 | K7: =I7*J7 -> 0
B8: Storm water drain in Soil | E8: 257.17 | F8: 1.5 | G8: 1.5 | I8: =PRODUCT(D8:H8) -> 578.6325 | K8: =I8*J8 -> 0
B9: Fire line/Electrical line in Soil | E9: 257.17 | F9: 0.6 | G9: 1 | I9: =PRODUCT(D9:H9) -> 154.302 | K9: =I9*J9 -> 0
B10: Total for Excavation | I10: =SUM(I4:I9) -> 22223.204 | K10: =SUM(K4:K9) -> 0 | M10: =I10*0.4 -> 8889.2818
B11: Total Excavation in Soil | I11: =I10*0.9 -> 20000.884
B12: Total Excavation in Rock | I12: =I10-I11 -> 2222.3204
A14: B | B14: Backfilling
B15: Murum Filling in Bldg Area above Raft | D15: 1 | G15: 2.9 | H15: =H4 -> 2077.24 | I15: =PRODUCT(D15:H15) -> 6023.996
B16: Filling in Drive way/LOS Area | D16: 1 | G16: =37.8-36.3 -> 1.5 | H16: 2398.05 | I16: =PRODUCT(D16:H16) -> 3597.075
B17: Total Backfilling with Soil within the plot | I17: =SUM(I15:I16) -> 9621.071
A19: C | B19: Plum Concrete for Edges at Level Difference
B20: Plum Concrete | E20: 84.44 | H20: =0.5*1.6*1.6 -> 1.28 | I20: =PRODUCT(D20:H20) -> 108.0832

Sheet Construction Area
A1: Project - Mulund
A2: Area Statement -Construction Area
A3: Mulund
A4: Sr.No. | B4: Description | C4: Floorplate Area (P line) | D4: Deduction | G4: Addition | P4: Total | Q4: No | R4: Total Construction Area (in Sq.m) | S4: Total Construction Area (in sq.ft)
D5: Lift Shaft | E5: MEP Shaft | F5: Void | G5: S Slab | H5: Deck /Balcony | I5: Utility/Dry Balcony | J5: Chajja | K5: Tower Area | L5: NTA Open to sky | M5: Terrace | N5: Beam for Jalli | O5: Refuge | V5: As per EC
A6: 1 | B6: Basement | C6: 3286.5 | D6: -71.26 | E6: -4.04 | F6: 0 | G6: 0 | H6: 0 | I6: 0 | J6: 0 | K6: 0 | L6: 0 | M6: 0 | N6: 0 | O6: 0 | P6: =SUM(C6:O6) -> 3211.2 | Q6: 1 | R6: =Q6*P6 -> 3211.2 | S6: =R6*10.764 -> 34565.357 | V6: =+S6 -> 34565.357
A7: 2 | B7: Ground Floor | C7: 3365.01 | D7: -71.26 | E7: -3.28 | F7: -128.74 | G7: 0 | H7: 0 | I7: 0 | J7: 0 | K7: 0 | L7: 0 | M7: 0 | N7: 0 | O7: 0 | P7: =SUM(C7:O7) -> 3161.73 | Q7: 1 | R7: =Q7*P7 -> 3161.73 | S7: =R7*10.764 -> 34032.862 | V7: =+S7 -> 34032.862
A8: 3 | B8: 1st Podium | C8: 2884.96 | D8: -71.26 | E8: -8.44 | F8: -111.23 | G8: 0 | H8: 0 | I8: 0 | J8: 7.02 | K8: 0 | L8: 0 | M8: 0 | N8: 0 | O8: 0 | P8: =SUM(C8:O8) -> 2701.05 | Q8: 1 | R8: =Q8*P8 -> 2701.05 | S8: =R8*10.764 -> 29074.102 | U8: =R7-R15 -> 1918.53 | V8: =+S8 -> 29074.102
A9: 4 | B9: 2nd Podium | C9: 2884.96 | D9: -71.26 | E9: -8.44 | F9: -142.7 | G9: 0 | H9: 0 | I9: 0 | J9: 7.02 | K9: 0 | L9: 0 | M9: 0 | N9: 0 | O9: 0 | P9: =SUM(C9:O9) -> 2669.58 | Q9: 1 | R9: =Q9*P9 -> 2669.58 | S9: =R9*10.764 -> 28735.359 | V9: =+S9 -> 28735.359
A10: 5 | B10: 3rd Podium | C10: =C9 -> 2884.96 | D10: =D9 -> -71.26 | E10: =E9 -> -8.44 | F10: -142.7 | G10: =G9 -> 0 | H10: =H9 -> 0 | I10: =I9 -> 0 | J10: =J9 -> 7.02 | K10: =K9 -> 0 | L10: =L9 -> 0 | M10: =M9 -> 0 | N10: =N9 -> 0 | O10: =O9 -> 0 | P10: =SUM(C10:O10) -> 2669.58 | Q10: 1 | R10: =Q10*P10 -> 2669.58 | S10: =R10*10.764 -> 28735.359 | V10: =+S10 -> 28735.359
A11: 6 | B11: 4th Podium | C11: 2717.55 | D11: -56.77 | E11: =E9 -> -8.44 | F11: -143.41 | G11: =G10 -> 0 | H11: =H10 -> 0 | I11: =I10 -> 0 | J11: 7.09 | K11: =K10 -> 0 | L11: =L10 -> 0 | M11: 167.4 | N11: =N10 -> 0 | O11: =O10 -> 0 | P11: =SUM(C11:O11) -> 2683.42 | Q11: 1 | R11: =Q11*P11 -> 2683.42 | S11: =R11*10.764 -> 28884.333 | V11: =+S11 -> 28884.333
A12: 7 | B12: 5th Podium | C12: 2749.87 | D12: -56.77 | E12: -13.72 | F12: -378.2 | G12: =G11 -> 0 | H12: 13.4 | I12: 12.94 | J12: 46.67 | K12: 0 | L12: 0 | M12: 0 | O12: =O11 -> 0 | P12: =SUM(C12:O12) -> 2374.19 | Q12: 1 | R12: =Q12*P12 -> 2374.19 | S12: =R12*10.764 -> 25555.781 | V12: =+S12 -> 25555.781
A13: 8 | B13: 6th Podium | C13: 2745.96 | D13: -56.77 | E13: -19.57 | F13: -202.91 | G13: 1.09 | H13: 13.4 | I13: 12.94 | J13: 46.67 | K13: =1371.78*0 -> 0 | L13: =(C13-K13)*0 -> 0 | M13: 0 | N13: 0.42 | O13: =O12 -> 0 | P13: =SUM(C13:O13) -> 2541.23 | Q13: 1 | R13: =Q13*P13 -> 2541.23 | S13: =R13*10.764 -> 27353.8 | V13: =+S14 -> 13576.418
A14: 9 | B14: 7th Floor | C14: 1359.04 | D14: -56.77 | E14: -25.27 | F14: -169.84 | G14: 1.09 | H14: 15.47 | I14: 14.45 | J14: 92.59 | K14: 0 | L14: 0 | M14: 30.1 | N14: 0.42 | O14: =221.33*0 -> 0 | P14: =SUM(C14:O14) -> 1261.28 | Q14: 1 | R14: =Q14*P14 -> 1261.28 | S14: =R14*10.764 -> 13576.418 | U14: =R15/804 -> 1.5462687 | V14: =+S14-J14*10.764 -> 12579.779
A15: 10 | B15: 8th Floor | C15: 1397.11 | D15: -56.77 | E15: -26.46 | F15: -213.67 | G15: 1.09 | H15: 22.17 | I15: 21.02 | J15: 95.99 | K15: 0 | L15: 0 | M15: 0 | N15: 2.72 | O15: 0 | P15: =SUM(C15:O15) -> 1243.2 | Q15: 1 | R15: =Q15*P15 -> 1243.2 | S15: =R15*10.764 -> 13381.805 | V15: =+S15-J15*10.764 -> 12348.568
A16: 11 | B16: 9th Floor | C16: =C15 -> 1397.11 | D16: =D15 -> -56.77 | E16: =E15 -> -26.46 | F16: =F15 -> -213.67 | G16: =G15 -> 1.09 | H16: =H15 -> 22.17 | I16: =I15 -> 21.02 | J16: =J15 -> 95.99 | ... O16: =O15 -> 0 | P16: =SUM(C16:O16) -> 1243.2 | Q16: 1 | R16: =Q16*P16 -> 1243.2 | S16: =R16*10.764 -> 13381.805 | V16: =+S16-J16*10.764 -> 12348.568
A17: 12 | B17: 10th Floor | C17: =C16 -> 1397.11 | D17: =D16 -> -56.77 | E17: =E16 -> -26.46 | F17: =F16 -> -213.67 | G17: =G16 -> 1.09 | H17: =H16 -> 22.17 | I17: =I16 -> 21.02 | J17: =J16 -> 95.99 | ... N17: =N16 -> 2.72 | O17: 0 | P17: =SUM(C17:O17) -> 1243.2 | Q17: 1 | R17: =Q17*P17 -> 1243.2 | S17: =R17*10.764 -> 13381.805 | V17: =+S17-J17*10.764 -> 12348.568
A18: 13 | B18: 11th Floor | C18: =C17 -> 1397.11 | D18: =D17 -> -56.77 | E18: =E17 -> -26.46 | F18: =F17 -> -213.67 | G18: =G17 -> 1.09 | H18: =H17 -> 22.17 | I18: =I17 -> 21.02 | J18: =J17 -> 95.99 | ... N18: =N17 -> 2.72 | O18: 0 | P18: =SUM(C18:O18) -> 1243.2 | Q18: 1 | R18: =Q18*P18 -> 1243.2 | S18: =R18*10.764 -> 13381.805 | V18: =+S18-J18*10.764 -> 12348.568 | AA18: =1630*9 -> 14670
A19: 14 | B19: 12th Floor | C19: =C18 -> 1397.11 | D19: =D18 -> -56.77 | E19: =E18 -> -26.46 | F19: =F18 -> -213.67 | G19: =G18 -> 1.09 | H19: =H18 -> 22.17 | I19: =I18 -> 21.02 | J19: =J18 -> 95.99 | ... N19: =N18 -> 2.72 | O19: 0 | P19: =SUM(C19:O19) -> 1243.2 | Q19: 1 | R19: =Q19*P19 -> 1243.2 | S19: =R19*10.764 -> 13381.805 | V19: =+S19-J19*10.764 -> 12348.568 | AA19: =+AA18*10.764 -> 157907.88
A20: 15 | B20: 13th Floor | C20: =C19 -> 1397.11 | D20: =D19 -> -56.77 | E20: =E19 -> -26.46 | F20: =F19 -> -213.67 | G20: =G19 -> 1.09 | H20: =H19 -> 22.17 | I20: =I19 -> 21.02 | J20: =J19 -> 95.99 | ... N20: =N19 -> 2.72 | O20: 0 | P20: =SUM(C20:O20) -> 1243.2 | Q20: 1 | R20: =Q20*P20 -> 1243.2 | S20: =R20*10.764 -> 13381.805 | V20: =+S20-J20*10.764 -> 12348.568 | AA20: =+AA19*1300 -> 205280244
A21: 16 | B21: 14th Floor | C21: 1410.34 | D21: -56.77 | E21: -26.46 | F21: -188.51 | G21: 1.09 | H21: 15.47 | I21: 14.5 | J21: 96.21 | K21: 0 | L21: 0 | M21: 0 | N21: 0.42 | O21: =224.19*0 -> 0 | P21: =SUM(C21:O21) -> 1266.29 | Q21: 1 | R21: =Q21*P21 -> 1266.29 | S21: =R21*10.764 -> 13630.346 | V21: =+S21-J21*10.764 -> 12594.741 | AA21: =+AA20/10^7 -> 20.528024
A22: 17 | B22: 15th Floor | C22: =C20 -> 1397.11 | D22: =D20 -> -56.77 | E22: =E20 -> -26.46 | F22: =F20 -> -213.67 | G22: =G20 -> 1.09 | H22: =H20 -> 22.17 | I22: =I20 -> 21.02 | J22: =J20 -> 95.99 | ... O22: =O20 -> 0 | P22: =SUM(C22:O22) -> 1243.2 | Q22: 1 | R22: =Q22*P22 -> 1243.2 | S22: =R22*10.764 -> 13381.805 | T22: =R22*3 -> 3729.6 | V22: =+S22-J22*10.764 -> 12348.568
A23: 18 | B23: 16th Floor | C23: =C22 -> 1397.11 | D23: =D22 -> -56.77 | E23: =E22 -> -26.46 | F23: =F22 -> -213.67 | G23: =G22 -> 1.09 | H23: =H22 -> 22.17 | I23: =I22 -> 21.02 | J23: =J22 -> 95.99 | ... O23: =O22 -> 0 | P23: =SUM(C23:O23) -> 1243.2 | Q23: 1 | R23: =Q23*P23 -> 1243.2 | S23: =R23*10.764 -> 13381.805 | V23: =+S23-J23*10.764 -> 12348.568
A24: 19 | B24: 17th Floor | C24: 1415.01 | D24: -56.77 | E24: -26.13 | F24: -170.18 | G24: 0 | H24: 30.94 | I24: 29 | J24: 94.98 | K24: 0 | L24: 0 | M24: 0 | N24: =N23 -> 2.72 | O24: 0 | P24: =SUM(C24:O24) -> 1319.57 | Q24: 1 | R24: =Q24*P24 -> 1319.57 | S24: =R24*10.764 -> 14203.851 | V24: =+S24-J24*10.764 -> 13181.487
A25: 20 | B25: 18th Floor | C25: =C24 -> 1415.01 | D25: =D24 -> -56.77 | E25: =E24 -> -26.13 | F25: =F24 -> -170.18 | G25: =G24 -> 0 | H25: =H24 -> 30.94 | I25: =I24 -> 29 | J25: =J24 -> 94.98 | ... O25: =O24 -> 0 | P25: =SUM(C25:O25) -> 1319.57 | Q25: 1 | R25: =Q25*P25 -> 1319.57 | S25: =R25*10.764 -> 14203.851 | V25: =+S25-J25*10.764 -> 13181.487
A26: 21 | B26: 19th Floor | C26: =C25 -> 1415.01 | D26: =D25 -> -56.77 | E26: =E25 -> -26.13 | F26: =F25 -> -170.18 | G26: =G25 -> 0 | H26: =H25 -> 30.94 | I26: =I25 -> 29 | J26: =J25 -> 94.98 | ... O26: =O25 -> 0 | P26: =SUM(C26:O26) -> 1319.57 | Q26: 1 | R26: =Q26*P26 -> 1319.57 | S26: =R26*10.764 -> 14203.851 | V26: =+S26-J26*10.764 -> 13181.487
A27: 22 | B27: 20th Floor | C27: =C26 -> 1415.01 | D27: =D26 -> -56.77 | E27: =E26 -> -26.13 | F27: =F26 -> -170.18 | G27: =G26 -> 0 | H27: =H26 -> 30.94 | I27: =I26 -> 29 | J27: =J26 -> 94.98 | ... O27: =O26 -> 0 | P27: =SUM(C27:O27) -> 1319.57 | Q27: 1 | R27: =Q27*P27 -> 1319.57 | S27: =R27*10.764 -> 14203.851 | V27: =+S27-J27*10.764 -> 13181.487
A28: 23 | B28: 21st Floor | C28: 1434.59 | D28: -56.77 | E28: -26.13 | F28: -145.98 | G28: 0 | H28: 24.22 | I28: 22.47 | J28: 88.39 | K28: 0 | L28: 0 | M28: 0 | N28: 0.42 | O28: =237.82*0 -> 0 | P28: =SUM(C28:O28) -> 1341.21 | Q28: 1 | R28: =Q28*P28 -> 1341.21 | S28: =R28*10.764 -> 14436.784 | V28: =+S28-J28*10.764 -> 13485.354
A29: 24 | B29: 22nd Floor | C29: =C24 -> 1415.01 | D29: =D24 -> -56.77 | E29: =E24 -> -26.13 | F29: =F24 -> -170.18 | G29: =G24 -> 0 | H29: =H24 -> 30.94 | I29: =I24 -> 29 | J29: =J24 -> 94.98 | ... O29: =O24 -> 0 | P29: =SUM(C29:O29) -> 1319.57 | Q29: 1 | R29: =Q29*P29 -> 1319.57 | S29: =R29*10.764 -> 14203.851 | V29: =+S29-J29*10.764 -> 13181.487
A30: 25 | B30: 23rd Floor | C30: =C25 -> 1415.01 | D30: -56.77 | E30: -26.13 | F30: -171.14 | G30: 0 | H30: 39.34 | I30: 28.95 | J30: 90.37 | K30: =K25 -> 0 | L30: =L25 -> 0 | M30: =M25 -> 0 | N30: 2.72 | O30: =O25 -> 0 | P30: =SUM(C30:O30) -> 1322.35 | Q30: 1 | R30: =Q30*P30 -> 1322.35 | S30: =R30*10.764 -> 14233.775 | U30: 38442 | V30: =+S30-J30*10.764 -> 13261.033
A31: 26 | B31: 24th Floor | C31: =C30 -> 1415.01 | D31: =D30 -> -56.77 | E31: =E30 -> -26.13 | F31: =F30 -> -171.14 | G31: =G30 -> 0 | H31: =H30 -> 39.34 | I31: =I30 -> 28.95 | J31: =J30 -> 90.37 | ... O31: =O30 -> 0 | P31: =SUM(C31:O31) -> 1322.35 | Q31: 1 | R31: =Q31*P31 -> 1322.35 | S31: =R31*10.764 -> 14233.775 | U31: =U30*3.5 -> 134547 | V31: =+S31-J31*10.764 -> 13261.033
A32: 27 | B32: 25th Floor | C32: =C31 -> 1415.01 | D32: =D31 -> -56.77 | E32: =E31 -> -26.13 | F32: =F31 -> -171.14 | G32: =G31 -> 0 | H32: =H31 -> 39.34 | I32: =I31 -> 28.95 | J32: =J31 -> 90.37 | ... O32: =O31 -> 0 | P32: =SUM(C32:O32) -> 1322.35 | Q32: 1 | R32: =Q32*P32 -> 1322.35 | S32: =R32*10.764 -> 14233.775 | U32: =U31*725 -> 97546575 | V32: =+S32-J32*10.764 -> 13261.033
A33: 28 | B33: 26th Floor | C33: =C32 -> 1415.01 | D33: =D32 -> -56.77 | E33: =E32 -> -26.13 | F33: =F32 -> -171.14 | G33: =G32 -> 0 | H33: =H32 -> 39.34 | I33: =I32 -> 28.95 | J33: =J32 -> 90.37 | ... O33: =O32 -> 0 | P33: =SUM(C33:O33) -> 1322.35 | Q33: 1 | R33: =Q33*P33 -> 1322.35 | S33: =R33*10.764 -> 14233.775 | V33: =+S33-J33*10.764 -> 13261.033
A34: 29 | B34: 27th Floor | C34: =C30 -> 1415.01 | D34: =D30 -> -56.77 | E34: =E30 -> -26.13 | F34: =F30 -> -171.14 | G34: =G30 -> 0 | H34: =H30 -> 39.34 | I34: =I30 -> 28.95 | J34: =J30 -> 90.37 | ... O34: =O30 -> 0 | P34: =SUM(C34:O34) -> 1322.35 | Q34: 1 | R34: =Q34*P34 -> 1322.35 | S34: =R34*10.764 -> 14233.775 | V34: =+S34-J34*10.764 -> 13261.033
A35: 30 | B35: 28th Floor | C35: 1434.59 | D35: -56.77 | E35: -26.13 | F35: -145.98 | G35: 0 | H35: 28.44 | I35: 22.47 | J35: 86.09 | K35: 0 | L35: 0 | M35: 0 | N35: 0.42 | O35: =234.42*0 -> 0 | P35: =SUM(C35:O35) -> 1343.13 | Q35: 1 | R35: =Q35*P35 -> 1343.13 | S35: =R35*10.764 -> 14457.451 | V35: =+S35-J35*10.764 -> 13530.779
A36: 31 | B36: 29th Floor | C36: =C30 -> 1415.01 | D36: =D30 -> -56.77 | E36: =E30 -> -26.13 | F36: =F30 -> -171.14 | G36: =G30 -> 0 | H36: =H30 -> 39.34 | I36: =I30 -> 28.95 | J36: =J30 -> 90.37 | ... O36: =O30 -> 0 | P36: =SUM(C36:O36) -> 1322.35 | Q36: 1 | R36: =Q36*P36 -> 1322.35 | S36: =R36*10.764 -> 14233.775 | V36: =+S36-J36*10.764 -> 13261.033
A37: 32 | B37: 30th Floor | C37: =C30 -> 1415.01 | D37: =D30 -> -56.77 | E37: =E30 -> -26.13 | F37: =F30 -> -171.14 | G37: =G30 -> 0 | H37: =H30 -> 39.34 | I37: =I30 -> 28.95 | J37: =J30 -> 90.37 | ... O37: =O30 -> 0 | P37: =SUM(C37:O37) -> 1322.35 | Q37: 1 | R37: =Q37*P37 -> 1322.35 | S37: =R37*10.764 -> 14233.775 | V37: =+S37-J37*10.764 -> 13261.033
A38: 33 | B38: 31st Floor | C38: =C30 -> 1415.01 | D38: =D30 -> -56.77 | E38: =E30 -> -26.13 | F38: =F30 -> -171.14 | G38: =G30 -> 0 | H38: =H30 -> 39.34 | I38: =I30 -> 28.95 | J38: =J30 -> 90.37 | ... O38: =O30 -> 0 | P38: =SUM(C38:O38) -> 1322.35 | Q38: 1 | R38: =Q38*P38 -> 1322.35 | S38: =R38*10.764 -> 14233.775 | V38: =+S38-J38*10.764 -> 13261.033
A39: 34 | B39: 32nd Floor | C39: =C30 -> 1415.01 | D39: =D30 -> -56.77 | E39: =E30 -> -26.13 | F39: =F30 -> -171.14 | G39: =G30 -> 0 | H39: =H30 -> 39.34 | I39: =I30 -> 28.95 | J39: =J30 -> 90.37 | ... O39: =O30 -> 0 | P39: =SUM(C39:O39) -> 1322.35 | Q39: 1 | R39: =Q39*P39 -> 1322.35 | S39: =R39*10.764 -> 14233.775 | V39: =+S39-J39*10.764 -> 13261.033
A40: 35 | B40: 33rd Floor | C40: =C30 -> 1415.01 | D40: =D30 -> -56.77 | E40: =E30 -> -26.13 | F40: =F30 -> -171.14 | G40: =G30 -> 0 | H40: =H30 -> 39.34 | I40: =I30 -> 28.95 | J40: =J30 -> 90.37 | ... O40: =O30 -> 0 | P40: =SUM(C40:O40) -> 1322.35 | Q40: 1 | R40: =Q40*P40 -> 1322.35 | S40: =R40*10.764 -> 14233.775 | V40: =+S40-J40*10.764 -> 13261.033
A41: 36 | B41: 34th Floor | C41: =C30 -> 1415.01 | D41: =D30 -> -56.77 | E41: =E30 -> -26.13 | F41: =F30 -> -171.14 | G41: =G30 -> 0 | H41: =H30 -> 39.34 | I41: =I30 -> 28.95 | J41: =J30 -> 90.37 | ... O41: =O30 -> 0 | P41: =SUM(C41:O41) -> 1322.35 | Q41: 1 | R41: =Q41*P41 -> 1322.35 | S41: =R41*10.764 -> 14233.775 | V41: =+S41-J41*10.764 -> 13261.033
A42: 37 | B42: Terrace Floor | C42: 1587.44 | D42: =D31 -> -56.77 | E42: -21.62 | F42: -145.02 | G42: 0 | H42: 0 | I42: 0 | J42: 7.09 | K42: 0 | L42: 0 | M42: 0 | N42: 0 | O42: 0 | P42: =SUM(C42:O42) -> 1371.12 | Q42: 1 | R42: =Q42*P42 -> 1371.12 | S42: =R42*10.764 -> 14758.736 | V42: =+S42-J42*10.764 -> 14682.419
A43: 38 | B43: LMR,Mumty (Floor) | C43: 384.84 | D43: 0 | E43: 0 | F43: 0 | G43: 0 | H43: 0 | I43: 0 | J43: 0 | K43: 0 | L43: 0 | M43: 0 | N43: 0 | O43: 0 | P43: =SUM(C43:O43) -> 384.84 | Q43: 1 | R43: =Q43*P43 -> 384.84 | S43: =R43*10.764 -> 4142.4178 | V43: =+S43 -> 4142.4178
A44: 39 | B44: LMR, Mumty (Roof) | C44: 384.84 | D44: 0 | E44: 0 | F44: 0 | G44: 0 | H44: 0 | I44: 0 | J44: 0 | K44: 0 | L44: 0 | M44: 0 | N44: 0 | O44: 0 | P44: =SUM(C44:O44) -> 384.84 | Q44: 1 | R44: =Q44*P44 -> 384.84 | S44: =R44*10.764 -> 4142.4178 | V44: =+S44 -> 4142.4178
A45: Total | C45: =SUM(C6:C44) -> 65332.49 | D45: =SUM(D6:D44) -> -2172.94 | E45: =SUM(E6:E44) -> -829.74 | F45: =SUM(F6:F44) -> -6488.02 | G45: =SUM(G6:G44) -> 11.99 | H45: =SUM(H6:H44) -> 875.2 | I45: =SUM(I6:I44) -> 731.38 | J45: =SUM(J6:J44) -> 2728.75 | ... S45: =SUM(S6:S44) -> 650726.75 | V45: =SUM(V6:V44) -> 608884.82
S47: =S45*400 -> 2.602907e+08
S48: 50000000
S49: =S45*6.5*54 -> 2.2840509e+08
S50: =S45/10.764*0.6*7200 -> 2.6116124e+08
S51: =SUM(S47:S50) -> 7.9985702e+08

Sheet Summary
A2: Summary Cost Estimate for Project - AVS Mulund as per DBOT
A3: Sr.No | B3: Particulars | C3: As per DBOT
C4: Total Construction Area in Sq. ft | E4: ='Construction Area'!S45 -> 650726.75
C5: Rate in Rs Per Sq Ft of CA | D5: Budget in Rs. Cr. | E5: Cost Incurred till date in Rs. Cr. | F5: Cost to Complete in Rs. Cr.
A6: 1 | B6: Preliminaries | C6: =D6*10^7/$E$4 -> 18.931488 | D6: =Preliminary!F13/10^7 -> 1.2319225 | E6: 0 | F6: =+D6-E6 -> 1.2319225
A7: 2 | B7: Civil | C7: =D7*10^7/$E$4 -> 1580.8539 | D7: =(SUM('Cost Sheet Tower'!I5:I38)/10^7)+(SUM('Cost Sheet office'!I6:I11)/10^7) -> 102.87039 | E7: 0 | F7: =+D7-E7 -> 102.87039
A8: 3 | B8: Finishing | C8: =D8*10^7/$E$4 -> 500.2137 | D8: =((SUM('Cost Sheet Tower'!I39:I99))/10^7)+((SUM('Cost Sheet office'!I13:I48)/10^7)) -> 32.550243 | E8: 0 | F8: =+D8-E8 -> 32.550243
A9: 4 | B9: MEP | C9: =D9*10^7/$E$4 -> 368.26196 | D9: =(SUM('Cost Sheet Tower'!I100:I110))/10^7 -> 23.963791 | E9: 0 | F9: =+D9-E9 -> 23.963791
A10: 5 | B10: MEP NTA | C10: =D10*10^7/$E$4 -> 114.6627 | D10: =(SUM('Cost Sheet Tower'!I111:I117))/10^7 -> 7.4614088 | E10: 0 | F10: =+D10-E10 -> 7.4614088
A11: 6 | B11: MEP EXTERNAL | C11: =D11*10^7/$E$4 -> 31.525306 | D11: =(SUM('Cost Sheet Tower'!I118:I125))/10^7 -> 2.051436 | E11: 0 | F11: =+D11-E11 -> 2.051436
A12: 7 | B12: Amenities | C12: =D12*10^7/$E$4 -> 57.888061 | D12: =Amenities!F29/10^7 -> 3.766931 | E12: 0 | F12: =+D12-E12 -> 3.766931
A13: 8 | B13: External Development | C13: =D13*10^7/$E$4 -> 71.596849 | D13: ='Cost Sheet Tower'!I127/10^7 -> 4.6589985 | E13: 0 | F13: =+D13-E13 -> 4.6589985
A14: 9 | B14: Post Construction | C14: 15 | D14: =(C14*E4)/10^7 -> 0.97609012 | E14: 0 | F14: =+D14-E14 -> 0.97609012
B15: Total | C15: =D15*10^7/$E$4 -> 2758.9339 | D15: =SUBTOTAL(9,D6:D14) -> 179.53121 | E15: =SUBTOTAL(9,E7:E13) -> 0 | F15: =SUBTOTAL(9,F6:F14) -> 179.53121
A16: 9 | B16: Escalation @ 3% | C16: =D16*10^7/$E$4 -> 82.768018 | D16: =+D15*3% -> 5.3859363 | E16: =+E15*4% -> 0 | F16: =+D16-E16 -> 5.3859363
A17: 10 | B17: Contingency @ 4% | C17: =D17*10^7/$E$4 -> 110.35736 | D17: =+D15*4% -> 7.1812484 | E17: =+E15*5% -> 0 | F17: =+D17-E17 -> 7.1812484
B18: Total construction cost excluding Taxes | C18: =D18*10^7/$E$4 -> 2952.0593 | D18: =SUBTOTAL(9,D6:D17) -> 192.09839 | E18: =SUBTOTAL(9,E7:E17) -> 0 | F18: =SUBTOTAL(9,F6:F17) -> 192.09839
A19: 11 | B19: GST 18% | C19: =D19*10^7/$E$4 -> 531.37067 | D19: =+D18*0.18 -> 34.577711 | E19: =+E18*0.18 -> 0 | F19: =+F18*0.18 -> 34.577711
B20: Total construction cost with Taxes | C20: =D20*10^7/$E$4 -> 3483.43 | D20: =SUBTOTAL(9,D6:D19) -> 226.67611 | E20: =SUBTOTAL(9,E7:E19) -> 0 | F20: =SUBTOTAL(9,F6:F19) -> 226.67611
F21: 2268500000
A23: Summary Cost Estimate for Project - AVS Mulund as per DBOT (Flats)
A24: Sr.No | B24: Particulars | C24: As per DBOT
C25: Total Construction Area in Sq. ft | E25: ='Construction Area'!S45 -> 650726.75
C26: Rate in Rs Per Sq Ft of CA | D26: Budget in Rs. Cr. | E26: Cost Incurred till date in Rs. Cr. | F26: Cost to Complete in Rs. Cr.
A27: 1 | B27: Preliminaries | C27: =D27*10^7/$E$4 -> 18.931488 | D27: =D6 -> 1.2319225 | E27: 0 | F27: =+D27-E27 -> 1.2319225 | H27: =D27+D47 -> 1.2319225 | K27: =H27=D6 -> TRUE
A28: 2 | B28: Civil | C28: =D28*10^7/$E$4 -> 1578.6902 | D28: =(SUM('Cost Sheet Tower'!I5:I38))/10^7 -> 102.72959 | E28: 0 | F28: =+D28-E28 -> 102.72959 | H28: =D28+D48 -> 102.87039 | K28: =H28=D7 -> TRUE
A29: 3 | B29: Finishing | C29: =D29*10^7/$E$4 -> 437.67624 | D29: =((SUM('Cost Sheet Tower'!I39:I99))/10^7) -> 28.480764 | E29: 0 | F29: =+D29-E29 -> 28.480764 | H29: =D29+D49 -> 32.550243 | K29: =H29=D8 -> TRUE
A30: 4 | B30: MEP | C30: =D30*10^7/$E$4 -> 368.26196 | D30: =D9 -> 23.963791 | E30: 0 | F30: =+D30-E30 -> 23.963791 | H30: =D30+D50 -> 23.963791 | K30: =H30=D9 -> TRUE
A31: 5 | B31: MEP NTA | C31: =D31*10^7/$E$4 -> 114.6627 | D31: =D10 -> 7.4614088 | E31: 0 | F31: =+D31-E31 -> 7.4614088 | H31: =D31+D51 -> 7.4614088 | K31: =H31=D10 -> TRUE
A32: 6 | B32: MEP EXTERNAL | C32: =D32*10^7/$E$4 -> 31.525306 | D32: =D11 -> 2.051436 | E32: 0 | F32: =+D32-E32 -> 2.051436 | H32: =D32+D52 -> 2.051436 | K32: =H32=D11 -> TRUE
A33: 7 | B33: Amenities | C33: =D33*10^7/$E$4 -> 57.888061 | D33: =D12 -> 3.766931 | E33: 0 | F33: =+D33-E33 -> 3.766931 | H33: =D33+D53 -> 3.766931 | K33: =H33=D12 -> TRUE
A34: 8 | B34: External Development | C34: =D34*10^7/$E$4 -> 71.596849 | D34: =D13 -> 4.6589985 | E34: 0 | F34: =+D34-E34 -> 4.6589985 | H34: =D34+D54 -> 4.6589985 | K34: =H34=D13 -> TRUE
A35: 9 | B35: Post Construction | C35: 15 | D35: =D14 -> 0.97609012 | E35: 0 | F35: =+D35-E35 -> 0.97609012 | H35: =D35+D55 -> 0.97609012 | K35: =H35=D14 -> TRUE
B36: Total | C36: =D36*10^7/$E$4 -> 2694.2328 | D36: =SUBTOTAL(9,D27:D35) -> 175.32093 | E36: =SUBTOTAL(9,E28:E34) -> 0 | F36: =SUBTOTAL(9,F27:F35) -> 175.32093
A37: 9 | B37: Escalation @ 3% | C37: =D37*10^7/$E$4 -> 80.826983 | D37: =+D36*3% -> 5.259628 | E37: =+E36*4% -> 0 | F37: =+D37-E37 -> 5.259628
A38: 10 | B38: Contingency @ 4% | C38: =D38*10^7/$E$4 -> 107.76931 | D38: =+D36*4% -> 7.0128373 | E38: =+E36*5% -> 0 | F38: =+D38-E38 -> 7.0128373
B39: Total construction cost excluding Taxes | C39: =D39*10^7/$E$4 -> 2882.8291 | D39: =SUBTOTAL(9,D27:D38) -> 187.5934 | E39: =SUBTOTAL(9,E28:E38) -> 0 | F39: =SUBTOTAL(9,F27:F38) -> 187.5934
A40: 11 | B40: GST 18% | C40: =D40*10^7/$E$4 -> 518.90923 | D40: =+D39*0.18 -> 33.766812 | E40: =+E39*0.18 -> 0 | F40: =+F39*0.18 -> 33.766812
B41: Total construction cost with Taxes | C41: =D41*10^7/$E$4 -> 3401.7383 | D41: =SUBTOTAL(9,D27:D40) -> 221.36021 | E41: =SUBTOTAL(9,E28:E40) -> 0 | F41: =SUBTOTAL(9,F27:F40) -> 221.36021
A43: Summary Cost Estimate for Project - AVS Mulund as per DBOT (Office)
A44: Sr.No | B44: Particulars | C44: As per DBOT
C45: Total Construction Area in Sq. ft | E45: ='Construction Area'!S45 -> 650726.75
C46: Rate in Rs Per Sq Ft of CA | D46: Budget in Rs. Cr. | E46: Cost Incurred till date in Rs. Cr. | F46: Cost to Complete in Rs. Cr.
A47: 1 | B47: Preliminaries | C47: =D47*10^7/$E$4 -> 0 | E47: 0 | F47: =+D47-E47 -> 0
A48: 2 | B48: Civil | C48: =D48*10^7/$E$4 -> 2.1636967 | D48: =+(SUM('Cost Sheet office'!I6:I11)/10^7) -> 0.14079753 | E48: 0 | F48: =+D48-E48 -> 0.14079753 | H48: =[1]Summary!$D$47+[2]Summary!$D$49 -> 0.14079753
A49: 3 | B49: Finishing | C49: =D49*10^7/$E$4 -> 62.537452 | D49: =+((SUM('Cost Sheet office'!I13:I48)/10^7)) -> 4.0694793 | E49: 0 | F49: =+D49-E49 -> 4.0694793 | H49: =[1]Summary!$D$48+[2]Summary!$D$50 -> 3.9673542 | K49: =H49-D49 -> -0.10212509
A50: 4 | B50: MEP | C50: =D50*10^7/$E$4 -> 0 | E50: 0 | F50: =+D50-E50 -> 0
A51: 5 | B51: MEP NTA | C51: =D51*10^7/$E$4 -> 0 | E51: 0 | F51: =+D51-E51 -> 0
A52: 6 | B52: MEP EXTERNAL | C52: =D52*10^7/$E$4 -> 0 | E52: 0 | F52: =+D52-E52 -> 0
A53: 7 | B53: Amenities | C53: =D53*10^7/$E$4 -> 0 | E53: 0 | F53: =+D53-E53 -> 0
A54: 8 | B54: External Development | C54: =D54*10^7/$E$4 -> 0 | E54: 0 | F54: =+D54-E54 -> 0
A55: 9 | B55: Post Construction | C55: 15 | E55: 0 | F55: =+D55-E55 -> 0
B56: Total | C56: =D56*10^7/$E$4 -> 64.701148 | D56: =SUBTOTAL(9,D47:D55) -> 4.2102768 | E56: =SUBTOTAL(9,E48:E54) -> 0 | F56: =SUBTOTAL(9,F47:F55) -> 4.2102768 | H56: =[1]Summary!$D$55+[2]Summary!$D$57 -> 4.1081517
A57: 9 | B57: Escalation @ 3% | C57: =D57*10^7/$E$4 -> 1.9410345 | D57: =+D56*3% -> 0.1263083 | E57: =+E56*4% -> 0 | F57: =+D57-E57 -> 0.1263083
A58: 10 | B58: Contingency @ 4% | C58: =D58*10^7/$E$4 -> 2.5880459 | D58: =+D56*4% -> 0.16841107 | E58: =+E56*5% -> 0 | F58: =+D58-E58 -> 0.16841107
B59: Total construction cost excluding Taxes | C59: =D59*10^7/$E$4 -> 69.230229 | D59: =SUBTOTAL(9,D47:D58) -> 4.5049962 | E59: =SUBTOTAL(9,E48:E58) -> 0 | F59: =SUBTOTAL(9,F47:F58) -> 4.5049962
A60: 11 | B60: GST 18% | C60: =D60*10^7/$E$4 -> 12.461441 | D60: =+D59*0.18 -> 0.81089931 | E60: =+E59*0.18 -> 0 | F60: =+F59*0.18 -> 0.81089931
B61: Total construction cost with Taxes | C61: =D61*10^7/$E$4 -> 81.69167 | D61: =SUBTOTAL(9,D47:D60) -> 5.3158955 | E61: =SUBTOTAL(9,E48:E60) -> 0 | F61: =SUBTOTAL(9,F47:F60) -> 5.3158955
D64: =D18*10^7 -> 1.9209839e+09 | E64: =6.15*E4*54*1.05 -> 2.2691167e+08 | F64: Steel
E65: =E4*0.05*7200*1.03 -> 2.4128948e+08 | F65: Concrete
E66: =E4*550 -> 3.5789971e+08 | F66: Shuttering and Labour
E67: =SUM(E64:E66) -> 8.2610086e+08
E68: =5*10^7 -> 50000000
E69: =SUM(E67:E68) -> 8.7610086e+08
E70: =SUM(D8:D14)*10^7 -> 7.5428898e+08
E71: =E69+E70 -> 1.6303898e+09
E72: =E71/E4 -> 2505.4907

Sheet Cost Sheet Tower
A2: Detailed Cost Estimate
E3: CA | G3: ='Construction Area'!S45 -> 650726.75 | H3: Sft
A4: Sr. No | B4: Description | C4: Rate Psf of Const Area | D4: % Completed | E4: Balance % | F4: Unit | G4: Quantity | H4: Rate | I4: Total Cost | J4: Cost till date | K4: Balance Cost | L4: Consumption
A5: SHELL AND CORE | B5: Excavation | C5: =I5/$G$3 -> 16.074129 | D5: 0 | E5: =+(1-D5) -> 1 | F5: Cu M | G5: =Excavation!I12 -> 22223.204 | H5: =I5/G5 -> 470.67314 | I5: =Excavation!K12 -> 10459865 | J5: =+I5*D5 -> 0 | K5: =+E5*I5 -> 10459865
B6: Shore Piling | C6: =I6/$G$3 -> 19.728638 | D6: 0 | E6: =+(1-D6) -> 1 | F6: Nos. | G6: ='Shore Pile'!M3 -> 200 | H6: =I6/G6 -> 64189.763 | I6: ='Shore Pile'!F12 -> 12837953 | J6: =+I6*D6 -> 0 | K6: =+E6*I6 -> 12837953
B7: Backfiling | C7: =I7/$G$3 -> 11.464612 | D7: 0 | E7: =+(1-D7) -> 1 | F7: Cu M | G7: =Excavation!I13 -> 6666.9613 | H7: ='Rate List - Flats'!G277 -> 1119 | I7: =G7*H7 -> 7460329.8 | J7: =+I7*D7 -> 0 | K7: =+E7*I7 -> 7460329.8
B8: Antitermite | C8: =I8/$G$3 -> 0.30006537 | D8: 0 | E8: =+(1-D8) -> 1 | F8: Sq M | G8: =Excavation!I14 -> 2077.24 | H8: ='Rate List - Flats'!G279 -> 94 | I8: =G8*H8 -> 195260.56 | J8: =+I8*D8 -> 0 | K8: =+E8*I8 -> 195260.56
B9: Soiling | C9: =I9/$G$3 -> 0 | D9: 0 | E9: =+(1-D9) -> 1 | F9: Sq M | G9: 0 | I9: =G9*H9 -> 0 | J9: =+I9*D9 -> 0 | K9: =+E9*I9 -> 0
B10: Steel | C10: =I10/$G$3 -> 492.63644 | D10: 0 | E10: =+(1-D10) -> 1 | F10: Ton | G10: ='Concrete & Steel Summary'!I60 -> 4042.0087 | H10: ='Rate List - Flats'!G245 -> 79310 | I10: =G10*H10 -> 3.2057171e+08 | J10: =+I10*D10 -> 0 | K10: =+E10*I10 -> 3.2057171e+08 | L10: =G10*1000/G3 -> 6.2115299 | M10: Kg/sft
B11: Concrete | C11: =I11/$G$3 -> 510.78891 | D11: 0 | E11: =+(1-D11) -> 1 | F11: Cu M | G11: ='Concrete & Steel Summary'!D80 -> 32058.57 | H11: =I11/G11 -> 10368.023 | I11: ='Concrete & Steel Summary'!F80 -> 3.32384e+08 | J11: =+I11*D11 -> 0 | K11: =+E11*I11 -> 3.32384e+08 | L11: =G11/G3 -> 0.049265794
B12: Mivan Shuttering | C12: =I12/$G$3 -> 137.87359 | D12: 0 | E12: =+(1-D12) -> 1 | F12: Sq M | G12: ='Shuttering Summary'!C4 -> 119624.04 | H12: ='Rate List - Flats'!G247 -> 750 | I12: =G12*H12 -> 89718033 | J12: =+I12*D12 -> 0 | K12: =+E12*I12 -> 89718033 | L12: =G12/G3 -> 0.18383145
B13: Conventional Shuttering | C13: =I13/$G$3 -> 85.63184 | D13: 0 | E13: =+(1-D13) -> 1 | F13: Sq M | G13: ='Shuttering Summary'!C3 -> 51310.247 | H13: ='Rate List - Flats'!G246 -> 1086 | I13: =G13*H13 -> 55722929 | J13: =+I13*D13 -> 0 | K13: =+E13*I13 -> 55722929 | L13: =G13/G3 -> 0.078850681
B14: Block Work | C14: =I14/$G$3 -> 58.051446 | D14: 0 | E14: =+(1-D14) -> 1 | F14: Sq M | G14: ='Blockwork & Plaster & Painting'!G3 -> 13162.24 | H14: ='Rate List - Flats'!G264 -> 2870 | I14: =G14*H14 -> 37775629 | J14: =+I14*D14 -> 0 | K14: =+E14*I14 -> 37775629
B15: Plum Concrete | C15: =I15/$G$3 -> 61.723479 | D15: 0 | E15: =+(1-D15) -> 1 | F15: Cu M | G15: ='Measurement Sheet'!F363 -> 6132.0792 | H15: ='Rate List - Flats'!G237 -> 6550 | I15: =G15*H15 -> 40165119 | J15: =+I15*D15 -> 0 | K15: =+E15*I15 -> 40165119
B16: Plaster | L16: =+SUM(I10:I13)/G3 -> 1226.9308
B17: Internal Cement Plaster (Wall Area) | C17: =I17/$G$3 -> 4.5845157 | D17: 0 | E17: =+(1-D17) -> 1 | F17: Sq M | G17: =VLOOKUP(B17,'Internal Finishes Flats'!$B$1998:$F$2038,3,FALSE) -> 5229.288 | H17: =VLOOKUP(B17,'Internal Finishes Flats'!$B$1998:$F$2038,4,FALSE) -> 570.492 | I17: =G17*H17 -> 2983267 | J17: =+I17*D17 -> 0 | K17: =+E17*I17 -> 2983267
B18: Internal Cement Plaster (Ceiling Area) | C18: =I18/$G$3 -> 0 | D18: 0 | E18: =+(1-D18) -> 1 | F18: Sq M | G18: =VLOOKUP(B18,'Internal Finishes Flats'!$B$1998:$F$2038,3,FALSE) -> 0 | H18: =VLOOKUP(B18,'Internal Finishes Flats'!$B$1998:$F$2038,4,FALSE) -> 0 | I18: =G18*H18 -> 0 | J18: =+I18*D18 -> 0 | K18: =+E18*I18 -> 0
B19: Internal Plastering - Back Coat | C19: =I19/$G$3 -> 20.895497 | D19: 0 | E19: =+(1-D19) -> 1 | F19: Sq M | G19: =VLOOKUP(B19,'Internal Finishes Flats'!$B$1998:$F$2038,3,FALSE) -> 23086.989 | H19: =VLOOKUP(B19,'Internal Finishes Flats'!$B$1998:$F$2038,4,FALSE) -> 588.95764 | I19: =G19*H19 -> 13597259 | J19: =+I19*D19 -> 0 | K19: =+E19*I19 -> 13597259
B20: External Plaster
B21: External Plastering - 15mm thick | C21: =I21/$G$3 -> 10.14004 | D21: 0 | E21: =+(1-D21) -> 1 | F21: Sq M | G21: =VLOOKUP(B21,'Internal Finishes Flats'!$B$1998:$F$2038,3,FALSE) -> 7211.834 | H21: =VLOOKUP(B21,'Internal Finishes Flats'!$B$1998:$F$2038,4,FALSE) -> 914.94 | I21: =G21*H21 -> 6598395.4 | J21: =+I21*D21 -> 0 | K21: =+E21*I21 -> 6598395.4
B22: Duct Plaster | C22: =I22/$G$3 -> 4.5488326 | D22: 0 | E22: =+(1-D22) -> 1 | F22: Sq M | G22: ='Blockwork & Plaster & Painting'!F11 -> 3846.085 | H22: ='Rate List - Flats'!G249 -> 769.626 | I22: =G22*H22 -> 2960047 | J22: =+I22*D22 -> 0 | K22: =+E22*I22 -> 2960047
B23: Waterproofing | I23: =G23*H23 -> 0 | J23: =+I23*D23 -> 0 | K23: =+E23*I23 -> 0
B24: Basecoat | C24: =I24/$G$3 -> 38.430284 | D24: 0 | E24: =+(1-D24) -> 1 | F24: Sq M | G24: =VLOOKUP(B24,Waterproofing!$B$147:$F$154,3,FALSE) -> 18586.112 | H24: =VLOOKUP(B24,Waterproofing!$B$147:$F$154,4,FALSE) -> 1345.5 | I24: =G24*H24 -> 25007614 | J24: =+I24*D24 -> 0 | K24: =+E24*I24 -> 25007614
B25: Terrace Waterproofing | C25: =I25/$G$3 -> 4.6591333 | D25: 0 | E25: =+(1-D25) -> 1 | F25: Sq M | G25: =VLOOKUP(B25,Waterproofing!$B$147:$F$154,3,FALSE) -> 1083.32 | H25: =VLOOKUP(B25,Waterproofing!$B$147:$F$154,4,FALSE) -> 2798.64 | I25: =G25*H25 -> 3031822.7 | J25: =+I25*D25 -> 0 | K25: =+E25*I25 -> 3031822.7
B26: Podium Waterproofing | C26: =I26/$G$3 -> 5.8399586 | D26: 0 | E26: =+(1-D26) -> 1 | F26: Sq M | G26: =VLOOKUP(B26,Waterproofing!$B$147:$F$154,3,FALSE) -> 1357.88 | H26: =VLOOKUP(B26,Waterproofing!$B$147:$F$154,4,FALSE) -> 2798.64 | I26: =G26*H26 -> 3800217.3 | J26: =+I26*D26 -> 0 | K26: =+E26*I26 -> 3800217.3
B27: Chajja Waterproofing | C27: =I27/$G$3 -> 5.6422041 | D27: 0 | E27: =+(1-D27) -> 1 | F27: Sq M | G27: =VLOOKUP(B27,Waterproofing!$B$147:$F$154,3,FALSE) -> 2728.75 | H27: =VLOOKUP(B27,Waterproofing!$B$147:$F$154,4,FALSE) -> 1345.5 | I27: =G27*H27 -> 3671533.1 | J27: =+I27*D27 -> 0 | K27: =+E27*I27 -> 3671533.1
B28: OHT Waterproofing | C28: =I28/$G$3 -> 1.5919809 | D28: 0 | E28: =+(1-D28) -> 1 | F28: Sq M | G28: =VLOOKUP(B28,Waterproofing!$B$147:$F$154,3,FALSE) -> 370.16 | H28: =VLOOKUP(B28,Waterproofing!$B$147:$F$154,4,FALSE) -> 2798.64 | I28: =G28*H28 -> 1035944.6 | J28: =+I28*D28 -> 0 | K28: =+E28*I28 -> 1035944.6
B29: Membrame Waterproofing | C29: =I29/$G$3 -> 7.2969175 | D29: 0 | E29: =+(1-D29) -> 1 | F29: Sq M | G29: =VLOOKUP(B29,Waterproofing!$B$147:$F$154,3,FALSE) -> 4128.956 | H29: =VLOOKUP(B29,Waterproofing!$B$147:$F$154,4,FALSE) -> 1150 | I29: =G29*H29 -> 4748299.4 | J29: =+I29*D29 -> 0 | K29: =+E29*I29 -> 4748299.4
B30: STP Waterproofing | C30: =I30/$G$3 -> 0.40805909 | D30: 0 | E30: =+(1-D30) -> 1 | F30: Sq M | G30: =VLOOKUP(B30,Waterproofing!$B$147:$F$154,3,FALSE) -> 94.88 | H30: =VLOOKUP(B30,Waterproofing!$B$147:$F$154,4,FALSE) -> 2798.64 | I30: =G30*H30 -> 265534.96 | J30: =+I30*D30 -> 0 | K30: =+E30*I30 -> 265534.96
B31: Brickbat | C31: =I31/$G$3 -> 17.783785 | D31: 0 | E31: =+(1-D31) -> 1 | F31: Cu M | G31: =VLOOKUP(B31,Waterproofing!$B$147:$F$154,3,FALSE) -> 1361.457 | H31: =VLOOKUP(B31,Waterproofing!$B$147:$F$154,4,FALSE) -> 8500 | I31: =G31*H31 -> 11572384 | J31: =+I31*D31 -> 0 | K31: =+E31*I31 -> 11572384
B32: Antiroot Waterproofing | C32: =I32/$G$3 -> 0.16360784 | D32: 0 | E32: =+(1-D32) -> 1 | F32: Cu M | G32: =VLOOKUP(B32,Waterproofing!$B$147:$F$155,3,FALSE) -> 133.08 | H32: =VLOOKUP(B32,Waterproofing!$B$147:$F$155,4,FALSE) -> 800 | I32: =G32*H32 -> 106464 | J32: =+I32*D32 -> 0 | K32: =+E32*I32 -> 106464
B33: Protection Board | C33: =I33/$G$3 -> 2.0494246 | D33: 0 | E33: =+(1-D33) -> 1 | F33: Cu M | G33: =VLOOKUP(B33,Waterproofing!$B$147:$F$156,3,FALSE) -> 2051.716 | H33: =VLOOKUP(B33,Waterproofing!$B$147:$F$156,4,FALSE) -> 650 | I33: =G33*H33 -> 1333615.4 | J33: =+I33*D33 -> 0 | K33: =+E33*I33 -> 1333615.4
B34: Int. Plaster Gypsum | I34: =G34*H34 -> 0 | J34: =+I34*D34 -> 0 | K34: =+E34*I34 -> 0
B35: Gypsum Plastering (Wall Area) | C35: =I35/$G$3 -> 28.290425 | D35: 0 | E35: =+(1-D35) -> 1 | F35: Sq M | G35: =VLOOKUP(B35,'Internal Finishes Flats'!$B$1998:$F$2038,3,FALSE) -> 51990.327 | H35: =VLOOKUP(B35,'Internal Finishes Flats'!$B$1998:$F$2038,4,FALSE) -> 354.09156 | I35: =VLOOKUP(B35,'Internal Finishes Flats'!$B$1998:$F$2038,5,FALSE) -> 18409336 | J35: =+I35*D35 -> 0 | K35: =+E35*I35 -> 18409336
B36: Gypsum Plastering (Ceiling Area) | C36: =I36/$G$3 -> 12.186832 | D36: 0 | E36: =+(1-D36) -> 1 | F36: Sq M | G36: =VLOOKUP(B36,'Internal Finishes Flats'!$B$1998:$F$2038,3,FALSE) -> 22443.66 | H36: =VLOOKUP(B36,'Internal Finishes Flats'!$B$1998:$F$2038,4,FALSE) -> 353.34245 | I36: =G36*H36 -> 7930297.8 | J36: =+I36*D36 -> 0 | K36: =+E36*I36 -> 7930297.8
B37: Tremix
B38: 75mm Thick Tremix | C38: =I38/$G$3 -> 19.90553 | D38: 0 | E38: =+(1-D38) -> 1 | F38: Sq M | G38: =Tremix!E7 -> 8722.6 | H38: ='Rate List - Flats'!G267 -> 1485 | I38: =G38*H38 -> 12953061 | J38: =+I38*D38 -> 0 | K38: =+E38*I38 -> 12953061
A39: FINISHING | B39: Flooring | I39: =G39*H39 -> 0 | J39: =+I39*D39 -> 0 | K39: =+E39*I39 -> 0
B40: Vitrified Flooring - Flats | C40: =I40/$G$3 -> 38.817224 | D40: 0 | E40: =+(1-D40) -> 1 | F40: Sq M | G40: =VLOOKUP(B40,'Internal Finishes Flats'!$B$1998:$F$2038,3,FALSE) -> 18809.63 | H40: =VLOOKUP(B40,'Internal Finishes Flats'!$B$1998:$F$2038,4,FALSE) -> 1342.8976 | I40: =G40*H40 -> 25259406 | J40: =+I40*D40 -> 0 | K40: =+E40*I40 -> 25259406
B41: Vitrfied Skirting - Flats | C41: =I41/$G$3 -> 9.7594334 | D41: 0 | E41: =+(1-D41) -> 1 | F41: RM | G41: =VLOOKUP(B41,'Internal Finishes Flats'!$B$1998:$F$2038,3,FALSE) -> 16182.69 | H41: =VLOOKUP(B41,'Internal Finishes Flats'!$B$1998:$F$2038,4,FALSE) -> 392.43935 | I41: =G41*H41 -> 6350724.4 | J41: =+I41*D41 -> 0 | K41: =+E41*I41 -> 6350724.4
B42: AntiSkid Vitrified/Ceramic Flooring - Toilet | C42: =I42/$G$3 -> 5.0621175 | D42: 0 | E42: =+(1-D42) -> 1 | F42: Sq M | G42: =VLOOKUP(B42,'Internal Finishes Flats'!$B$1998:$F$2038,3,FALSE) -> 2354.04 | H42: =VLOOKUP(B42,'Internal Finishes Flats'!$B$1998:$F$2038,4,FALSE) -> 1399.32 | I42: =G42*H42 -> 3294055.3 | J42: =+I42*D42 -> 0 | K42: =+E42*I42 -> 3294055.3
B43: Vitrified/Ceramic Dado - Toilet | C43: =I43/$G$3 -> 25.858795 | D43: 0 | E43: =+(1-D43) -> 1 | F43: Sq M | G43: =VLOOKUP(B43,'Internal Finishes Flats'!$B$1998:$F$2038,3,FALSE) -> 11369.217 | H43: =VLOOKUP(B43,'Internal Finishes Flats'!$B$1998:$F$2038,4,FALSE) -> 1480.05 | I43: =G43*H43 -> 16827010 | J43: =+I43*D43 -> 0 | K43: =+E43*I43 -> 16827010
B44: Vitrified/Ceramic Dado - Kitchen | C44: =I44/$G$3 -> 4.9322427 | D44: 0 | E44: =+(1-D44) -> 1 | F44: Sq M | G44: =VLOOKUP(B44,'Internal Finishes Flats'!$B$1998:$F$2038,3,FALSE) -> 2302.5 | H44: =VLOOKUP(B44,'Internal Finishes Flats'!$B$1998:$F$2038,4,FALSE) -> 1393.938 | I44: =G44*H44 -> 3209542.2 | J44: =+I44*D44 -> 0 | K44: =+E44*I44 -> 3209542.2
B45: Vitrified/Ceramic Dado - Below Kitchen Platform | C45: =I45/$G$3 -> 2.406325 | D45: 0 | E45: =+(1-D45) -> 1 | F45: Sq M | G45: =VLOOKUP(B45,'Internal Finishes Flats'!$B$1998:$F$2038,3,FALSE) -> 1381.5 | H45: =VLOOKUP(B45,'Internal Finishes Flats'!$B$1998:$F$2038,4,FALSE) -> 1133.4492 | I45: =G45*H45 -> 1565860.1 | J45: =+I45*D45 -> 0 | K45: =+E45*I45 -> 1565860.1
B46: Vitrified Flooring - Balcony | C46: =I46/$G$3 -> 1.349701 | D46: 0 | E46: =+(1-D46) -> 1 | F46: Sq M | G46: =VLOOKUP(B46,'Internal Finishes Flats'!$B$1998:$F$2038,3,FALSE) -> 655.38 | H46: =VLOOKUP(B46,'Internal Finishes Flats'!$B$1998:$F$2038,4,FALSE) -> 1340.118 | I46: =G46*H46 -> 878286.53 | J46: =+I46*D46 -> 0 | K46: =+E46*I46 -> 878286.53
B47: Vitrified Skirting - Balcony | C47: =I47/$G$3 -> 1.0132114 | D47: 0 | E47: =+(1-D47) -> 1 | F47: RM | G47: =VLOOKUP(B47,'Internal Finishes Flats'!$B$1998:$F$2038,3,FALSE) -> 1682.12 | H47: =VLOOKUP(B47,'Internal Finishes Flats'!$B$1998:$F$2038,4,FALSE) -> 391.96 | I47: =G47*H47 -> 659323.76 | J47: =+I47*D47 -> 0 | K47: =+E47*I47 -> 659323.76
B48: Vitrified Dado - Balcony | C48: =I48/$G$3 -> 0 | D48: 0 | E48: =+(1-D48) -> 1 | F48: Sq M | G48: =VLOOKUP(B48,'Internal Finishes Flats'!$B$1998:$F$2038,3,FALSE) -> 0 | H48: =VLOOKUP(B48,'Internal Finishes Flats'!$B$1998:$F$2038,4,FALSE) -> 0 | I48: =G48*H48 -> 0 | J48: =+I48*D48 -> 0 | K48: =+E48*I48 -> 0
B49: Vitrified Flooring - Utility | C49: =I49/$G$3 -> 1.2863327 | D49: 0 | E49: =+(1-D49) -> 1 | F49: Sq M | G49: =VLOOKUP(B49,'Internal Finishes Flats'!$B$1998:$F$2038,3,FALSE) -> 624.61 | H49: =VLOOKUP(B49,'Internal Finishes Flats'!$B$1998:$F$2038,4,FALSE) -> 1340.118 | I49: =G49*H49 -> 837051.1 | J49: =+I49*D49 -> 0 | K49: =+E49*I49 -> 837051.1
B50: Vitrified Skirting - Utility | C50: =I50/$G$3 -> 0.98581688 | D50: 0 | E50: =+(1-D50) -> 1 | F50: Sq M | G50: =VLOOKUP(B50,'Internal Finishes Flats'!$B$1998:$F$2038,3,FALSE) -> 1636.64 | H50: =VLOOKUP(B50,'Internal Finishes Flats'!$B$1998:$F$2038,4,FALSE) -> 391.96 | I50: =G50*H50 -> 641497.41 | J50: =+I50*D50 -> 0 | K50: =+E50*I50 -> 641497.41
B51: Vitrified Dado - Utility | C51: =I51/$G$3 -> 0 | D51: 0 | E51: =+(1-D51) -> 1 | F51: Sq M | G51: =VLOOKUP(B51,'Internal Finishes Flats'!$B$1998:$F$2038,3,FALSE) -> 0 | H51: =VLOOKUP(B51,'Internal Finishes Flats'!$B$1998:$F$2038,4,FALSE) -> 0 | I51: =G51*H51 -> 0 | J51: =+I51*D51 -> 0 | K51: =+E51*I51 -> 0
... B59: Kota Flooring - Riser - Staircase | C59: =I59/$G$3 -> 2.9241147 | D59: 0 | E59: =+(1-D59) -> 1 | F59: Sq M | G59: =VLOOKUP(B59,'Internal Finishes Flats'!$B$1998:$F$2038,3,FALSE) -> 1140.48 | H59: =VLOOKUP(B59,'Internal Finishes Flats'!$B$1998:$F$2038,4,FALSE) -> 1668.42 | I59: =G59*H59 -> 1902799.6 | J59: =+I59*D59 -> 0 | K59: =+E59*I59 -> 1902799.6
B60: Painting Works(Internal & External)
B61: Internal Painting (Wall Area - Arcylic Emulsion Paint) | C61: =I61/$G$3 -> 22.956574 | D61: 0 | E61: =+(1-D61) -> 1 | F61: Sq M | G61: =VLOOKUP(B61,'Internal Finishes Flats'!$B$1998:$F$2038,3,FALSE) -> 59524.536 | H61: =VLOOKUP(B61,'Internal Finishes Flats'!$B$1998:$F$2038,4,FALSE) -> 250.96301 | I61: =G61*H61 -> 14938456 | J61: =+I61*D61 -> 0 | K61: =+E61*I61 -> 14938456
B62: Internal Painting (Ceiling Area - Arcylic Emulsion Paint) | C62: =I62/$G$3 -> 9.8813684 | D62: 0 | E62: =+(1-D62) -> 1 | F62: Sq M | G62: =VLOOKUP(B62,'Internal Finishes Flats'!$B$1998:$F$2038,3,FALSE) -> 26951.9 | H62: =VLOOKUP(B62,'Internal Finishes Flats'!$B$1998:$F$2038,4,FALSE) -> 238.57579 | I62: =G62*H62 -> 6430070.7 | J62: =+I62*D62 -> 0 | K62: =+E62*I62 -> 6430070.7
B63: Internal Painting (Wall Area - Cement Paint) | C63: =I63/$G$3 -> 4.8215939 | D63: 0 | E63: =+(1-D63) -> 1 | F63: Sq M | G63: =VLOOKUP(B63,'Internal Finishes Flats'!$B$1998:$F$2038,3,FALSE) -> 17564.126 | H63: =VLOOKUP(B63,'Internal Finishes Flats'!$B$1998:$F$2038,4,FALSE) -> 178.63343 | I63: =G63*H63 -> 3137540.1 | J63: =+I63*D63 -> 0 | K63: =+E63*I63 -> 3137540.1
B64: Internal Painting (Ceiling Area - Cement Paint) | C64: =I64/$G$3 -> 0.939404 | D64: 0 | E64: =+(1-D64) -> 1 | F64: Sq M | G64: =VLOOKUP(B64,'Internal Finishes Flats'!$B$1998:$F$2038,3,FALSE) -> 3155.04 | H64: =VLOOKUP(B64,'Internal Finishes Flats'!$B$1998:$F$2038,4,FALSE) -> 193.752 | I64: =G64*H64 -> 611295.31 | J64: =+I64*D64 -> 0 | K64: =+E64*I64 -> 611295.31
B65: External Painting
B66: Texture Painting External | C66: =I66/$G$3 -> 21.34117 | D66: 0 | E66: =+(1-D66) -> 1 | F66: Sq M | G66: ='Blockwork & Plaster & Painting'!F20 -> 30860.6 | H66: ='Rate List - Flats'!G265 -> 450 | I66: =G66*H66 -> 13887270 | J66: =+I66*D66 -> 0 | K66: =+E66*I66 -> 13887270
B67: Duct Painting | C67: =I67/$G$3 -> 2.2267012 | D67: 0 | E67: =+(1-D67) -> 1 | F67: Sq M | G67: ='Blockwork & Plaster & Painting'!F11 -> 3846.085 | H67: ='Rate List - Flats'!G266 -> 376.74 | I67: =G67*H67 -> 1448974.1 | J67: =+I67*D67 -> 0 | K67: =+E67*I67 -> 1448974.1
B68: Doors & Windows
B69: Doors
B70: FRD | C70: =I70/$G$3 -> 24.895242 | D70: 0 | E70: =+(1-D70) -> 1 | F70: Nos. | G70: =VLOOKUP(B70,Doors!$D$146:$H$149,3,FALSE)-32 -> 508 | H70: =VLOOKUP(B70,Doors!$D$146:$H$149,4,FALSE) -> 30000 | I70: =VLOOKUP(B70,Doors!$D$146:$H$149,5,FALSE) -> 16200000 | J70: =+I70*D70 -> 0 | K70: =+E70*I70 -> 16200000
B71: D1 | C71: =I71/$G$3 -> 18.450141 | D71: 0 | E71: =+(1-D71) -> 1 | F71: Nos. | G71: =VLOOKUP(B71,Doors!$D$146:$H$149,3,FALSE)-32 -> 635 | H71: =VLOOKUP(B71,Doors!$D$146:$H$149,4,FALSE) -> 18000 | I71: =VLOOKUP(B71,Doors!$D$146:$H$149,5,FALSE) -> 12006000 | J71: =+I71*D71 -> 0 | K71: =+E71*I71 -> 12006000
B72: D2 | C72: =I72/$G$3 -> 11.214385 | D72: 0 | E72: =+(1-D72) -> 1 | F72: Nos. | G72: =VLOOKUP(B72,Doors!$D$146:$H$149,3,FALSE)-32 -> 663 | H72: =VLOOKUP(B72,Doors!$D$146:$H$149,4,FALSE) -> 10500 | I72: =VLOOKUP(B72,Doors!$D$146:$H$149,5,FALSE) -> 7297500 | J72: =+I72*D72 -> 0 | K72: =+E72*I72 -> 7297500
B73: K FRD | C73: =I73/$G$3 -> 10.680366 | D73: 0 | E73: =+(1-D73) -> 1 | F73: Nos. | G73: =VLOOKUP(B73,Doors!$D$146:$H$149,3,FALSE) -> 278 | H73: =VLOOKUP(B73,Doors!$D$146:$H$149,4,FALSE) -> 25000 | I73: =VLOOKUP(B73,Doors!$D$146:$H$149,5,FALSE) -> 6950000 | J73: =+I73*D73 -> 0 | K73: =+E73*I73 -> 6950000
B74: Windows
B75: W1 | C75: =I75/$G$3 -> 4.7688085 | D75: 0 | E75: =+(1-D75) -> 1 | F75: Sq M | G75: =VLOOKUP(B75,Windows!$D$166:$H$177,3,FALSE) -> 524.17 | H75: =VLOOKUP(B75,Windows!$D$166:$H$177,4,FALSE) -> 5920.2 | I75: =VLOOKUP(B75,Windows!$D$166:$H$177,5,FALSE) -> 3103191.2 | J75: =+I75*D75 -> 0 | K75: =+E75*I75 -> 3103191.2
B76: W8 | C76: =I76/$G$3 -> 0.53125857 | D76: 0 | E76: =+(1-D76) -> 1 | F76: Sq M | G76: =VLOOKUP(B76,Windows!$D$166:$H$177,3,FALSE) -> 58.394 | H76: =VLOOKUP(B76,Windows!$D$166:$H$177,4,FALSE) -> 5920.2 | I76: =VLOOKUP(B76,Windows!$D$166:$H$177,5,FALSE) -> 345704.16 | J76: =+I76*D76 -> 0 | K76: =+E76*I76 -> 345704.16
B77: W4 | C77: =I77/$G$3 -> 37.704492 | D77: 0 | E77: =+(1-D77) -> 1 | F77: Sq M | G77: =VLOOKUP(B77,Windows!$D$166:$H$177,3,FALSE) -> 4144.34 | H77: =VLOOKUP(B77,Windows!$D$166:$H$177,4,FALSE) -> 5920.2 | I77: =VLOOKUP(B77,Windows!$D$166:$H$177,5,FALSE) -> 24535322 | J77: =+I77*D77 -> 0 | K77: =+E77*I77 -> 24535322
B78: V | C78: =I78/$G$3 -> 2.714337 | D78: 0 | E78: =+(1-D78) -> 1 | F78: Sq M | G78: =VLOOKUP(B78,Windows!$D$166:$H$177,3,FALSE) -> 298.35 | H78: =VLOOKUP(B78,Windows!$D$166:$H$177,4,FALSE) -> 5920.2 | I78: =VLOOKUP(B78,Windows!$D$166:$H$177,5,FALSE) -> 1766291.7 | J78: =+I78*D78 -> 0 | K78: =+E78*I78 -> 1766291.7
B79: W7 | C79: =I79/$G$3 -> 4.8900825 | D79: 0 | E79: =+(1-D79) -> 1 | F79: Sq M | G79: =VLOOKUP(B79,Windows!$D$166:$H$177,3,FALSE) -> 537.5 | H79: =VLOOKUP(B79,Windows!$D$166:$H$177,4,FALSE) -> 5920.2 | I79: =VLOOKUP(B79,Windows!$D$166:$H$177,5,FALSE) -> 3182107.5 | J79: =+I79*D79 -> 0 | K79: =+E79*I79 -> 3182107.5
B80: UR | C80: =I80/$G$3 -> 3.6497654 | D80: 0 | E80: =+(1-D80) -> 1 | F80: RM | G80: =VLOOKUP(B80,Windows!$D$166:$H$177,3,FALSE) -> 250 | H80: =VLOOKUP(B80,Windows!$D$166:$H$177,4,FALSE) -> 9500 | I80: =VLOOKUP(B80,Windows!$D$166:$H$177,5,FALSE) -> 2375000 | J80: =+I80*D80 -> 0 | K80: =+E80*I80 -> 2375000
B81: BR | C81: =I81/$G$3 -> 12.257956 | D81: 0 | E81: =+(1-D81) -> 1 | F81: Sq M | G81: =VLOOKUP(B81,Windows!$D$166:$H$177,3,FALSE) -> 839.64 | H81: =VLOOKUP(B81,Windows!$D$166:$H$177,4,FALSE) -> 9500 | I81: =VLOOKUP(B81,Windows!$D$166:$H$177,5,FALSE) -> 7976580 | J81: =+I81*D81 -> 0 | K81: =+E81*I81 -> 7976580
B82: W2 | C82: =I82/$G$3 -> 7.2764428 | D82: 0 | E82: =+(1-D82) -> 1 | F82: Sq M | G82: =VLOOKUP(B82,Windows!$D$166:$H$177,3,FALSE) -> 799.8 | H82: =VLOOKUP(B82,Windows!$D$166:$H$177,4,FALSE) -> 5920.2 | I82: =VLOOKUP(B82,Windows!$D$166:$H$177,5,FALSE) -> 4734976 | J82: =+I82*D82 -> 0 | K82: =+E82*I82 -> 4734976
B83: W3 | C83: =I83/$G$3 -> 6.2309432 | D83: 0 | E83: =+(1-D83) -> 1 | F83: Sq M | G83: =VLOOKUP(B83,Windows!$D$166:$H$177,3,FALSE) -> 684.8825 | H83: =VLOOKUP(B83,Windows!$D$166:$H$177,4,FALSE) -> 5920.2 | I83: =VLOOKUP(B83,Windows!$D$166:$H$177,5,FALSE) -> 4054641.4 | J83: =+I83*D83 -> 0 | K83: =+E83*I83 -> 4054641.4
B84: W4A | C84: =I84/$G$3 -> 2.2564797 | D84: 0 | E84: =+(1-D84) -> 1 | F84: Sq M | G84: =VLOOKUP(B84,Windows!$D$166:$H$177,3,FALSE) -> 248.024 | H84: =VLOOKUP(B84,Windows!$D$166:$H$177,4,FALSE) -> 5920.2 | I84: =VLOOKUP(B84,Windows!$D$166:$H$177,5,FALSE) -> 1468351.7 | J84: =+I84*D84 -> 0 | K84: =+E84*I84 -> 1468351.7
B85: LW | C85: =I85/$G$3 -> 3.5318132 | D85: 0 | E85: =+(1-D85) -> 1 | F85: Sq M | G85: =VLOOKUP(B85,Windows!$D$166:$H$177,3,FALSE) -> 388.204 | H85: =VLOOKUP(B85,Windows!$D$166:$H$177,4,FALSE) -> 5920.2 | I85: =VLOOKUP(B85,Windows!$D$166:$H$177,5,FALSE) -> 2298245.3 | J85: =+I85*D85 -> 0 | K85: =+E85*I85 -> 2298245.3
B86: SW | C86: =I86/$G$3 -> 8.6847866 | D86: 0 | E86: =+(1-D86) -> 1 | F86: Sq M | G86: =VLOOKUP(B86,Windows!$D$166:$H$177,3,FALSE) -> 954.6 | H86: =VLOOKUP(B86,Windows!$D$166:$H$177,4,FALSE) -> 5920.2 | I86: =VLOOKUP(B86,Windows!$D$166:$H$177,5,FALSE) -> 5651422.9 | J86: =+I86*D86 -> 0 | K86: =+E86*I86 -> 5651422.9
B87: MS Railing - Staircase | C87: =I87/$G$3 -> 4.967975 | D87: 0 | E87: =+(1-D87) -> 1 | F87: Sq M | G87: =VLOOKUP(B87,'Internal Finishes Flats'!$B$1998:$F$2038,3,FALSE) -> 1010.88 | H87: =VLOOKUP(B87,'Internal Finishes Flats'!$B$1998:$F$2038,4,FALSE) -> 3198 | I87: =G87*H87 -> 3232794.2 | J87: =+I87*D87 -> 0 | K87: =+E87*I87 -> 3232794.2
B88: Miscellenous | I88: =G88*H88 -> 0 | J88: =+I88*D88 -> 0 | K88: =+E88*I88 -> 0
B89: Granite Basin Counter | C89: =I89/$G$3 -> 2.3216598 | D89: 0 | E89: =+(1-D89) -> 1 | F89: Sq M | G89: =VLOOKUP(B89,'Internal Finishes Flats'!$B$1998:$F$2038,3,FALSE) -> 238.68 | H89: =VLOOKUP(B89,'Internal Finishes Flats'!$B$1998:$F$2038,4,FALSE) -> 6329.672 | I89: =G89*H89 -> 1510766.1 | J89: =+I89*D89 -> 0 | K89: =+E89*I89 -> 1510766.1
B90: Granite Door Frame | C90: =I90/$G$3 -> 7.6186033 | D90: 0 | E90: =+(1-D90) -> 1 | F90: RM | G90: =VLOOKUP(B90,'Internal Finishes Flats'!$B$1998:$F$2038,3,FALSE) -> 7558.2 | H90: =VLOOKUP(B90,'Internal Finishes Flats'!$B$1998:$F$2038,4,FALSE) -> 655.9272 | I90: =G90*H90 -> 4957629 | J90: =+I90*D90 -> 0 | K90: =+E90*I90 -> 4957629
B91: Granite Window Frame | C91: =I91/$G$3 -> 12.711522 | D91: 0 | E91: =+(1-D91) -> 1 | F91: RM | G91: =VLOOKUP(B91,'Internal Finishes Flats'!$B$1998:$F$2038,3,FALSE) -> 12610.74 | H91: =VLOOKUP(B91,'Internal Finishes Flats'!$B$1998:$F$2038,4,FALSE) -> 655.9272 | I91: =G91*H91 -> 8271727.4 | J91: =+I91*D91 -> 0 | K91: =+E91*I91 -> 8271727.4
B92: Marble Window Frame | C92: =I92/$G$3 -> 8.6990611 | D92: 0 | E92: =+(1-D92) -> 1 | F92: RM | G92: =VLOOKUP(B92,'Internal Finishes Flats'!$B$1998:$F$2038,3,FALSE) -> 14185.74 | H92: =VLOOKUP(B92,'Internal Finishes Flats'!$B$1998:$F$2038,4,FALSE) -> 399.0424 | I92: =G92*H92 -> 5660711.7 | J92: =+I92*D92 -> 0 | K92: =+E92*I92 -> 5660711.7
B93: Granite Kitchen Counter - Main Platform | C93: =I93/$G$3 -> 9.889347 | D93: 0 | E93: =+(1-D93) -> 1 | F93: Sq M | G93: =VLOOKUP(B93,'Internal Finishes Flats'!$B$1998:$F$2038,3,FALSE) -> 880 | H93: =VLOOKUP(B93,'Internal Finishes Flats'!$B$1998:$F$2038,4,FALSE) -> 7312.7984 | I93: =G93*H93 -> 6435262.6 | J93: =+I93*D93 -> 0 | K93: =+E93*I93 -> 6435262.6
B94: Granite Kitchen Counter - Service Platform | C94: =I94/$G$3 -> 7.3608208 | D94: 0 | E94: =+(1-D94) -> 1 | F94: Sq M | G94: =VLOOKUP(B94,'Internal Finishes Flats'!$B$1998:$F$2038,3,FALSE) -> 655 | H94: =VLOOKUP(B94,'Internal Finishes Flats'!$B$1998:$F$2038,4,FALSE) -> 7312.7984 | I94: =G94*H94 -> 4789883 | J94: =+I94*D94 -> 0 | K94: =+E94*I94 -> 4789883
B95: Granite Architrave | C95: =I95/$G$3 -> 10.356208 | D95: 0 | E95: =+(1-D95) -> 1 | F95: RM | G95: =VLOOKUP(B95,'Internal Finishes Flats'!$B$1998:$F$2038,3,FALSE) -> 1944 | H95: =VLOOKUP(B95,'Internal Finishes Flats'!$B$1998:$F$2038,4,FALSE) -> 3466.5956 | I95: =G95*H95 -> 6739061.8 | J95: =+I95*D95 -> 0 | K95: =+E95*I95 -> 6739061.8
B96: Fire Stopper - Ducts | C96: =I96/$G$3 -> 3.8435842 | D96: 0 | E96: =+(1-D96) -> 1 | F96: Sq M | G96: =VLOOKUP(B96,'Internal Finishes Flats'!$B$1998:$F$2038,3,FALSE) -> 116.18 | H96: =VLOOKUP(B96,'Internal Finishes Flats'!$B$1998:$F$2038,4,FALSE) -> 21528 | I96: =G96*H96 -> 2501123 | J96: =+I96*D96 -> 0 | K96: =+E96*I96 -> 2501123
B97: False Ceiling
B98: False Ceiling - Flats | C98: =I98/$G$3 -> 0 | D98: 0 | E98: =+(1-D98) -> 1 | F98: Sq M | I98: =G98*H98 -> 0 | J98: =+I98*D98 -> 0 | K98: =+E98*I98 -> 0
B99: False Ceiling - Common Lobby | C99: =I99/$G$3 -> 0 | D99: 0 | E99: =+(1-D99) -> 1 | F99: Sq M | G99: =VLOOKUP(B99,'Internal Finishes Flats'!$B$1998:$F$2038,3,FALSE) -> 4508.24 | H99: =VLOOKUP(B99,'Internal Finishes Flats'!$B$1998:$F$2038,4,FALSE) -> 0 | I99: =G99*H99 -> 0 | J99: =+I99*D99 -> 0 | K99: =+E99*I99 -> 0 | L99: =G99*135*10.764 -> 6551103.9
A100: MEP | B100: Electrical | C100: =I100/$G$3 -> 78.73105 | D100: 0 | E100: =+(1-D100) -> 1 | F100: LS | G100: 1 | H100: =I100/'MEP Summary'!$I$1 -> 123.81166 | I100: ='MEP Summary'!E5 -> 51232400 | J100: =+I100*D100 -> 0 | K100: =+E100*I100 -> 51232400
B101: Plumbing | C101: =I101/$G$3 -> 50.871491 | D101: 0 | E101: =+(1-D101) -> 1 | F101: LS | G101: 1 | H101: =I101/'MEP Summary'!$I$1 -> 80 | I101: ='MEP Summary'!E6 -> 33103440 | J101: =+I101*D101 -> 0 | K101: =+E101*I101 -> 33103440
B102: CP & sanitory & Kitchen Sink | C102: =I102/$G$3 -> 27.66138 | D102: 0 | E102: =+(1-D102) -> 1 | F102: LS | G102: 1 | H102: =I102/'MEP Summary'!$I$1 -> 43.500011 | I102: ='MEP Summary'!E7 -> 18000000 | J102: =+I102*D102 -> 0 | K102: =+E102*I102 -> 18000000
B103: FF incl. | C103: =I103/$G$3 -> 44.512555 | D103: 0 | E103: =+(1-D103) -> 1 | F103: LS | G103: 1 | H103: =I103/'MEP Summary'!$I$1 -> 70 | I103: ='MEP Summary'!E8 -> 28965510 | J103: =+I103*D103 -> 0 | K103: =+E103*I103 -> 28965510
B104: FAPA | C104: =I104/$G$3 -> 11.446086 | D104: 0 | E104: =+(1-D104) -> 1 | F104: LS | G104: 1 | H104: =I104/'MEP Summary'!$I$1 -> 18 | I104: ='MEP Summary'!E9 -> 7448274 | J104: =+I104*D104 -> 0 | K104: =+E104*I104 -> 7448274
B105: CCTV | C105: =I105/$G$3 -> 5.0000173 | D105: 0 | E105: =+(1-D105) -> 1 | F105: LS | G105: 1 | H105: =I105/'MEP Summary'!$I$1 -> 7.8629774 | I105: ='MEP Summary'!E10 -> 3253645 | J105: =+I105*D105 -> 0 | K105: =+E105*I105 -> 3253645
B106: HVAC Ventilation + pressurization | C106: =I106/$G$3 -> 25.435746 | D106: 0 | E106: =+(1-D106) -> 1 | F106: LS | G106: 1 | H106: =I106/'MEP Summary'!$I$1 -> 40 | I106: ='MEP Summary'!E11 -> 16551720 | J106: =+I106*D106 -> 0 | K106: =+E106*I106 -> 16551720
B107: Gas Supply | C107: =I107/$G$3 -> 3.4423051 | D107: 0 | E107: =+(1-D107) -> 1 | F107: LS | G107: 1 | H107: =I107/'MEP Summary'!$I$1 -> 5.4133347 | I107: ='MEP Summary'!E12 -> 2240000 | J107: =+I107*D107 -> 0 | K107: =+E107*I107 -> 2240000
B108: Elevators | C108: =I108/$G$3 -> 111.56757 | D108: 0 | E108: =+(1-D108) -> 1 | F108: LS | G108: 1 | H108: =I108/'MEP Summary'!$I$1 -> 175.45004 | I108: ='MEP Summary'!E13 -> 72600000 | J108: =+I108*D108 -> 0 | K108: =+E108*I108 -> 72600000
...

Sheet Cost Sheet office
A2: Detailed Cost Estimate
E3: CA | G3: ='Construction Area'!S45 -> 650726.75 | H3: Sft
A4: Sr. No | B4: Description | C4: Rate Psf of Const Area | D4: % Completed | E4: Balance % | F4: Unit | G4: Quantity | H4: Rate | I4: Total Cost | J4: Cost till date | K4: Balance Cost
B5: Plaster
B6: Internal Cement Plaster (Wall Area) | C6: =I6/$G$3 -> 0.32013569 | D6: 0 | E6: =+(1-D6) -> 1 | F6: Sq M | G6: =VLOOKUP(B6,'Internal Finishes Offices'!$B$78:$I$106,4,FALSE) -> 570.492 | H6: =I6/G6 -> 365.16 | I6: =VLOOKUP(B6,'Internal Finishes Offices'!$B$78:$I$106,5,FALSE) -> 208320.86 | L6: =SUM(I6:I8)+SUM('Cost Sheet Tower'!I17:I19) -> 16856694 | N6: =I6/2 -> 104160.43
B7: Internal Cement Plaster (Ceiling Area) | C7: =I7/$G$3 -> 0 | D7: 0 | E7: =+(1-D7) -> 1 | F7: Sq M | G7: =VLOOKUP(B7,'Internal Finishes Offices'!$B$78:$I$106,4,FALSE) -> 0 | I7: =VLOOKUP(B7,'Internal Finishes Offices'!$B$78:$I$106,5,FALSE) -> 0 | N7: =I7/2 -> 0
B8: Internal Plastering - Back Coat | C8: =I8/$G$3 -> 0.10426484 | D8: 0 | E8: =+(1-D8) -> 1 | F8: Sq M | G8: =VLOOKUP(B8,'Internal Finishes Offices'!$B$78:$I$106,4,FALSE) -> 588.95764 | H8: =I8/G8 -> 115.2 | I8: =VLOOKUP(B8,'Internal Finishes Offices'!$B$78:$I$106,5,FALSE) -> 67847.92 | N8: =I8/2 -> 33923.96
B9: Int. Plaster Gypsum | N9: =I9/2 -> 0
B10: Gypsum Plastering (Wall Area) | C10: =I10/$G$3 -> 1.1177114 | D10: 0 | E10: =+(1-D10) -> 1 | F10: Sq M | G10: =VLOOKUP(B10,'Internal Finishes Offices'!$B$78:$I$106,4,FALSE) -> 343.76521 | H10: =I10/G10 -> 2115.76 | I10: =VLOOKUP(B10,'Internal Finishes Offices'!$B$78:$I$106,5,FALSE) -> 727324.69 | L10: =SUM(I10:I11)+SUM('Cost Sheet Tower'!I35:I36) -> 27471441 | N10: =I10/2 -> 363662.34
B11: Gypsum Plastering (Ceiling Area) | C11: =I11/$G$3 -> 0.62158478 | D11: 0 | E11: =+(1-D11) -> 1 | F11: Sq M | G11: =VLOOKUP(B11,'Internal Finishes Offices'!$B$78:$I$106,4,FALSE) -> 336.17174 | H11: =I11/G11 -> 1203.2 | I11: =VLOOKUP(B11,'Internal Finishes Offices'!$B$78:$I$106,5,FALSE) -> 404481.84 | N11: =I11/2 -> 202240.92
A12: FINISHING | B12: Flooring | J12: =+I12*D12 -> 0 | K12: =+E12*I12 -> 0 | N12: =I12/2 -> 0
B13: Vitrified Flooring - Office | C13: =I13/$G$3 -> 2.3361078 | D13: 0 | E13: =+(1-D13) -> 1 | F13: Sq M | G13: =VLOOKUP(B13,'Internal Finishes Offices'!$B$78:$I$106,4,FALSE) -> 1336.6698 | H13: =I13/G13 -> 1137.28 | I13: =VLOOKUP(B13,'Internal Finishes Offices'!$B$78:$I$106,5,FALSE) -> 1520167.9 | J13: =+I13*D13 -> 0 | K13: =+E13*I13 -> 1520167.9 | L13: =SUM(I13:I24,I40:I45)+SUM('Cost Sheet Tower'!I40:I59,'Cost Sheet Tower'!I89:I95) -> 1.3902476e+08 | N13: =I13/2 -> 760083.93
B14: Vitrfied Skirting - Office | C14: =I14/$G$3 -> 0.23978027 | D14: 0 | E14: =+(1-D14) -> 1 | F14: RM | G14: =VLOOKUP(B14,'Internal Finishes Offices'!$B$78:$I$106,4,FALSE) -> 391.96 | H14: =I14/G14 -> 398.08 | I14: =VLOOKUP(B14,'Internal Finishes Offices'!$B$78:$I$106,5,FALSE) -> 156031.44 | J14: =+I14*D14 -> 0 | K14: =+E14*I14 -> 156031.44 | N14: =I14/2 -> 78015.718
B15: Vitrified/Ceramic Dado - Pantry | C15: =I15/$G$3 -> 0.2362921 | D15: 0 | E15: =+(1-D15) -> 1 | F15: Sq M | G15: =VLOOKUP(B15,'Internal Finishes Offices'!$B$78:$I$106,4,FALSE) -> 1334.736 | H15: =I15/G15 -> 115.2 | I15: =VLOOKUP(B15,'Internal Finishes Offices'!$B$78:$I$106,5,FALSE) -> 153761.59 | J15: =+I15*D15 -> 0 | K15: =+E15*I15 -> 153761.59 | N15: =I15/2 -> 76880.794
B16: AntiSkid Vitrified/Ceramic Flooring - Toilet | C16: =I16/$G$3 -> 0.12975951 | D16: 0 | E16: =+(1-D16) -> 1 | F16: Sq M | G16: =VLOOKUP(B16,'Internal Finishes Offices'!$B$78:$I$106,4,FALSE) -> 1280.916 | H16: =I16/G16 -> 65.92 | I16: =VLOOKUP(B16,'Internal Finishes Offices'!$B$78:$I$106,5,FALSE) -> 84437.983 | J16: =+I16*D16 -> 0 | K16: =+E16*I16 -> 84437.983 | N16: =I16/2 -> 42218.991
B17: Vitrified/Ceramic Dado - Toilet | C17: =I17/$G$3 -> 0.79654256 | D17: 0 | E17: =+(1-D17) -> 1 | F17: Sq M | G17: =VLOOKUP(B17,'Internal Finishes Offices'!$B$78:$I$106,4,FALSE) -> 1356.264 | H17: =I17/G17 -> 382.176 | I17: =VLOOKUP(B17,'Internal Finishes Offices'!$B$78:$I$106,5,FALSE) -> 518331.55 | J17: =+I17*D17 -> 0 | K17: =+E17*I17 -> 518331.55 | N17: =I17/2 -> 259165.78
B18: Vitrified Flooring - Common Lobby | C18: =I18/$G$3 -> 0.27045891 | D18: 0 | E18: =+(1-D18) -> 1 | F18: Sq M | G18: =VLOOKUP(B18,'Internal Finishes Offices'!$B$78:$I$106,4,FALSE) -> 1619.982 | H18: =I18/G18 -> 108.64 | I18: =VLOOKUP(B18,'Internal Finishes Offices'!$B$78:$I$106,5,FALSE) -> 175994.84 | J18: =+I18*D18 -> 0 | K18: =+E18*I18 -> 175994.84 | N18: =I18/2 -> 87997.422
B19: Vitrfied Skirting - Common Lobby | C19: =I19/$G$3 -> 0 | D19: 0 | E19: =+(1-D19) -> 1 | F19: Sq M | G19: =VLOOKUP(B19,'Internal Finishes Offices'!$B$78:$I$106,4,FALSE) -> 0 | I19: =VLOOKUP(B19,'Internal Finishes Offices'!$B$78:$I$106,5,FALSE) -> 0 | J19: =+I19*D19 -> 0 | K19: =+E19*I19 -> 0 | N19: =I19/2 -> 0
B20: Kota Flooring - Staircase | C20: =I20/$G$3 -> 0.75772269 | D20: 0 | E20: =+(1-D20) -> 1 | F20: RM | G20: =VLOOKUP(B20,'Internal Finishes Offices'!$B$78:$I$106,4,FALSE) -> 1625.364 | H20: =I20/G20 -> 303.36 | I20: =VLOOKUP(B20,'Internal Finishes Offices'!$B$78:$I$106,5,FALSE) -> 493070.42 | J20: =+I20*D20 -> 0 | K20: =+E20*I20 -> 493070.42 | N20: =I20/2 -> 246535.21
B21: Kota Skriting - Staircase | C21: =I21/$G$3 -> 0.068551047 | D21: 0 | E21: =+(1-D21) -> 1 | F21: Sq M | G21: =VLOOKUP(B21,'Internal Finishes Offices'!$B$78:$I$106,4,FALSE) -> 446.08 | H21: =I21/G21 -> 100 | I21: =VLOOKUP(B21,'Internal Finishes Offices'!$B$78:$I$106,5,FALSE) -> 44608 | J21: =+I21*D21 -> 0 | K21: =+E21*I21 -> 44608 | N21: =I21/2 -> 22304
B22: Kota Dado - Staircase | C22: =I22/$G$3 -> 0 | D22: 0 | E22: =+(1-D22) -> 1 | F22: Sq M | G22: =VLOOKUP(B22,'Internal Finishes Offices'!$B$78:$I$106,4,FALSE) -> 0 | I22: =VLOOKUP(B22,'Internal Finishes Offices'!$B$78:$I$106,5,FALSE) -> 0 | J22: =+I22*D22 -> 0 | K22: =+E22*I22 -> 0 | N22: =I22/2 -> 0
B23: Kota Flooring - Tread - Staircase | C23: =I23/$G$3 -> 0.23025775 | D23: 0 | E23: =+(1-D23) -> 1 | F23: Sq M | G23: =VLOOKUP(B23,'Internal Finishes Offices'!$B$78:$I$106,4,FALSE) -> 1560.78 | H23: =I23/G23 -> 96 | I23: =VLOOKUP(B23,'Internal Finishes Offices'!$B$78:$I$106,5,FALSE) -> 149834.88 | J23: =+I23*D23 -> 0 | K23: =+E23*I23 -> 149834.88 | N23: =I23/2 -> 74917.44
B24: Kota Flooring - Riser - Staircase | C24: =I24/$G$3 -> 0.15197012 | D24: 0 | E24: =+(1-D24) -> 1 | F24: Sq M | G24: =VLOOKUP(B24,'Internal Finishes Offices'!$B$78:$I$106,4,FALSE) -> 1560.78 | H24: =I24/G24 -> 63.36 | I24: =VLOOKUP(B24,'Internal Finishes Offices'!$B$78:$I$106,5,FALSE) -> 98891.021 | J24: =+I24*D24 -> 0 | K24: =+E24*I24 -> 98891.021 | N24: =I24/2 -> 49445.51
B25: Painting Works(Internal & External) | N25: =I25/2 -> 0
B26: Internal Painting (Wall Area - Arcylic Emulsion Paint) | C26: =I26/$G$3 -> 0.71844125 | D26: 0 | E26: =+(1-D26) -> 1 | F26: Sq M | G26: =VLOOKUP(B26,'Internal Finishes Offices'!$B$78:$I$106,4,FALSE) -> 220.96501 | H26: =I26/G26 -> 2115.76 | I26: =VLOOKUP(B26,'Internal Finishes Offices'!$B$78:$I$106,5,FALSE) -> 467508.94 | J26: =+I26*D26 -> 0 | K26: =+E26*I26 -> 467508.94 | L26: =SUM(I26:I29)+SUM('Cost Sheet Tower'!I61:I64) -> 26093412 | N26: =I26/2 -> 233754.47
B27: Internal Painting (Ceiling Area - Arcylic Emulsion Paint) | C27: =I27/$G$3 -> 0.43513528 | D27: 0 | E27: =+(1-D27) -> 1 | F27: Sq M | G27: =VLOOKUP(B27,'Internal Finishes Offices'!$B$78:$I$106,4,FALSE) -> 215.84505 | H27: =I27/G27 -> 1311.84 | I27: =VLOOKUP(B27,'Internal Finishes Offices'!$B$78:$I$106,5,FALSE) -> 283154.17 | J27: =+I27*D27 -> 0 | K27: =+E27*I27 -> 283154.17 | N27: =I27/2 -> 141577.08
B28: Internal Painting (Wall Area - Cement Paint) | C28: =I28/$G$3 -> 0.31086941 | D28: 0 | E28: =+(1-D28) -> 1 | F28: Sq M | G28: =VLOOKUP(B28,'Internal Finishes Offices'!$B$78:$I$106,4,FALSE) -> 179.18734 | H28: =I28/G28 -> 1128.936 | I28: =VLOOKUP(B28,'Internal Finishes Offices'!$B$78:$I$106,5,FALSE) -> 202291.04 | J28: =+I28*D28 -> 0 | K28: =+E28*I28 -> 202291.04 | N28: =I28/2 -> 101145.52
B29: Internal Painting (Ceiling Area - Cement Paint) | C29: =I29/$G$3 -> 0.035491454 | D29: 0 | E29: =+(1-D29) -> 1 | F29: Sq M | G29: =VLOOKUP(B29,'Internal Finishes Offices'!$B$78:$I$106,4,FALSE) -> 193.752 | H29: =I29/G29 -> 119.2 | I29: =VLOOKUP(B29,'Internal Finishes Offices'!$B$78:$I$106,5,FALSE) -> 23095.238 | J29: =+I29*D29 -> 0 | K29: =+E29*I29 -> 23095.238 | N29: =I29/2 -> 11547.619
B30: Doors & Windows | N30: =I30/2 -> 0
B31: Doors | N31: =I31/2 -> 0
B32: FRD | C32: =I32/$G$3 -> 1.4752736 | D32: 0 | E32: =+(1-D32) -> 1 | F32: Nos. | G32: 32 | H32: =VLOOKUP(B32,Doors!$D$146:$H$149,4,FALSE) -> 30000 | I32: =G32*H32 -> 960000 | J32: =+I32*D32 -> 0 | K32: =+E32*I32 -> 960000 | L32: =SUM(I32:I34)+SUM('Cost Sheet Tower'!I70:I73) -> 44325500 | N32: =I32/2 -> 480000
B33: D1 | C33: =I33/$G$3 -> 0.88516417 | D33: 0 | E33: =+(1-D33) -> 1 | F33: Nos. | G33: 32 | H33: =VLOOKUP(B33,Doors!$D$146:$H$149,4,FALSE) -> 18000 | I33: =G33*H33 -> 576000 | J33: =+I33*D33 -> 0 | K33: =+E33*I33 -> 576000 | N33: =I33/2 -> 288000
B34: D2 | C34: =I34/$G$3 -> 0.51634576 | D34: 0 | E34: =+(1-D34) -> 1 | F34: Nos. | G34: 32 | H34: =VLOOKUP(B34,Doors!$D$146:$H$149,4,FALSE) -> 10500 | I34: =G34*H34 -> 336000 | J34: =+I34*D34 -> 0 | K34: =+E34*I34 -> 336000 | N34: =I34/2 -> 168000
B35: Windows | N35: =I35/2 -> 0
B36: V | C36: =I36/$G$3 -> 0.26201745 | D36: 0 | E36: =+(1-D36) -> 1 | F36: Sq M | G36: ='D&W Schedule'!E19*32*2 -> 28.8 | H36: ='D&W Schedule'!F19 -> 5920.2 | I36: =G36*H36 -> 170501.76 | J36: =+I36*D36 -> 0 | K36: =+E36*I36 -> 170501.76 | L36: =SUM(I36:I38)+SUM('Cost Sheet Tower'!I75:I86) -> 94814945 | N36: =I36/2 -> 85250.88
B37: MS Railing - Staircase | C37: =I37/$G$3 -> 0.1698453 | D37: 0 | E37: =+(1-D37) -> 1 | F37: Sq M | G37: =VLOOKUP(B37,'Internal Finishes Offices'!$B$78:$I$106,4,FALSE) -> 1968 | H37: =I37/G37 -> 56.16 | I37: =VLOOKUP(B37,'Internal Finishes Offices'!$B$78:$I$106,5,FALSE) -> 110522.88 | J37: =+I37*D37 -> 0 | K37: =+E37*I37 -> 110522.88 | N37: =I37/2 -> 55261.44
B38: Curtain Wall | C38: =I38/$G$3 -> 50.777208 | D38: 0 | E38: =+(1-D38) -> 1 | F38: Sq M | G38: ='D&W Schedule'!E33 -> 4722.592 | H38: =I38/G38 -> 6996.6 | I38: ='D&W Schedule'!G33 -> 33042087 | J38: =+I38*D38 -> 0 | K38: =+E38*I38 -> 33042087 | N38: =I38/2 -> 16521044
B39: Miscellenous | J39: =+I39*D39 -> 0 | K39: =+E39*I39 -> 0 | N39: =I39/2 -> 0
B40: Granite Window Frame | C40: =I40/$G$3 -> 0.17418098 | D40: 0 | E40: =+(1-D40) -> 1 | F40: Sq M | G40: =VLOOKUP(B40,'Internal Finishes Offices'!$B$78:$I$106,4,FALSE) -> 655.9272 | H40: =I40/G40 -> 172.8 | I40: =VLOOKUP(B40,'Internal Finishes Offices'!$B$78:$I$106,5,FALSE) -> 113344.22 | J40: =+I40*D40 -> 0 | K40: =+E40*I40 -> 113344.22 | N40: =I40/2 -> 56672.11
B41: Marble Window Frame | C41: =I41/$G$3 -> 0.10596541 | D41: 0 | E41: =+(1-D41) -> 1 | F41: RM | G41: =VLOOKUP(B41,'Internal Finishes Offices'!$B$78:$I$106,4,FALSE) -> 399.0424 | H41: =I41/G41 -> 172.8 | I41: =VLOOKUP(B41,'Internal Finishes Offices'!$B$78:$I$106,5,FALSE) -> 68954.527 | J41: =+I41*D41 -> 0 | K41: =+E41*I41 -> 68954.527 | N41: =I41/2 -> 34477.263
B42: Granite Kitchen Counter - Service Platform | C42: =I42/$G$3 -> 0.53941893 | D42: 0 | E42: =+(1-D42) -> 1 | F42: RM | G42: =VLOOKUP(B42,'Internal Finishes Offices'!$B$78:$I$106,4,FALSE) -> 7312.7984 | H42: =I42/G42 -> 48 | I42: =VLOOKUP(B42,'Internal Finishes Offices'!$B$78:$I$106,5,FALSE) -> 351014.32 | J42: =+I42*D42 -> 0 | K42: =+E42*I42 -> 351014.32 | N42: =I42/2 -> 175507.16
B43: Granite Door Frame | C43: =I43/$G$3 -> 0.36771539 | D43: 0 | E43: =+(1-D43) -> 1 | F43: RM | G43: =VLOOKUP(B43,'Internal Finishes Offices'!$B$78:$I$106,4,FALSE) -> 655.9272 | H43: =I43/G43 -> 364.8 | I43: =VLOOKUP(B43,'Internal Finishes Offices'!$B$78:$I$106,5,FALSE) -> 239282.24 | J43: =+I43*D43 -> 0 | K43: =+E43*I43 -> 239282.24 | N43: =I43/2 -> 119641.12
B44: Granite Basin Counter | C44: =I44/$G$3 -> 0.063031487 | D44: 0 | E44: =+(1-D44) -> 1 | F44: Sq M | G44: =VLOOKUP(B44,'Internal Finishes Offices'!$B$78:$I$106,4,FALSE) -> 6329.672 | H44: =I44/G44 -> 6.48 | I44: =VLOOKUP(B44,'Internal Finishes Offices'!$B$78:$I$106,5,FALSE) -> 41016.275 | J44: =+I44*D44 -> 0 | K44: =+E44*I44 -> 41016.275 | N44: =I44/2 -> 20508.137
B45: Granite Architrave | C45: =I45/$G$3 -> 0.21704068 | D45: 0 | E45: =+(1-D45) -> 1 | F45: Sq M | G45: =VLOOKUP(B45,'Internal Finishes Offices'!$B$78:$I$106,4,FALSE) -> 3043.84 | H45: =I45/G45 -> 46.4 | I45: =VLOOKUP(B45,'Internal Finishes Offices'!$B$78:$I$106,5,FALSE) -> 141234.18 | J45: =+I45*D45 -> 0 | K45: =+E45*I45 -> 141234.18 | N45: =I45/2 -> 70617.088
B46: False Ceiling | J46: =+I46*D46 -> 0 | K46: =+E46*I46 -> 0 | N46: =I46/2 -> 0
B47: False Ceiling - Flats | C47: =I47/$G$3 -> 0 | D47: 0 | E47: =+(1-D47) -> 1 | F47: Sq M | J47: =+I47*D47 -> 0 | K47: =+E47*I47 -> 0 | N47: =I47/2 -> 0
B48: False Ceiling - Common Lobby | C48: =I48/$G$3 -> 0.26686477 | D48: 0 | E48: =+(1-D48) -> 1 | F48: Sq M | G48: =VLOOKUP(B48,'Internal Finishes Offices'!$B$78:$I$106,4,FALSE) -> 1598.454 | H48: =I48/G48 -> 108.64 | I48: =VLOOKUP(B48,'Internal Finishes Offices'!$B$78:$I$106,5,FALSE) -> 173656.04 | J48: =+I48*D48 -> 0 | K48: =+E48*I48 -> 173656.04 | N48: =I48/2 -> 86828.021
B49: TOTAL | C49: =SUM(C5:C48) -> 64.701148 | D49: =SUMPRODUCT(D5:D48,I5:I48)/I49 -> 0 | E49: =1-D49 -> 1 | I49: =SUM(I5:I48) -> 42102768 | J49: =I49-K49 -> 0 | K49: =+E49*I49 -> 42102768
I50: =I49/10^7 -> 4.2102768

Sheet Room Conf
A1: Room Matrix Details
A2: Sr No | B2: Floor No | C2: Flr to Flr Ht | D2: Office 1 | E2: Office 2 | F2: Office 3 | G2: Office 4 | H2: Office 5 | I2: Office 6 | J2: Office 7 | K2: Office 8 | L2: Flat 1A | M2: Flat 1B, 2BHK | N2: Flat 2A | O2: Flat 2B, 2BHK | P2: Flat 3A, 2BHK | Q2: Flat 3B, 3BHK | R2: Flat 4A, 2BHK | S2: Flat 4B, 3BHK | T2: Flat 5A | U2: Flat 5B, 2BHK | V2: Flat 6, 2BHK | W2: Flat 7, 3BHK | X2: Flat 8, 3BHK | Y2: Flat 9, 2BHK | Z2: Flat 10, 2BHK | AA2: Common Lobby 1 | AB2: Common Lobby 2 | AC2: Staircase
A3: 1 | B3: Basement | C3: 4.4 | AA3: 1 | AB3: 1 | AC3: 4
A4: =A3+1 -> 2 | B4: Ground Floor | C4: 4.2 | D4: 1 | E4: 1 | F4: 1 | G4: 1 | H4: 1 | I4: 1 | J4: 1 | K4: 1 | AA4: 1 | AB4: 1 | AC4: 8
A5: =A4+1 -> 3 | B5: 1st Podium | C5: 4.2 | D5: 1 | E5: 1 | F5: 1 | G5: 1 | H5: 1 | I5: 1 | J5: 1 | K5: 1 | AA5: 1 | AB5: 1 | AC5: 8
A6: =A5+1 -> 4 | B6: 2nd Podium | C6: 2.9 | D6: 1 | E6: 1 | F6: 1 | G6: 1 | H6: 1 | I6: 1 | J6: 1 | K6: 1 | AA6: 1 | AB6: 1 | AC6: 8
A7: =A6+1 -> 5 | B7: 3rd Podium | C7: 2.9 | D7: 1 | E7: 1 | F7: 1 | G7: 1 | H7: 1 | I7: 1 | J7: 1 | K7: 1 | AA7: 1 | AB7: 1 | AC7: 8
A8: =A7+1 -> 6 | B8: 4th Podium | C8: 2.9 | AA8: 1 | AB8: 1 | AC8: 4
A9: =A8+1 -> 7 | B9: 5th Podium | C9: 3.5 | P9: 1 | R9: 1 | W9: 1 | X9: 1 | AA9: 1 | AB9: 1 | AC9: 4
A10: =A9+1 -> 8 | B10: 6th Podium | C10: 3.1 | P10: 1 | R10: 1 | W10: 1 | X10: 1 | AA10: 1 | AB10: 1 | AC10: 4
A11: =A10+1 -> 9 | B11: 7th Floor | C11: 3.1 | L11: 1 | N11: 1 | P11: 1 | V11: 1 | X11: 1 | Y11: 1 | Z11: 1 | AA11: 1 | AB11: 1 | AC11: 4
A12: =A11+1 -> 10 | B12: 8th Floor | C12: 3.1 | L12: 1 | N12: 1 | Q12: 1 | S12: 1 | T12: 1 | V12: 1 | W12: 1 | X12: 1 | Y12: 1 | Z12: 1 | AA12: 1 | AB12: 1 | AC12: 4
A13: =A12+1 -> 11 | B13: 9th Floor | C13: 3.1 | L13: 1 | N13: 1 | Q13: 1 | S13: 1 | T13: 1 | V13: 1 | W13: 1 | X13: 1 | Y13: 1 | Z13: 1 | AA13: 1 | AB13: 1 | AC13: 4
A14: =A13+1 -> 12 | B14: 10th Floor | C14: 3.1 | L14: 1 | N14: 1 | Q14: 1 | S14: 1 | T14: 1 | V14: 1 | W14: 1 | X14: 1 | Y14: 1 | Z14: 1 | AA14: 1 | AB14: 1 | AC14: 4
A15: =A14+1 -> 13 | B15: 11th Floor | C15: 3.1 | L15: 1 | N15: 1 | Q15: 1 | S15: 1 | T15: 1 | V15: 1 | W15: 1 | X15: 1 | Y15: 1 | Z15: 1 | AA15: 1 | AB15: 1 | AC15: 4
A16: =A15+1 -> 14 | B16: 12th Floor | C16: 3.1 | L16: 1 | N16: 1 | Q16: 1 | S16: 1 | T16: 1 | V16: 1 | W16: 1 | X16: 1 | Y16: 1 | Z16: 1 | AA16: 1 | AB16: 1 | AC16: 4
A17: =A16+1 -> 15 | B17: 13th Floor | C17: 3.1 | L17: 1 | N17: 1 | Q17: 1 | S17: 1 | T17: 1 | V17: 1 | W17: 1 | X17: 1 | Y17: 1 | Z17: 1 | AA17: 1 | AB17: 1 | AC17: 4
A18: =A17+1 -> 16 | B18: 14th Floor | C18: 3.1 | L18: 1 | N18: 1 | Q18: 1 | V18: 1 | X18: 1 | Y18: 1 | Z18: 1 | AA18: 1 | AB18: 1 | AC18: 4
A19: =A18+1 -> 17 | B19: 15th Floor | C19: 3.1 | L19: 1 | N19: 1 | Q19: 1 | S19: 1 | T19: 1 | V19: 1 | W19: 1 | X19: 1 | Y19: 1 | Z19: 1 | AA19: 1 | AB19: 1 | AC19: 4
A20: =A19+1 -> 18 | B20: 16th Floor | C20: 3.1 | L20: 1 | N20: 1 | Q20: 1 | S20: 1 | T20: 1 | V20: 1 | W20: 1 | X20: 1 | Y20: 1 | Z20: 1 | AA20: 1 | AB20: 1 | AC20: 4
A21: =A20+1 -> 19 | B21: 17th Floor | C21: 3.1 | M21: 1 | O21: 1 | Q21: 1 | S21: 1 | U21: 1 | V21: 1 | W21: 1 | X21: 1 | Y21: 1 | Z21: 1 | AA21: 1 | AB21: 1 | AC21: 4
A22: =A21+1 -> 20 | B22: 18th Floor | C22: 3.1 | M22: 1 | O22: 1 | Q22: 1 | S22: 1 | U22: 1 | V22: 1 | W22: 1 | X22: 1 | Y22: 1 | Z22: 1 | AA22: 1 | AB22: 1 | AC22: 4
A23: =A22+1 -> 21 | B23: 19th Floor | C23: 3.1 | M23: 1 | O23: 1 | Q23: 1 | S23: 1 | U23: 1 | V23: 1 | W23: 1 | X23: 1 | Y23: 1 | Z23: 1 | AA23: 1 | AB23: 1 | AC23: 4
A24: =A23+1 -> 22 | B24: 20th Floor | C24: 3.1 | M24: 1 | O24: 1 | Q24: 1 | S24: 1 | U24: 1 | V24: 1 | W24: 1 | X24: 1 | Y24: 1 | Z24: 1 | AA24: 1 | AB24: 1 | AC24: 4
A25: =A24+1 -> 23 | B25: 21st Floor | C25: 3.1 | M25: 1 | O25: 1 | Q25: 1 | U25: 1 | V25: 1 | X25: 1 | Y25: 1 | Z25: 1 | AA25: 1 | AB25: 1 | AC25: 4
A26: =A25+1 -> 24 | B26: 22nd Floor | C26: 3.1 | M26: 1 | O26: 1 | Q26: 1 | S26: 1 | U26: 1 | V26: 1 | W26: 1 | X26: 1 | Y26: 1 | Z26: 1 | AA26: 1 | AB26: 1 | AC26: 4
A27: =A26+1 -> 25 | B27: 23rd Floor | C27: 3.1 | M27: 1 | O27: 1 | Q27: 1 | S27: 1 | U27: 1 | V27: 1 | W27: 1 | X27: 1 | Y27: 1 | Z27: 1 | AA27: 1 | AB27: 1 | AC27: 4
A28: =A27+1 -> 26 | B28: 24th Floor | C28: 3.1 | M28: 1 | O28: 1 | Q28: 1 | S28: 1 | U28: 1 | V28: 1 | W28: 1 | X28: 1 | Y28: 1 | Z28: 1 | AA28: 1 | AB28: 1 | AC28: 4
A29: =A28+1 -> 27 | B29: 25th Floor | C29: 3.1 | M29: 1 | O29: 1 | Q29: 1 | S29: 1 | U29: 1 | V29: 1 | W29: 1 | X29: 1 | Y29: 1 | Z29: 1 | AA29: 1 | AB29: 1 | AC29: 4
A30: =A29+1 -> 28 | B30: 26th Floor | C30: 3.1 | M30: 1 | O30: 1 | Q30: 1 | S30: 1 | U30: 1 | V30: 1 | W30: 1 | X30: 1 | Y30: 1 | Z30: 1 | AA30: 1 | AB30: 1 | AC30: 4
A31: =A30+1 -> 29 | B31: 27th Floor | C31: 3.1 | M31: 1 | O31: 1 | Q31: 1 | S31: 1 | U31: 1 | V31: 1 | W31: 1 | X31: 1 | Y31: 1 | Z31: 1 | AA31: 1 | AB31: 1 | AC31: 4
A32: =A31+1 -> 30 | B32: 28th Floor | C32: 3.1 | M32: 1 | O32: 1 | Q32: 1 | U32: 1 | V32: 1 | X32: 1 | Y32: 1 | Z32: 1 | AA32: 1 | AB32: 1 | AC32: 4
A33: =A32+1 -> 31 | B33: 29th Floor | C33: 3.1 | M33: 1 | O33: 1 | Q33: 1 | S33: 1 | U33: 1 | V33: 1 | W33: 1 | X33: 1 | Y33: 1 | Z33: 1 | AA33: 1 | AB33: 1 | AC33: 4
A34: =A33+1 -> 32 | B34: 30th Floor | C34: 3.1 | M34: 1 | O34: 1 | Q34: 1 | S34: 1 | U34: 1 | V34: 1 | W34: 1 | X34: 1 | Y34: 1 | Z34: 1 | AA34: 1 | AB34: 1 | AC34: 4
A35: =A34+1 -> 33 | B35: 31st Floor | C35: 3.1 | M35: 1 | O35: 1 | Q35: 1 | S35: 1 | U35: 1 | V35: 1 | W35: 1 | X35: 1 | Y35: 1 | Z35: 1 | AA35: 1 | AB35: 1 | AC35: 4
A36: =A35+1 -> 34 | B36: 32nd Floor | C36: 3.1 | M36: 1 | O36: 1 | Q36: 1 | S36: 1 | U36: 1 | V36: 1 | W36: 1 | X36: 1 | Y36: 1 | Z36: 1 | AA36: 1 | AB36: 1 | AC36: 4
A37: =A36+1 -> 35 | B37: 33rd Floor | C37: 3.1 | M37: 1 | O37: 1 | Q37: 1 | S37: 1 | U37: 1 | V37: 1 | W37: 1 | X37: 1 | Y37: 1 | Z37: 1 | AA37: 1 | AB37: 1 | AC37: 4
A38: =A37+1 -> 36 | B38: 34th Floor | C38: 3.1 | M38: 1 | O38: 1 | Q38: 1 | S38: 1 | U38: 1 | V38: 1 | W38: 1 | X38: 1 | Y38: 1 | Z38: 1 | AA38: 1 | AB38: 1 | AC38: 4
A39: =A38+1 -> 37 | B39: Terrace Floor | C39: 6.5 | AA39: 1 | AB39: 1 | AC39: 4
B40: Total Apartments | C40: =SUM(C3:C39) -> 121.4 | D40: =SUM(D3:D39) -> 4 | E40: =SUM(E3:E39) -> 4 | F40: =SUM(F3:F39) -> 4 | G40: =SUM(G3:G39) -> 4 | H40: =SUM(H3:H39) -> 4 | I40: =SUM(I3:I39) -> 4 | J40: =SUM(J3:J39) -> 4 | ... AC40: =SUM(AC3:AC39) -> 164
B41: Grand Total | D41: =SUM(D40:K40) -> 32 | L41: =SUM(L40:Z40) -> 278
M42: ='Flat Sizes'!D20 -> 70.36 | O42: ='Flat Sizes'!D37 -> 70.14 | Q42: ='Flat Sizes'!D59 -> 95.7 | S42: ='Flat Sizes'!D81 -> 95.72 | U42: ='Flat Sizes'!D98 -> 70.43 | V42: ='Flat Sizes'!D108 -> 70.44 | W42: ='Flat Sizes'!D120 -> 96 | X42: ='Flat Sizes'!D132 -> 95.08 | Y42: ='Flat Sizes'!D142 -> 70.13 | Z42: ='Flat Sizes'!D152 -> 70.37 | AA42: ='Flat Sizes'!D154+'Flat Sizes'!D155+'Flat Sizes'!D156+'Flat Sizes'!D157 -> 138.87 | AC42: ='Flat Sizes'!D161 -> 29.18 | AD42: =SUM(M42:AC42) -> 972.42
K43: 1BHK | L43: =L40+N40+T40 -> 28
K44: 2 | L44: =M40+O40+R40+U40+V40+Y40+Z40+P40 -> 143 | AD44: =AD42*1.12 -> 1089.1104
K45: 3 | L45: =Q40+S40+W40+X40 -> 107 | AD45: =AD44*1.08 -> 1176.2392
A46: Flat 1A | B46: Multipurpose Room
A47: Flat 2A | B47: Multipurpose Room
A48: Flat 5A | B48: Multipurpose Room

Sheet Flat Sizes
A1: Flat Sizes
A2: Sr.No | B2: Type of Apartment | C2: No.of Apartment per floor | D2: Area in Sq.m | E2: Area in Sq.ft | F2: Total Area | G2: Perimeter in Rmt | H2: Nos | I2: Area In Sft
A4: 1 | B4: ='Room Conf'!L2 -> Flat 1A | H4: ='Room Conf'!L40 -> 10 | I4: =+H4*F10 -> 5032.17
A5: 1 | B5: Multi Purpose Room | C5: 1 | D5: 22.05 | E5: =D5*10.764 -> 237.3462 | F5: =E5*C5 -> 237.3462 | G5: 19.39
A6: 2 | B6: Study Room | C6: 1 | D6: 5.47 | E6: =D6*10.764 -> 58.87908 | F6: =E6*C6 -> 58.87908 | G6: 9.77
A7: 3 | B7: M. Bedroom | C7: 1 | D7: 12.42 | E7: =D7*10.764 -> 133.68888 | F7: =E7*C7 -> 133.68888 | G7: 14.75
A8: 4 | B8: M. Toilet | C8: 1 | D8: 3.46 | E8: =D8*10.764 -> 37.24344 | F8: =E8*C8 -> 37.24344 | G8: 7.91
A9: 5 | B9: C. Toilet | C9: 1 | D9: 3.35 | E9: =D9*10.764 -> 36.0594 | F9: =E9*C9 -> 36.0594 | G9: 7.76
B10: Sub Total | D10: =SUM(D5:D9) -> 46.75 | E10: =SUM(E5:E9) -> 503.217 | F10: =SUM(F5:F9) -> 503.217
A11: 2 | B11: ='Room Conf'!M2 -> Flat 1B, 2BHK | H11: ='Room Conf'!M40 -> 18 | I11: =+H11*F20 -> 13632.391
A12: 1 | B12: Living, Dining & Passage | C12: 1 | D12: 25.47 | E12: =D12*10.764 -> 274.15908 | F12: =E12*C12 -> 274.15908 | G12: 22.71
A13: 2 | B13: M. Bedroom | C13: 1 | D13: 15.79 | E13: =D13*10.764 -> 169.96356 | F13: =E13*C13 -> 169.96356 | G13: 19.49
A14: 3 | B14: M. Toilet | C14: 1 | D14: 3.46 | E14: =D14*10.764 -> 37.24344 | F14: =E14*C14 -> 37.24344 | G14: 7.92
A15: 4 | B15: C.Bedroom | C15: 1 | D15: 10.67 | E15: =D15*10.764 -> 114.85188 | F15: =E15*C15 -> 114.85188 | G15: 13.55
A16: 5 | B16: C. Toilet | C16: 1 | D16: 3.35 | E16: =D16*10.764 -> 36.0594 | F16: =E16*C16 -> 36.0594 | G16: 7.76
A17: 6 | B17: Kitchen | C17: 1 | D17: 6.41 | E17: =D17*10.764 -> 68.99724 | F17: =E17*C17 -> 68.99724 | G17: 10.99
A18: 7 | B18: Utility | C18: 1 | D18: 2.61 | E18: =D18*10.764 -> 28.09404 | F18: =E18*C18 -> 28.09404 | G18: 6.71
A19: 8 | B19: Balcony | C19: 1 | D19: 2.6 | E19: =D19*10.764 -> 27.9864 | F19: =E19*C19 -> 27.9864 | G19: 6.7
B20: Sub Total | D20: =SUM(D12:D19) -> 70.36 | E20: =SUM(E12:E19) -> 757.35504 | F20: =SUM(F12:F19) -> 757.35504
A21: 3 | B21: ='Room Conf'!N2 -> Flat 2A | H21: ='Room Conf'!N40 -> 10 | I21: =+H21*F27 -> 4708.1736
A22: 1 | B22: Multi Purpose Room | C22: 1 | D22: 21.86 | E22: =D22*10.764 -> 235.30104 | F22: =E22*C22 -> 235.30104 | G22: 19.09
A23: 2 | B23: Study Room | C23: 1 | D23: 6.96 | E23: =D23*10.764 -> 74.91744 | F23: =E23*C23 -> 74.91744 | G23: 11.08
A24: 3 | B24: M. Bedroom | C24: 1 | D24: 9.48 | E24: =D24*10.764 -> 102.04272 | F24: =E24*C24 -> 102.04272 | G24: 14.59
A25: 4 | B25: M. Toilet | C25: 1 | D25: 2.57 | E25: =D25*10.764 -> 27.66348 | F25: =E25*C25 -> 27.66348 | G25: 6.75
A26: 5 | B26: C. Toilet | C26: 1 | D26: 2.87 | E26: =D26*10.764 -> 30.89268 | F26: =E26*C26 -> 30.89268 | G26: 7.05
B27: Sub Total | D27: =SUM(D22:D26) -> 43.74 | E27: =SUM(E22:E26) -> 470.81736 | F27: =SUM(F22:F26) -> 470.81736
A28: 4 | B28: ='Room Conf'!O2 -> Flat 2B, 2BHK | H28: ='Room Conf'!O40 -> 18 | I28: =+H28*F37 -> 13589.765
A29: 1 | B29: Living, Dining & Passage | C29: 1 | D29: 25.4 | E29: =D29*10.764 -> 273.4056 | F29: =E29*C29 -> 273.4056 | G29: 22.55
A30: 2 | B30: M. Bedroom | C30: 1 | D30: 15.45 | E30: =D30*10.764 -> 166.3038 | F30: =E30*C30 -> 166.3038 | G30: 19.33
A31: 3 | B31: M. Toilet | C31: 1 | D31: 3.39 | E31: =D31*10.764 -> 36.48996 | F31: =E31*C31 -> 36.48996 | G31: 7.94
A32: 4 | B32: C.Bedroom | C32: 1 | D32: 10.63 | E32: =D32*10.764 -> 114.42132 | F32: =E32*C32 -> 114.42132 | G32: 13.55
A33: 5 | B33: C. Toilet | C33: 1 | D33: 3.47 | E33: =D33*10.764 -> 37.35108 | F33: =E33*C33 -> 37.35108 | G33: 7.94
A34: 6 | B34: Kitchen | C34: 1 | D34: 6.93 | E34: =D34*10.764 -> 74.59452 | F34: =E34*C34 -> 74.59452 | G34: 11.08
A35: 7 | B35: Utility | C35: 1 | D35: 2.27 | E35: =D35*10.764 -> 24.43428 | F35: =E35*C35 -> 24.43428 | G35: 6.1
A36: 8 | B36: Balcony | C36: 1 | D36: 2.6 | E36: =D36*10.764 -> 27.9864 | F36: =E36*C36 -> 27.9864 | G36: 6.7
B37: Sub Total | D37: =SUM(D29:D36) -> 70.14 | E37: =SUM(E29:E36) -> 754.98696 | F37: =SUM(F29:F36) -> 754.98696
A38: 5 | B38: ='Room Conf'!P2 -> Flat 3A, 2BHK | H38: ='Room Conf'!P40 -> 3 | I38: =+H38*F47 -> 2269.4818
A39: 1 | B39: Living, Dining & Passage | C39: 1 | D39: 28.59 | E39: =D39*10.764 -> 307.74276 | F39: =E39*C39 -> 307.74276 | G39: 29.11
A40: 2 | B40: M. Bedroom | C40: 1 | D40: 11.26 | E40: =D40*10.764 -> 121.20264 | F40: =E40*C40 -> 121.20264 | G40: 13.29
A41: 3 | B41: M. Toilet | C41: 1 | D41: 3.9 | E41: =D41*10.764 -> 41.9796 | F41: =E41*C41 -> 41.9796 | G41: 8.27
A42: 4 | B42: M. Bedroom | C42: 1 | D42: 11.02 | E42: =D42*10.764 -> 118.61928 | F42: =E42*C42 -> 118.61928 | G42: 13.7
A43: 5 | B43: M. Toilet | C43: 1 | D43: 3.83 | E43: =D43*10.764 -> 41.22612 | F43: =E43*C43 -> 41.22612 | G43: 8.22
A44: 6 | B44: Kitchen | C44: 1 | D44: 6.13 | E44: =D44*10.764 -> 65.98332 | F44: =E44*C44 -> 65.98332 | G44: 10.39
A45: 7 | B45: Utility | C45: 1 | D45: 2.75 | E45: =D45*10.764 -> 29.601 | F45: =E45*C45 -> 29.601 | G45: 7.05
A46: 8 | B46: Balcony | C46: 1 | D46: 2.8 | E46: =D46*10.764 -> 30.1392 | F46: =E46*C46 -> 30.1392 | G46: 7.01
B47: Sub Total | D47: =SUM(D39:D46) -> 70.28 | E47: =SUM(E39:E46) -> 756.49392 | F47: =SUM(F39:F46) -> 756.49392
A48: 6 | B48: ='Room Conf'!Q2 -> Flat 3B, 3BHK | H48: ='Room Conf'!Q40 -> 27 | I48: =+H48*F59 -> 27188.611
A49: 1 | B49: Living, Dining & Passage | C49: 1 | D49: 30.36 | E49: =D49*10.764 -> 326.79504 | F49: =E49*C49 -> 326.79504 | G49: 31.47
A50: 2 | B50: M. Bedroom | C50: 1 | D50: 15.29 | E50: =D50*10.764 -> 164.58156 | F50: =E50*C50 -> 164.58156 | G50: 18.32
A51: 3 | B51: M. Toilet | C51: 1 | D51: 3.9 | E51: =D51*10.764 -> 41.9796 | F51: =E51*C51 -> 41.9796 | G51: 8.27
A52: 4 | B52: M. Bedroom | C52: 1 | D52: 14.58 | E52: =D52*10.764 -> 156.93912 | F52: =E52*C52 -> 156.93912 | G52: 17.35
A53: 5 | B53: M. Toilet | C53: 1 | D53: 3.82 | E53: =D53*10.764 -> 41.11848 | F53: =E53*C53 -> 41.11848 | G53: 8.21
A54: 6 | B54: C. Bedroom | C54: 1 | D54: 10.47 | E54: =D54*10.764 -> 112.69908 | F54: =E54*C54 -> 112.69908 | G54: 13.43
A55: 7 | B55: C. Toilet | C55: 1 | D55: 3.83 | E55: =D55*10.764 -> 41.22612 | F55: =E55*C55 -> 41.22612 | G55: 8.22
A56: 8 | B56: Kitchen | C56: 1 | D56: 7.83 | E56: =D56*10.764 -> 84.28212 | F56: =E56*C56 -> 84.28212 | G56: 11.93
A57: 9 | B57: Balcony | C57: 1 | D57: 2.8 | E57: 7.01 | F57: =E57*C57 -> 7.01 | G57: 7.01
A58: 10 | B58: Utility | C58: 1 | D58: 2.82 | E58: =D58*10.764 -> 30.35448 | F58: =E58*C58 -> 30.35448 | G58: 7.05
B59: Sub Total | D59: =SUM(D49:D58) -> 95.7 | E59: =SUM(E49:E58) -> 1006.9856 | F59: =SUM(F49:F58) -> 1006.9856
A60: 7 | B60: ='Room Conf'!R2 -> Flat 4A, 2BHK | H60: ='Room Conf'!R40 -> 2 | I60: =+H60*SUM(F61:F68) -> 1512.9878
A61: 1 | B61: Living, Dining & Passage | C61: 1 | D61: 28.59 | E61: =D61*10.764 -> 307.74276 | F61: =E61*C61 -> 307.74276 | G61: 29.12
A62: 2 | B62: M. Bedroom | C62: 1 | D62: 11.01 | E62: =D62*10.764 -> 118.51164 | F62: =E62*C62 -> 118.51164 | G62: 13.69
A63: 3 | B63: M. Toilet | C63: 1 | D63: 3.83 | E63: =D63*10.764 -> 41.22612 | F63: =E63*C63 -> 41.22612 | G63: 8.21
A64: 4 | B64: M. Bedroom | C64: 1 | D64: 11.26 | E64: =D64*10.764 -> 121.20264 | F64: =E64*C64 -> 121.20264 | G64: 13.7
A65: 5 | B65: M. Toilet | C65: 1 | D65: 3.9 | E65: =D65*10.764 -> 41.9796 | F65: =E65*C65 -> 41.9796 | G65: 8.27
A66: 6 | B66: Kitchen | C66: 1 | D66: 6.14 | E66: =D66*10.764 -> 66.09096 | F66: =E66*C66 -> 66.09096 | G66: 10.4
A67: 7 | B67: Utility | C67: 1 | D67: 2.75 | E67: =D67*10.764 -> 29.601 | F67: =E67*C67 -> 29.601 | G67: 7.05
A68: 8 | B68: Balcony | C68: 1 | D68: 2.8 | E68: =D68*10.764 -> 30.1392 | F68: =E68*C68 -> 30.1392 | G68: 7.01
B69: Sub Total | D69: =SUM(D61:D68) -> 70.28 | E69: =SUM(E61:E68) -> 756.49392 | F69: =SUM(F60:F68) -> 756.49392
A70: 8 | B70: ='Room Conf'!S2 -> Flat 4B, 3BHK | H70: ='Room Conf'!S40 -> 24 | I70: =+H70*SUM(F71:F80) -> 24727.922
A71: 1 | B71: Living, Dining & Passage | C71: 1 | D71: 30.55 | E71: =D71*10.764 -> 328.8402 | F71: =E71*C71 -> 328.8402 | G71: 31.89 | L71: =95*10.764 -> 1022.58
A72: 2 | B72: M. Bedroom | C72: 1 | D72: 14.53 | E72: =D72*10.764 -> 156.40092 | F72: =E72*C72 -> 156.40092 | G72: 17.23
A73: 3 | B73: M. Toilet | C73: 1 | D73: 3.83 | E73: =D73*10.764 -> 41.22612 | F73: =E73*C73 -> 41.22612 | G73: 8.22
A74: 4 | B74: M. Bedroom | C74: 1 | D74: 15.16 | E74: =D74*10.764 -> 163.18224 | F74: =E74*C74 -> 163.18224 | G74: 18.02
A75: 5 | B75: M. Toilet | C75: 1 | D75: 3.9 | E75: =D75*10.764 -> 41.9796 | F75: =E75*C75 -> 41.9796 | G75: 8.27
A76: 6 | B76: C. Bedroom | C76: 1 | D76: 10.47 | E76: =D76*10.764 -> 112.69908 | F76: =E76*C76 -> 112.69908 | G76: 13.43
A77: 7 | B77: C. Toilet | C77: 1 | D77: 3.83 | E77: =D77*10.764 -> 41.22612 | F77: =E77*C77 -> 41.22612 | G77: 8.22
A78: 8 | B78: Kitchen | C78: 1 | D78: 7.83 | E78: =D78*10.764 -> 84.28212 | F78: =E78*C78 -> 84.28212 | G78: 11.93
A79: 9 | B79: Utility | C79: 1 | D79: 2.82 | E79: =D79*10.764 -> 30.35448 | F79: =E79*C79 -> 30.35448 | G79: 7.05
A80: 10 | B80: Balcony | C80: 1 | D80: 2.8 | E80: =D80*10.764 -> 30.1392 | F80: =E80*C80 -> 30.1392 | G80: 7.01
B81: Sub Total | D81: =SUM(D71:D80) -> 95.72 | E81: =SUM(E71:E80) -> 1030.3301 | F81: =SUM(F71:F80) -> 1030.3301
A82: 9 | B82: ='Room Conf'!T2 -> Flat 5A | H82: ='Room Conf'!T40 -> 8 | I82: =+H82*SUM(F83:F87) -> 3999.9024
A83: 1 | B83: Multi Purpose Room | C83: 1 | D83: 25.44 | E83: =D83*10.764 -> 273.83616 | F83: =E83*C83 -> 273.83616 | G83: 23.86
A84: 2 | B84: Study Room | C84: 1 | D84: 6.91 | E84: =D84*10.764 -> 74.37924 | F84: =E84*C84 -> 74.37924 | G84: 11.06
A85: 3 | B85: M. Bedroom | C85: 1 | D85: 8.6 | E85: =D85*10.764 -> 92.5704 | F85: =E85*C85 -> 92.5704 | G85: 12.5
A86: 4 | B86: M. Toilet | C86: 1 | D86: 2.43 | E86: =D86*10.764 -> 26.15652 | F86: =E86*C86 -> 26.15652 | G86: 6.54
A87: 5 | B87: C. Toilet | C87: 1 | D87: 3.07 | E87: =D87*10.764 -> 33.04548 | F87: =E87*C87 -> 33.04548 | G87: 7.35
B88: Sub Total | D88: =SUM(D83:D87) -> 46.45 | E88: =SUM(E83:E87) -> 499.9878 | F88: =SUM(F83:F87) -> 499.9878
A89: 10 | B89: ='Room Conf'!U2 -> Flat 5B, 2BHK | H89: ='Room Conf'!U40 -> 18 | I89: =+H89*SUM(F90:F97) -> 13645.953
A90: 1 | B90: Living, Dining & Passage | C90: 1 | D90: 28.62 | E90: =D90*10.764 -> 308.06568 | F90: =E90*C90 -> 308.06568 | G90: 29.32
A91: 2 | B91: M. Bedroom | C91: 1 | D91: 13.68 | E91: =D91*10.764 -> 147.25152 | F91: =E91*C91 -> 147.25152 | G91: 14.11
A92: 3 | B92: M. Toilet | C92: 1 | D92: 3.27 | E92: =D92*10.764 -> 35.19828 | F92: =E92*C92 -> 35.19828 | G92: 7.64
A93: 4 | B93: C. Bedroom | C93: 1 | D93: 10.62 | E93: =D93*10.764 -> 114.31368 | F93: =E93*C93 -> 114.31368 | G93: 13.56
A94: 5 | B94: C. Toilet | C94: 1 | D94: 3.25 | E94: =D94*10.764 -> 34.983 | F94: =E94*C94 -> 34.983 | G94: 7.61
A95: 6 | B95: Kitchen | C95: 1 | D95: 6.92 | E95: =D95*10.764 -> 74.48688 | F95: =E95*C95 -> 74.48688 | G95: 11.06
A96: 7 | B96: Utility | C96: 1 | D96: 1.84 | E96: =D96*10.764 -> 19.80576 | F96: =E96*C96 -> 19.80576 | G96: 5.61
A97: 8 | B97: Balcony | C97: 1 | D97: 2.23 | E97: =D97*10.764 -> 24.00372 | F97: =E97*C97 -> 24.00372 | G97: 6.1
B98: Sub Total | D98: =SUM(D90:D97) -> 70.43 | E98: =SUM(E90:E97) -> 758.10852 | F98: =SUM(F90:F97) -> 758.10852
A99: 11 | B99: ='Room Conf'!V2 -> Flat 6, 2BHK | H99: ='Room Conf'!V40 -> 28 | I99: =+H99*SUM(F100:F107) -> 21230.052
A100: 1 | B100: Living, Dining & Passage | C100: 1 | D100: 28.62 | E100: =D100*10.764 -> 308.06568 | F100: =E100*C100 -> 308.06568 | G100: 29.32
A101: 2 | B101: M. Bedroom | C101: 1 | D101: 13.69 | E101: =D101*10.764 -> 147.35916 | F101: =E101*C101 -> 147.35916 | G101: 15.11
...

Sheet Office Sizes
A1: Office Sizes
A2: Sr.No | B2: Type of Apartment | C2: No.of Apartment per floor | D2: Area in Sq.m | E2: Area in Sq.ft | F2: Total Area | G2: Perimeter in Rmt | H2: Nos | I2: Area In Sft
A4: 1 | B4: ='Room Conf'!D2 -> Office 1 | H4: ='Room Conf'!D40 -> 4 | I4: =+H4*F8 -> 1618.9056
A5: 1 | B5: Office | C5: 1 | D5: 33.47 | E5: =D5*10.764 -> 360.27108 | F5: =E5*C5 -> 360.27108 | G5: 19.39
A6: 2 | B6: Pantry | C6: 1 | D6: 2.07 | E6: =D6*10.764 -> 22.28148 | F6: =E6*C6 -> 22.28148 | G6: 6.04
A7: 3 | B7: WC | C7: 1 | D7: 2.06 | E7: =D7*10.764 -> 22.17384 | F7: =E7*C7 -> 22.17384 | G7: 5.82
B8: Sub Total | D8: =SUM(D5:D7) -> 37.6 | E8: =SUM(E5:E7) -> 404.7264 | F8: =SUM(F5:F7) -> 404.7264
A9: 2 | B9: ='Room Conf'!E2 -> Office 2 | H9: ='Room Conf'!E40 -> 4 | I9: =+H9*F13 -> 1567.669
A10: 1 | B10: Office | C10: 1 | D10: 31.85 | E10: =D10*10.764 -> 342.8334 | F10: =E10*C10 -> 342.8334 | G10: 24.91
A11: 2 | B11: Pantry | C11: 1 | D11: 2.5 | E11: =D11*10.764 -> 26.91 | F11: =E11*C11 -> 26.91 | G11: 6.72
A12: 3 | B12: WC | C12: 1 | D12: 2.06 | E12: =D12*10.764 -> 22.17384 | F12: =E12*C12 -> 22.17384 | G12: 6.12
B13: Sub Total | D13: =SUM(D10:D12) -> 36.41 | E13: =SUM(E10:E12) -> 391.91724 | F13: =SUM(F10:F12) -> 391.91724
A14: 3 | B14: ='Room Conf'!F2 -> Office 3 | H14: ='Room Conf'!F40 -> 4 | I14: =+H14*F18 -> 1329.5693
A15: 1 | B15: Office | C15: 1 | D15: 21.86 | E15: =D15*10.764 -> 235.30104 | F15: =E15*C15 -> 235.30104 | G15: 19.09
A16: 2 | B16: Pantry | C16: 1 | D16: 6.96 | E16: =D16*10.764 -> 74.91744 | F16: =E16*C16 -> 74.91744 | G16: 11.08
A17: 3 | B17: WC | C17: 1 | D17: 2.06 | E17: =D17*10.764 -> 22.17384 | F17: =E17*C17 -> 22.17384 | G17: 14.59
B18: Sub Total | D18: =SUM(D15:D17) -> 30.88 | E18: =SUM(E15:E17) -> 332.39232 | F18: =SUM(F15:F17) -> 332.39232
A19: 4 | B19: ='Room Conf'!G2 -> Office 4 | H19: ='Room Conf'!G40 -> 4 | I19: =+H19*F23 -> 3686.8853
A20: 1 | B20: Office | C20: 1 | D20: 81.65 | E20: =D20*10.764 -> 878.8806 | F20: =E20*C20 -> 878.8806 | G20: 38.64
A21: 2 | B21: Pantry | C21: 1 | D21: 1.92 | E21: =D21*10.764 -> 20.66688 | F21: =E21*C21 -> 20.66688 | G21: 5.82
A22: 3 | B22: WC | C22: 1 | D22: 2.06 | E22: =D22*10.764 -> 22.17384 | F22: =E22*C22 -> 22.17384 | G22: 5.82
B23: Sub Total | D23: =SUM(D20:D22) -> 85.63 | E23: =SUM(E20:E22) -> 921.72132 | F23: =SUM(F20:F22) -> 921.72132
A24: 5 | B24: ='Room Conf'!H2 -> Office 5 | H24: ='Room Conf'!H40 -> 4 | I24: =+H24*F28 -> 2132.1331
A25: 1 | B25: Office | C25: 1 | D25: 45.39 | E25: =D25*10.764 -> 488.57796 | F25: =E25*C25 -> 488.57796 | G25: 30.18
A26: 2 | B26: Pantry | C26: 1 | D26: 2.07 | E26: =D26*10.764 -> 22.28148 | F26: =E26*C26 -> 22.28148 | G26: 6.04
A27: 3 | B27: WC | C27: 1 | D27: 2.06 | E27: =D27*10.764 -> 22.17384 | F27: =E27*C27 -> 22.17384 | G27: 5.82
B28: Sub Total | D28: =SUM(D25:D27) -> 49.52 | E28: =SUM(E25:E27) -> 533.03328 | F28: =SUM(F25:F27) -> 533.03328
A29: 6 | B29: ='Room Conf'!I2 -> Office 6 | H29: ='Room Conf'!I40 -> 4 | I29: =+H29*F33 -> 1559.4883
A30: 1 | B30: Office | C30: 1 | D30: 32.09 | E30: =D30*10.764 -> 345.41676 | F30: =E30*C30 -> 345.41676 | G30: 24.96
A31: 2 | B31: Pantry | C31: 1 | D31: 2.07 | E31: =D31*10.764 -> 22.28148 | F31: =E31*C31 -> 22.28148 | G31: 6.04
A32: 3 | B32: WC | C32: 1 | D32: 2.06 | E32: =D32*10.764 -> 22.17384 | F32: =E32*C32 -> 22.17384 | G32: 5.82
B33: Sub Total | D33: =SUM(D30:D32) -> 36.22 | E33: =SUM(E30:E32) -> 389.87208 | F33: =SUM(F30:F32) -> 389.87208
A34: 7 | B34: ='Room Conf'!J2 -> Office 7 | H34: ='Room Conf'!J40 -> 4 | I34: =+H34*SUM(F35:F37) -> 1578.433
A35: 1 | B35: Office | C35: 1 | D35: =32.53 -> 32.53 | E35: =D35*10.764 -> 350.15292 | F35: =E35*C35 -> 350.15292 | G35: 24.9
A36: 2 | B36: Pantry | C36: 1 | D36: 2.07 | E36: =D36*10.764 -> 22.28148 | F36: =E36*C36 -> 22.28148 | G36: 6.04
A37: 3 | B37: WC | C37: 1 | D37: 2.06 | E37: =D37*10.764 -> 22.17384 | F37: =E37*C37 -> 22.17384 | G37: 5.82
B38: Sub Total | D38: =SUM(D35:D37) -> 36.66 | E38: =SUM(E35:E37) -> 394.60824 | F38: =SUM(F34:F37) -> 394.60824
A39: 8 | B39: ='Room Conf'!K2 -> Office 8 | H39: ='Room Conf'!K40 -> 4 | I39: =+H39*SUM(F40:F42) -> 1618.9056
A40: 1 | B40: Office | C40: 1 | D40: 33.47 | E40: =D40*10.764 -> 360.27108 | F40: =E40*C40 -> 360.27108 | G40: 25.54
A41: 2 | B41: Pantry | C41: 1 | D41: 2.07 | E41: =D41*10.764 -> 22.28148 | F41: =E41*C41 -> 22.28148 | G41: 6.04
A42: 3 | B42: WC | C42: 1 | D42: 2.06 | E42: =D42*10.764 -> 22.17384 | F42: =E42*C42 -> 22.17384 | G42: 5.82
B43: Sub Total | D43: =SUM(D40:D42) -> 37.6 | E43: =SUM(E40:E42) -> 404.7264 | F43: =SUM(F40:F42) -> 404.7264
A44: 9 | B44: Common Area
A45: 1 | B45: Lobby | C45: 4 | D45: 13.58 | E45: =D45*10.764 -> 146.17512 | F45: =E45*C45 -> 584.70048 | G45: 18.24 | H45: 4 | I45: =F45*H45 -> 2338.8019
A46: 2 | B46: Lifts | C46: 4 | D46: 3.62 | E46: =D46*10.764 -> 38.96568 | F46: =E46*C46 -> 155.86272 | G46: 7.63 | H46: 4 | I46: =F46*H46 -> 623.45088
A47: 3 | B47: Staircase | C47: 4 | D47: 13.81 | E47: =D47*10.764 -> 148.65084 | F47: =E47*C47 -> 594.60336 | G47: 14.9 | H47: 4 | I47: =F47*H47 -> 2378.4134
B48: Total | I48: =SUM(I4:I47) -> 20432.655

Sheet Waterproofing
A1: Waterproofing Work details
A2: Sr no | B2: Item | C2: Unit | D2: No | E2: Area | F2: Perimeter | G2: Ht. | H2: Quantity (sq.m) | J2: Sunk Filling in cum | K2: Total Nos. | L2: WP Area Sq.m | M2: Sunk Cu.m
H3: Floor | I3: Wall
A4: A | B4: Lift Pits
A5: 1 | B5: Passenger | C5: Sq M | D5: 1 | E5: ='Flat Sizes'!D158 -> 59.78 | F5: ='Flat Sizes'!G158 -> 95.94 | G5: 2 | H5: =D5*E5 -> 59.78 | I5: =F5*G5*D5 -> 191.88 | J5: =E5*0.3*D5 -> 17.934 | K5: 1 | L5: =SUM(H5:I5)*K5 -> 251.66 | M5: =J5*K5 -> 17.934 | N5: Lift Pit Basecoat | O5: Lift Pit Brickbat
A6: =+CHAR(CODE(A4)+1) -> B | B6: For Toilet, Utility and Balcony
A7: 1 | B7: ='Flat Sizes'!B4 -> Flat 1A
B8: ='Flat Sizes'!B8 -> M. Toilet | C8: Sq M | D8: 1 | E8: ='Flat Sizes'!D8 -> 3.46 | F8: ='Flat Sizes'!G8 -> 7.91 | G8: 1.2 | H8: =D8*E8 -> 3.46 | I8: =F8*G8*D8 -> 9.492 | J8: =E8*0.3*D8 -> 1.038 | K8: ='Flat Sizes'!H4 -> 10 | L8: =SUM(H8:I8)*K8 -> 129.52 | M8: =J8*K8 -> 10.38 | N8: Toilet Basecoat | O8: Toilet Brickbat
B9: ='Flat Sizes'!B9 -> C. Toilet | C9: Sq M | D9: 1 | E9: ='Flat Sizes'!D9 -> 3.35 | F9: ='Flat Sizes'!G9 -> 7.76 | G9: 1.2 | H9: =D9*E9 -> 3.35 | I9: =F9*G9*D9 -> 9.312 | J9: =E9*0.3*D9 -> 1.005 | K9: ='Flat Sizes'!H4 -> 10 | L9: =SUM(H9:I9)*K9 -> 126.62 | M9: =J9*K9 -> 10.05 | N9: Toilet Basecoat | O9: Toilet Brickbat
A10: 2 | B10: ='Flat Sizes'!B11 -> Flat 1B, 2BHK
B11: ='Flat Sizes'!B14 -> M. Toilet | C11: Sq M | D11: 1 | E11: ='Flat Sizes'!D14 -> 3.46 | F11: ='Flat Sizes'!G14 -> 7.92 | G11: 1.2 | H11: =D11*E11 -> 3.46 | I11: =F11*G11*D11 -> 9.504 | J11: =E11*0.3*D11 -> 1.038 | K11: ='Flat Sizes'!$H$11 -> 18 | L11: =SUM(H11:I11)*K11 -> 233.352 | M11: =J11*K11 -> 18.684 | N11: Toilet Basecoat | O11: Toilet Brickbat
B12: ='Flat Sizes'!B16 -> C. Toilet | C12: Sq M | D12: 1 | E12: ='Flat Sizes'!D16 -> 3.35 | F12: ='Flat Sizes'!G16 -> 7.76 | G12: 1.2 | H12: =D12*E12 -> 3.35 | I12: =F12*G12*D12 -> 9.312 | J12: =E12*0.3*D12 -> 1.005 | K12: ='Flat Sizes'!$H$11 -> 18 | L12: =SUM(H12:I12)*K12 -> 227.916 | M12: =J12*K12 -> 18.09 | N12: Toilet Basecoat | O12: Toilet Brickbat
B13: ='Flat Sizes'!B17 -> Kitchen | C13: Sq M | D13: 1 | E13: =(0.6*2.5) -> 1.5 | F13: =(2.5+0.6)*2 -> 6.2 | G13: 1.2 | H13: =D13*E13 -> 1.5 | I13: =F13*G13*D13 -> 7.44 | J13: =E13*0.3*D13 -> 0.45 | K13: ='Flat Sizes'!$H$11 -> 18 | L13: =SUM(H13:I13)*K13 -> 160.92 | M13: =J13*K13 -> 8.1 | N13: Kitchen Basecoat | O13: Kitchen Brickbat
B14: ='Flat Sizes'!B18 -> Utility | C14: Sq M | D14: 1 | E14: ='Flat Sizes'!D18 -> 2.61 | F14: ='Flat Sizes'!G18 -> 6.71 | G14: 1.2 | H14: =D14*E14 -> 2.61 | I14: =F14*G14*D14 -> 8.052 | J14: =E14*0.3*D14 -> 0.783 | K14: ='Flat Sizes'!$H$11 -> 18 | L14: =SUM(H14:I14)*K14 -> 191.916 | M14: =J14*K14 -> 14.094 | N14: Utility Basecoat | O14: Utility Brickbat
B15: ='Flat Sizes'!B19 -> Balcony | C15: Sq M | D15: 1 | E15: ='Flat Sizes'!D19 -> 2.6 | F15: ='Flat Sizes'!G19 -> 6.7 | G15: 1.2 | H15: =D15*E15 -> 2.6 | I15: =F15*G15*D15 -> 8.04 | J15: =E15*0.3*D15 -> 0.78 | K15: ='Flat Sizes'!$H$11 -> 18 | L15: =SUM(H15:I15)*K15 -> 191.52 | M15: =J15*K15 -> 14.04 | N15: Balcony Basecoat | O15: Balcony Brickbat
A16: 3 | B16: ='Flat Sizes'!B21 -> Flat 2A
B17: ='Flat Sizes'!B25 -> M. Toilet | C17: Sq M | D17: 1 | E17: ='Flat Sizes'!D25 -> 2.57 | F17: ='Flat Sizes'!G25 -> 6.75 | G17: 1.2 | H17: =D17*E17 -> 2.57 | I17: =F17*G17*D17 -> 8.1 | J17: =E17*0.3*D17 -> 0.771 | K17: ='Flat Sizes'!H21 -> 10 | L17: =SUM(H17:I17)*K17 -> 106.7 | M17: =J17*K17 -> 7.71 | N17: Toilet Basecoat | O17: Toilet Brickbat
B18: ='Flat Sizes'!B26 -> C. Toilet | C18: Sq M | D18: 1 | E18: ='Flat Sizes'!D26 -> 2.87 | F18: ='Flat Sizes'!G26 -> 7.05 | G18: 1.2 | H18: =D18*E18 -> 2.87 | I18: =F18*G18*D18 -> 8.46 | J18: =E18*0.3*D18 -> 0.861 | K18: ='Flat Sizes'!H21 -> 10 | L18: =SUM(H18:I18)*K18 -> 113.3 | M18: =J18*K18 -> 8.61 | N18: Toilet Basecoat | O18: Toilet Brickbat
A19: 4 | B19: ='Flat Sizes'!B28 -> Flat 2B, 2BHK
B20: ='Flat Sizes'!B31 -> M. Toilet | C20: Sq M | D20: 1 | E20: ='Flat Sizes'!D31 -> 3.39 | F20: ='Flat Sizes'!G31 -> 7.94 | G20: 1.2 | H20: =D20*E20 -> 3.39 | I20: =F20*G20*D20 -> 9.528 | J20: =E20*0.3*D20 -> 1.017 | K20: ='Flat Sizes'!$H$28 -> 18 | L20: =SUM(H20:I20)*K20 -> 232.524 | M20: =J20*K20 -> 18.306 | N20: Toilet Basecoat | O20: Toilet Brickbat
B21: ='Flat Sizes'!B33 -> C. Toilet | C21: Sq M | D21: 1 | E21: ='Flat Sizes'!D33 -> 3.47 | F21: ='Flat Sizes'!G33 -> 7.94 | G21: 1.2 | H21: =D21*E21 -> 3.47 | I21: =F21*G21*D21 -> 9.528 | J21: =E21*0.3*D21 -> 1.041 | K21: ='Flat Sizes'!$H$28 -> 18 | L21: =SUM(H21:I21)*K21 -> 233.964 | M21: =J21*K21 -> 18.738 | N21: Toilet Basecoat | O21: Toilet Brickbat
B22: ='Flat Sizes'!B34 -> Kitchen | C22: Sq M | D22: 1 | E22: =(0.6*2.5) -> 1.5 | F22: =(2.5+0.6)*2 -> 6.2 | G22: 1.2 | H22: =D22*E22 -> 1.5 | I22: =F22*G22*D22 -> 7.44 | J22: =E22*0.3*D22 -> 0.45 | K22: ='Flat Sizes'!$H$28 -> 18 | L22: =SUM(H22:I22)*K22 -> 160.92 | M22: =J22*K22 -> 8.1 | N22: Kitchen Basecoat | O22: Kitchen Brickbat
B23: ='Flat Sizes'!B35 -> Utility | C23: Sq M | D23: 1 | E23: ='Flat Sizes'!D35 -> 2.27 | F23: ='Flat Sizes'!G35 -> 6.1 | G23: 1.2 | H23: =D23*E23 -> 2.27 | I23: =F23*G23*D23 -> 7.32 | J23: =E23*0.3*D23 -> 0.681 | K23: ='Flat Sizes'!$H$28 -> 18 | L23: =SUM(H23:I23)*K23 -> 172.62 | M23: =J23*K23 -> 12.258 | N23: Utility Basecoat | O23: Utility Brickbat
B24: ='Flat Sizes'!B36 -> Balcony | C24: Sq M | D24: 1 | E24: ='Flat Sizes'!D36 -> 2.6 | F24: ='Flat Sizes'!G36 -> 6.7 | G24: 1.2 | H24: =D24*E24 -> 2.6 | I24: =F24*G24*D24 -> 8.04 | J24: =E24*0.3*D24 -> 0.78 | K24: ='Flat Sizes'!$H$28 -> 18 | L24: =SUM(H24:I24)*K24 -> 191.52 | M24: =J24*K24 -> 14.04 | N24: Balcony Basecoat | O24: Balcony Brickbat
A25: 5 | B25: ='Flat Sizes'!B38 -> Flat 3A, 2BHK
B26: ='Flat Sizes'!B41 -> M. Toilet | C26: Sq M | D26: 1 | E26: ='Flat Sizes'!D41 -> 3.9 | F26: ='Flat Sizes'!G41 -> 8.27 | G26: 1.2 | H26: =D26*E26 -> 3.9 | I26: =F26*G26*D26 -> 9.924 | J26: =E26*0.3*D26 -> 1.17 | K26: ='Flat Sizes'!$H$38 -> 3 | L26: =SUM(H26:I26)*K26 -> 41.472 | M26: =J26*K26 -> 3.51 | N26: Toilet Basecoat | O26: Toilet Brickbat
B27: ='Flat Sizes'!B43 -> M. Toilet | C27: Sq M | D27: 1 | E27: ='Flat Sizes'!D43 -> 3.83 | F27: ='Flat Sizes'!G43 -> 8.22 | G27: 1.2 | H27: =D27*E27 -> 3.83 | I27: =F27*G27*D27 -> 9.864 | J27: =E27*0.3*D27 -> 1.149 | K27: ='Flat Sizes'!$H$38 -> 3 | L27: =SUM(H27:I27)*K27 -> 41.082 | M27: =J27*K27 -> 3.447 | N27: Toilet Basecoat | O27: Toilet Brickbat
B28: ='Flat Sizes'!B44 -> Kitchen | C28: Sq M | D28: 1 | E28: =E23 -> 2.27 | F28: =F22 -> 6.2 | G28: 1.2 | H28: =D28*E28 -> 2.27 | I28: =F28*G28*D28 -> 7.44 | J28: =E28*0.3*D28 -> 0.681 | K28: ='Flat Sizes'!$H$38 -> 3 | L28: =SUM(H28:I28)*K28 -> 29.13 | M28: =J28*K28 -> 2.043 | N28: Kitchen Basecoat | O28: Kitchen Brickbat
B29: ='Flat Sizes'!B45 -> Utility | C29: Sq M | D29: 1 | E29: ='Flat Sizes'!D45 -> 2.75 | F29: ='Flat Sizes'!G45 -> 7.05 | G29: 1.2 | H29: =D29*E29 -> 2.75 | I29: =F29*G29*D29 -> 8.46 | J29: =E29*0.3*D29 -> 0.825 | K29: ='Flat Sizes'!$H$38 -> 3 | L29: =SUM(H29:I29)*K29 -> 33.63 | M29: =J29*K29 -> 2.475 | N29: Utility Basecoat | O29: Utility Brickbat
B30: ='Flat Sizes'!B46 -> Balcony | C30: Sq M | D30: 1 | E30: ='Flat Sizes'!D46 -> 2.8 | F30: ='Flat Sizes'!G46 -> 7.01 | G30: 1.2 | H30: =D30*E30 -> 2.8 | I30: =F30*G30*D30 -> 8.412 | J30: =E30*0.3*D30 -> 0.84 | K30: ='Flat Sizes'!$H$38 -> 3 | L30: =SUM(H30:I30)*K30 -> 33.636 | M30: =J30*K30 -> 2.52 | N30: Balcony Basecoat | O30: Balcony Brickbat
A31: 6 | B31: ='Flat Sizes'!B48 -> Flat 3B, 3BHK
B32: ='Flat Sizes'!B51 -> M. Toilet | C32: Sq M | D32: 1 | E32: ='Flat Sizes'!D51 -> 3.9 | F32: ='Flat Sizes'!G51 -> 8.27 | G32: 1.2 | H32: =D32*E32 -> 3.9 | I32: =F32*G32*D32 -> 9.924 | J32: =E32*0.3*D32 -> 1.17 | K32: ='Flat Sizes'!$H$48 -> 27 | L32: =SUM(H32:I32)*K32 -> 373.248 | M32: =J32*K32 -> 31.59 | N32: Toilet Basecoat | O32: Toilet Brickbat
B33: ='Flat Sizes'!B53 -> M. Toilet | C33: Sq M | D33: 1 | E33: ='Flat Sizes'!D53 -> 3.82 | F33: ='Flat Sizes'!G53 -> 8.21 | G33: 1.2 | H33: =D33*E33 -> 3.82 | I33: =F33*G33*D33 -> 9.852 | J33: =E33*0.3*D33 -> 1.146 | K33: ='Flat Sizes'!$H$48 -> 27 | L33: =SUM(H33:I33)*K33 -> 369.144 | M33: =J33*K33 -> 30.942 | N33: Toilet Basecoat | O33: Toilet Brickbat
B34: ='Flat Sizes'!B55 -> C. Toilet | C34: Sq M | D34: 1 | E34: ='Flat Sizes'!D55 -> 3.83 | F34: ='Flat Sizes'!G55 -> 8.22 | G34: 1.2 | H34: =D34*E34 -> 3.83 | I34: =F34*G34*D34 -> 9.864 | J34: =E34*0.3*D34 -> 1.149 | K34: ='Flat Sizes'!$H$48 -> 27 | L34: =SUM(H34:I34)*K34 -> 369.738 | M34: =J34*K34 -> 31.023 | N34: Toilet Basecoat | O34: Toilet Brickbat
B35: ='Flat Sizes'!B56 -> Kitchen | C35: Sq M | D35: 1 | E35: =E28 -> 2.27 | F35: =F28 -> 6.2 | G35: 1.2 | H35: =D35*E35 -> 2.27 | I35: =F35*G35*D35 -> 7.44 | J35: =E35*0.3*D35 -> 0.681 | K35: ='Flat Sizes'!$H$48 -> 27 | L35: =SUM(H35:I35)*K35 -> 262.17 | M35: =J35*K35 -> 18.387 | N35: Kitchen Basecoat | O35: Kitchen Brickbat
B36: ='Flat Sizes'!B57 -> Balcony | C36: Sq M | D36: 1 | E36: ='Flat Sizes'!D57 -> 2.8 | F36: ='Flat Sizes'!G57 -> 7.01 | G36: 1.2 | H36: =D36*E36 -> 2.8 | I36: =F36*G36*D36 -> 8.412 | J36: =E36*0.3*D36 -> 0.84 | K36: ='Flat Sizes'!$H$48 -> 27 | L36: =SUM(H36:I36)*K36 -> 302.724 | M36: =J36*K36 -> 22.68 | N36: Balcony Basecoat | O36: Balcony Brickbat
B37: ='Flat Sizes'!B58 -> Utility | C37: Sq M | D37: 1 | E37: ='Flat Sizes'!D58 -> 2.82 | F37: ='Flat Sizes'!G58 -> 7.05 | G37: 1.2 | H37: =D37*E37 -> 2.82 | I37: =F37*G37*D37 -> 8.46 | J37: =E37*0.3*D37 -> 0.846 | K37: ='Flat Sizes'!$H$48 -> 27 | L37: =SUM(H37:I37)*K37 -> 304.56 | M37: =J37*K37 -> 22.842 | N37: Utility Basecoat | O37: Utility Brickbat
A38: 7 | B38: ='Flat Sizes'!B60 -> Flat 4A, 2BHK
B39: ='Flat Sizes'!B63 -> M. Toilet | C39: Sq M | D39: 1 | E39: ='Flat Sizes'!G63 -> 8.21 | F39: ='Flat Sizes'!G63 -> 8.21 | G39: 1.2 | H39: =D39*E39 -> 8.21 | I39: =F39*G39*D39 -> 9.852 | J39: =E39*0.3*D39 -> 2.463 | K39: ='Flat Sizes'!$H$60 -> 2 | L39: =SUM(H39:I39)*K39 -> 36.124 | M39: =J39*K39 -> 4.926 | N39: Toilet Basecoat | O39: Toilet Brickbat
B40: ='Flat Sizes'!B65 -> M. Toilet | C40: Sq M | D40: 1 | E40: ='Flat Sizes'!G65 -> 8.27 | F40: ='Flat Sizes'!G65 -> 8.27 | G40: 1.2 | H40: =D40*E40 -> 8.27 | I40: =F40*G40*D40 -> 9.924 | J40: =E40*0.3*D40 -> 2.481 | K40: ='Flat Sizes'!$H$60 -> 2 | L40: =SUM(H40:I40)*K40 -> 36.388 | M40: =J40*K40 -> 4.962 | N40: Toilet Basecoat | O40: Toilet Brickbat
B41: ='Flat Sizes'!B66 -> Kitchen | C41: Sq M | D41: 1 | E41: =E35 -> 2.27 | F41: =F35 -> 6.2 | G41: 1.2 | H41: =D41*E41 -> 2.27 | I41: =F41*G41*D41 -> 7.44 | J41: =E41*0.3*D41 -> 0.681 | K41: ='Flat Sizes'!$H$60 -> 2 | L41: =SUM(H41:I41)*K41 -> 19.42 | M41: =J41*K41 -> 1.362 | N41: Kitchen Basecoat | O41: Kitchen Brickbat
B42: ='Flat Sizes'!B67 -> Utility | C42: Sq M | D42: 1 | E42: ='Flat Sizes'!D67 -> 2.75 | F42: ='Flat Sizes'!G67 -> 7.05 | G42: 1.2 | H42: =D42*E42 -> 2.75 | I42: =F42*G42*D42 -> 8.46 | J42: =E42*0.3*D42 -> 0.825 | K42: ='Flat Sizes'!$H$60 -> 2 | L42: =SUM(H42:I42)*K42 -> 22.42 | M42: =J42*K42 -> 1.65 | N42: Utility Basecoat | O42: Utility Brickbat
B43: ='Flat Sizes'!B68 -> Balcony | C43: Sq M | D43: 1 | E43: ='Flat Sizes'!D68 -> 2.8 | F43: ='Flat Sizes'!G68 -> 7.01 | G43: 1.2 | H43: =D43*E43 -> 2.8 | I43: =F43*G43*D43 -> 8.412 | J43: =E43*0.3*D43 -> 0.84 | K43: ='Flat Sizes'!$H$60 -> 2 | L43: =SUM(H43:I43)*K43 -> 22.424 | M43: =J43*K43 -> 1.68 | N43: Balcony Basecoat | O43: Balcony Brickbat
A44: 8 | B44: ='Flat Sizes'!B70 -> Flat 4B, 3BHK
B45: ='Flat Sizes'!B73 -> M. Toilet | C45: Sq M | D45: 1 | E45: ='Flat Sizes'!D73 -> 3.83 | F45: ='Flat Sizes'!G73 -> 8.22 | G45: 1.2 | H45: =D45*E45 -> 3.83 | I45: =F45*G45*D45 -> 9.864 | J45: =E45*0.3*D45 -> 1.149 | K45: ='Flat Sizes'!$H$70 -> 24 | L45: =SUM(H45:I45)*K45 -> 328.656 | M45: =J45*K45 -> 27.576 | N45: Toilet Basecoat | O45: Toilet Brickbat
B46: ='Flat Sizes'!B75 -> M. Toilet | C46: Sq M | D46: 1 | E46: ='Flat Sizes'!D75 -> 3.9 | F46: ='Flat Sizes'!G75 -> 8.27 | G46: 1.2 | H46: =D46*E46 -> 3.9 | I46: =F46*G46*D46 -> 9.924 | J46: =E46*0.3*D46 -> 1.17 | K46: ='Flat Sizes'!$H$70 -> 24 | L46: =SUM(H46:I46)*K46 -> 331.776 | M46: =J46*K46 -> 28.08 | N46: Toilet Basecoat | O46: Toilet Brickbat
B47: ='Flat Sizes'!B77 -> C. Toilet | C47: Sq M | D47: 1 | E47: ='Flat Sizes'!D77 -> 3.83 | F47: ='Flat Sizes'!G77 -> 8.22 | G47: 1.2 | H47: =D47*E47 -> 3.83 | I47: =F47*G47*D47 -> 9.864 | J47: =E47*0.3*D47 -> 1.149 | K47: ='Flat Sizes'!$H$70 -> 24 | L47: =SUM(H47:I47)*K47 -> 328.656 | M47: =J47*K47 -> 27.576 | N47: Toilet Basecoat | O47: Toilet Brickbat
B48: ='Flat Sizes'!B78 -> Kitchen | C48: Sq M | D48: 1 | E48: =E41 -> 2.27 | F48: =F41 -> 6.2 | G48: 1.2 | H48: =D48*E48 -> 2.27 | I48: =F48*G48*D48 -> 7.44 | J48: =E48*0.3*D48 -> 0.681 | K48: ='Flat Sizes'!$H$70 -> 24 | L48: =SUM(H48:I48)*K48 -> 233.04 | M48: =J48*K48 -> 16.344 | N48: Kitchen Basecoat | O48: Kitchen Brickbat
B49: ='Flat Sizes'!B79 -> Utility | C49: Sq M | D49: 1 | E49: ='Flat Sizes'!D79 -> 2.82 | F49: ='Flat Sizes'!G79 -> 7.05 | G49: 1.2 | H49: =D49*E49 -> 2.82 | I49: =F49*G49*D49 -> 8.46 | J49: =E49*0.3*D49 -> 0.846 | K49: ='Flat Sizes'!$H$70 -> 24 | L49: =SUM(H49:I49)*K49 -> 270.72 | M49: =J49*K49 -> 20.304 | N49: Utility Basecoat | O49: Utility Brickbat
B50: ='Flat Sizes'!B80 -> Balcony | C50: Sq M | D50: 1 | E50: ='Flat Sizes'!D80 -> 2.8 | F50: ='Flat Sizes'!G80 -> 7.01 | G50: 1.2 | H50: =D50*E50 -> 2.8 | I50: =F50*G50*D50 -> 8.412 | J50: =E50*0.3*D50 -> 0.84 | K50: ='Flat Sizes'!$H$70 -> 24 | L50: =SUM(H50:I50)*K50 -> 269.088 | M50: =J50*K50 -> 20.16 | N50: Balcony Basecoat | O50: Balcony Brickbat
A51: 9 | B51: ='Flat Sizes'!B82 -> Flat 5A
B52: ='Flat Sizes'!B86 -> M. Toilet | C52: Sq M | D52: 1 | E52: ='Flat Sizes'!D86 -> 2.43 | F52: ='Flat Sizes'!G86 -> 6.54 | G52: 1.2 | H52: =D52*E52 -> 2.43 | I52: =F52*G52*D52 -> 7.848 | J52: =E52*0.3*D52 -> 0.729 | K52: ='Flat Sizes'!$H$82 -> 8 | L52: =SUM(H52:I52)*K52 -> 82.224 | M52: =J52*K52 -> 5.832 | N52: Toilet Basecoat | O52: Toilet Brickbat
B53: ='Flat Sizes'!B87 -> C. Toilet | C53: Sq M | D53: 1 | E53: ='Flat Sizes'!D87 -> 3.07 | F53: ='Flat Sizes'!G87 -> 7.35 | G53: 1.2 | H53: =D53*E53 -> 3.07 | I53: =F53*G53*D53 -> 8.82 | J53: =E53*0.3*D53 -> 0.921 | K53: ='Flat Sizes'!$H$82 -> 8 | L53: =SUM(H53:I53)*K53 -> 95.12 | M53: =J53*K53 -> 7.368 | N53: Toilet Basecoat | O53: Toilet Brickbat
A54: 10 | B54: ='Flat Sizes'!B89 -> Flat 5B, 2BHK
B55: ='Flat Sizes'!B92 -> M. Toilet | C55: Sq M | D55: 1 | E55: ='Flat Sizes'!D92 -> 3.27 | F55: ='Flat Sizes'!G92 -> 7.64 | G55: 1.2 | H55: =D55*E55 -> 3.27 | I55: =F55*G55*D55 -> 9.168 | J55: =E55*0.3*D55 -> 0.981 | K55: ='Flat Sizes'!$H$89 -> 18 | L55: =SUM(H55:I55)*K55 -> 223.884 | M55: =J55*K55 -> 17.658 | N55: Toilet Basecoat | O55: Toilet Brickbat
B56: ='Flat Sizes'!B94 -> C. Toilet | C56: Sq M | D56: 1 | E56: ='Flat Sizes'!D94 -> 3.25 | F56: ='Flat Sizes'!G94 -> 7.61 | G56: 1.2 | H56: =D56*E56 -> 3.25 | I56: =F56*G56*D56 -> 9.132 | J56: =E56*0.3*D56 -> 0.975 | K56: ='Flat Sizes'!$H$89 -> 18 | L56: =SUM(H56:I56)*K56 -> 222.876 | M56: =J56*K56 -> 17.55 | N56: Toilet Basecoat | O56: Toilet Brickbat
B57: ='Flat Sizes'!B95 -> Kitchen | C57: Sq M | D57: 1 | E57: =E48 -> 2.27 | F57: =F48 -> 6.2 | G57: 1.2 | H57: =D57*E57 -> 2.27 | I57: =F57*G57*D57 -> 7.44 | J57: =E57*0.3*D57 -> 0.681 | K57: ='Flat Sizes'!$H$89 -> 18 | L57: =SUM(H57:I57)*K57 -> 174.78 | M57: =J57*K57 -> 12.258 | N57: Kitchen Basecoat | O57: Kitchen Brickbat
B58: ='Flat Sizes'!B96 -> Utility | C58: Sq M | D58: 1 | E58: ='Flat Sizes'!D96 -> 1.84 | F58: ='Flat Sizes'!G96 -> 5.61 | G58: 1.2 | H58: =D58*E58 -> 1.84 | I58: =F58*G58*D58 -> 6.732 | J58: =E58*0.3*D58 -> 0.552 | K58: ='Flat Sizes'!$H$89 -> 18 | L58: =SUM(H58:I58)*K58 -> 154.296 | M58: =J58*K58 -> 9.936 | N58: Utility Basecoat | O58: Utility Brickbat
B59: ='Flat Sizes'!B97 -> Balcony | C59: Sq M | D59: 1 | E59: ='Flat Sizes'!D97 -> 2.23 | F59: ='Flat Sizes'!G97 -> 6.1 | G59: 1.2 | H59: =D59*E59 -> 2.23 | I59: =F59*G59*D59 -> 7.32 | J59: =E59*0.3*D59 -> 0.669 | K59: ='Flat Sizes'!$H$89 -> 18 | L59: =SUM(H59:I59)*K59 -> 171.9 | M59: =J59*K59 -> 12.042 | N59: Balcony Basecoat | O59: Balcony Brickbat
A60: 11 | B60: ='Flat Sizes'!B99 -> Flat 6, 2BHK
B61: ='Flat Sizes'!B102 -> M. Toilet | C61: Sq M | D61: 1 | E61: ='Flat Sizes'!D102 -> 3.27 | F61: ='Flat Sizes'!G102 -> 7.64 | G61: 1.2 | H61: =D61*E61 -> 3.27 | I61: =F61*G61*D61 -> 9.168 | J61: =E61*0.3*D61 -> 0.981 | K61: ='Flat Sizes'!$H$99 -> 28 | L61: =SUM(H61:I61)*K61 -> 348.264 | M61: =J61*K61 -> 27.468 | N61: Toilet Basecoat | O61: Toilet Brickbat
B62: ='Flat Sizes'!B104 -> C. Toilet | C62: Sq M | D62: 1 | E62: ='Flat Sizes'!D104 -> 3.25 | F62: ='Flat Sizes'!G104 -> 7.61 | G62: 1.2 | H62: =D62*E62 -> 3.25 | I62: =F62*G62*D62 -> 9.132 | J62: =E62*0.3*D62 -> 0.975 | K62: ='Flat Sizes'!$H$99 -> 28 | L62: =SUM(H62:I62)*K62 -> 346.696 | M62: =J62*K62 -> 27.3 | N62: Toilet Basecoat | O62: Toilet Brickbat
B63: ='Flat Sizes'!B105 -> Kitchen | C63: Sq M | D63: 1 | E63: =E57 -> 2.27 | F63: =F57 -> 6.2 | G63: 1.2 | H63: =D63*E63 -> 2.27 | I63: =F63*G63*D63 -> 7.44 | J63: =E63*0.3*D63 -> 0.681 | K63: ='Flat Sizes'!$H$99 -> 28 | L63: =SUM(H63:I63)*K63 -> 271.88 | M63: =J63*K63 -> 19.068 | N63: Kitchen Basecoat | O63: Kitchen Brickbat
B64: ='Flat Sizes'!B106 -> Utility | C64: Sq M | D64: 1 | E64: ='Flat Sizes'!D106 -> 1.84 | F64: ='Flat Sizes'!G106 -> 5.6 | G64: 1.2 | H64: =D64*E64 -> 1.84 | I64: =F64*G64*D64 -> 6.72 | J64: =E64*0.3*D64 -> 0.552 | K64: ='Flat Sizes'!$H$99 -> 28 | L64: =SUM(H64:I64)*K64 -> 239.68 | M64: =J64*K64 -> 15.456 | N64: Utility Basecoat | O64: Utility Brickbat
B65: ='Flat Sizes'!B107 -> Balcony | C65: Sq M | D65: 1 | E65: ='Flat Sizes'!D107 -> 2.23 | F65: ='Flat Sizes'!G107 -> 6.1 | G65: 1.2 | H65: =D65*E65 -> 2.23 | I65: =F65*G65*D65 -> 7.32 | J65: =E65*0.3*D65 -> 0.669 | K65: ='Flat Sizes'!$H$99 -> 28 | L65: =SUM(H65:I65)*K65 -> 267.4 | M65: =J65*K65 -> 18.732 | N65: Balcony Basecoat | O65: Balcony Brickbat
A66: 12 | B66: ='Flat Sizes'!B109 -> Flat 7, 3BHK
B67: ='Flat Sizes'!B112 -> M. Toilet | C67: Sq M | D67: 1 | E67: ='Flat Sizes'!D112 -> 3.9 | F67: ='Flat Sizes'!G112 -> 8.27 | G67: 1.2 | H67: =D67*E67 -> 3.9 | I67: =F67*G67*D67 -> 9.924 | J67: =E67*0.3*D67 -> 1.17 | K67: ='Flat Sizes'!$H$109 -> 26 | L67: =SUM(H67:I67)*K67 -> 359.424 | M67: =J67*K67 -> 30.42 | N67: Toilet Basecoat | O67: Toilet Brickbat
B68: ='Flat Sizes'!B114 -> M. Toilet | C68: Sq M | D68: 1 | E68: ='Flat Sizes'!D114 -> 3.83 | F68: ='Flat Sizes'!G114 -> 8.32 | G68: 1.2 | H68: =D68*E68 -> 3.83 | I68: =F68*G68*D68 -> 9.984 | J68: =E68*0.3*D68 -> 1.149 | K68: ='Flat Sizes'!$H$109 -> 26 | L68: =SUM(H68:I68)*K68 -> 359.164 | M68: =J68*K68 -> 29.874 | N68: Toilet Basecoat | O68: Toilet Brickbat
B69: ='Flat Sizes'!B116 -> C. Toilet | C69: Sq M | D69: 1 | E69: ='Flat Sizes'!D116 -> 3.83 | F69: ='Flat Sizes'!G116 -> 8.32 | G69: 1.2 | H69: =D69*E69 -> 3.83 | I69: =F69*G69*D69 -> 9.984 | J69: =E69*0.3*D69 -> 1.149 | K69: ='Flat Sizes'!$H$109 -> 26 | L69: =SUM(H69:I69)*K69 -> 359.164 | M69: =J69*K69 -> 29.874 | N69: Toilet Basecoat | O69: Toilet Brickbat
B70: ='Flat Sizes'!B117 -> Kitchen | C70: Sq M | D70: 1 | E70: =E63 -> 2.27 | F70: =F63 -> 6.2 | G70: 1.2 | H70: =D70*E70 -> 2.27 | I70: =F70*G70*D70 -> 7.44 | J70: =E70*0.3*D70 -> 0.681 | K70: ='Flat Sizes'!$H$109 -> 26 | L70: =SUM(H70:I70)*K70 -> 252.46 | M70: =J70*K70 -> 17.706 | N70: Kitchen Basecoat | O70: Kitchen Brickbat
B71: ='Flat Sizes'!B118 -> Utility | C71: Sq M | D71: 1 | E71: ='Flat Sizes'!D118 -> 2.82 | F71: ='Flat Sizes'!G118 -> 7.05 | G71: 1.2 | H71: =D71*E71 -> 2.82 | I71: =F71*G71*D71 -> 8.46 | J71: =E71*0.3*D71 -> 0.846 | K71: ='Flat Sizes'!$H$109 -> 26 | L71: =SUM(H71:I71)*K71 -> 293.28 | M71: =J71*K71 -> 21.996 | N71: Utility Basecoat | O71: Utility Brickbat
B72: ='Flat Sizes'!B119 -> Balcony | C72: Sq M | D72: 1 | E72: ='Flat Sizes'!D119 -> 2.8 | F72: ='Flat Sizes'!G119 -> 7.01 | G72: 1.2 | H72: =D72*E72 -> 2.8 | I72: =F72*G72*D72 -> 8.412 | J72: =E72*0.3*D72 -> 0.84 | K72: ='Flat Sizes'!$H$109 -> 26 | L72: =SUM(H72:I72)*K72 -> 291.512 | M72: =J72*K72 -> 21.84 | N72: Balcony Basecoat | O72: Balcony Brickbat
A73: 13 | B73: ='Flat Sizes'!B121 -> Flat 8, 3BHK
B74: ='Flat Sizes'!B124 -> M. Toilet | C74: Sq M | D74: 1 | E74: ='Flat Sizes'!D124 -> 3.28 | F74: ='Flat Sizes'!G124 -> 8.21 | G74: 1.2 | H74: =D74*E74 -> 3.28 | I74: =F74*G74*D74 -> 9.852 | J74: =E74*0.3*D74 -> 0.984 | K74: ='Flat Sizes'!$H$121 -> 30 | L74: =SUM(H74:I74)*K74 -> 393.96 | M74: =J74*K74 -> 29.52 | N74: Toilet Basecoat | O74: Toilet Brickbat
B75: ='Flat Sizes'!B126 -> M. Toilet | C75: Sq M | D75: 1 | E75: ='Flat Sizes'!D126 -> 3.9 | F75: ='Flat Sizes'!G126 -> 8.27 | G75: 1.2 | H75: =D75*E75 -> 3.9 | I75: =F75*G75*D75 -> 9.924 | J75: =E75*0.3*D75 -> 1.17 | K75: ='Flat Sizes'!$H$121 -> 30 | L75: =SUM(H75:I75)*K75 -> 414.72 | M75: =J75*K75 -> 35.1 | N75: Toilet Basecoat | O75: Toilet Brickbat
B76: ='Flat Sizes'!B128 -> C. Toilet | C76: Sq M | D76: 1 | E76: ='Flat Sizes'!D128 -> 3.83 | F76: ='Flat Sizes'!G128 -> 8.22 | G76: 1.2 | H76: =D76*E76 -> 3.83 | I76: =F76*G76*D76 -> 9.864 | J76: =E76*0.3*D76 -> 1.149 | K76: ='Flat Sizes'!$H$121 -> 30 | L76: =SUM(H76:I76)*K76 -> 410.82 | M76: =J76*K76 -> 34.47 | N76: Toilet Basecoat | O76: Toilet Brickbat
B77: ='Flat Sizes'!B129 -> Kitchen | C77: Sq M | D77: 1 | E77: =E70 -> 2.27 | F77: =F70 -> 6.2 | G77: 1.2 | H77: =D77*E77 -> 2.27 | I77: =F77*G77*D77 -> 7.44 | J77: =E77*0.3*D77 -> 0.681 | K77: ='Flat Sizes'!$H$121 -> 30 | L77: =SUM(H77:I77)*K77 -> 291.3 | M77: =J77*K77 -> 20.43 | N77: Kitchen Basecoat | O77: Kitchen Brickbat
B78: ='Flat Sizes'!B130 -> Utility | C78: Sq M | D78: 1 | E78: ='Flat Sizes'!D130 -> 2.82 | F78: ='Flat Sizes'!G130 -> 7.05 | G78: 1.2 | H78: =D78*E78 -> 2.82 | I78: =F78*G78*D78 -> 8.46 | J78: =E78*0.3*D78 -> 0.846 | K78: ='Flat Sizes'!$H$121 -> 30 | L78: =SUM(H78:I78)*K78 -> 338.4 | M78: =J78*K78 -> 25.38 | N78: Utility Basecoat | O78: Utility Brickbat
B79: ='Flat Sizes'!B131 -> Balcony | C79: Sq M | D79: 1 | E79: ='Flat Sizes'!D131 -> 2.8 | F79: ='Flat Sizes'!G131 -> 7.01 | G79: 1.2 | H79: =D79*E79 -> 2.8 | I79: =F79*G79*D79 -> 8.412 | J79: =E79*0.3*D79 -> 0.84 | K79: ='Flat Sizes'!$H$121 -> 30 | L79: =SUM(H79:I79)*K79 -> 336.36 | M79: =J79*K79 -> 25.2 | N79: Balcony Basecoat | O79: Balcony Brickbat
A80: 14 | B80: ='Flat Sizes'!B133 -> Flat 9, 2BHK
B81: ='Flat Sizes'!B136 -> M. Toilet | C81: Sq M | D81: 1 | E81: ='Flat Sizes'!D136 -> 3.39 | F81: ='Flat Sizes'!G136 -> 7.94 | G81: 1.2 | H81: =D81*E81 -> 3.39 | I81: =F81*G81*D81 -> 9.528 | J81: =E81*0.3*D81 -> 1.017 | K81: ='Flat Sizes'!$H$133 -> 28 | L81: =SUM(H81:I81)*K81 -> 361.704 | M81: =J81*K81 -> 28.476 | N81: Toilet Basecoat | O81: Toilet Brickbat
B82: ='Flat Sizes'!B138 -> C. Toilet | C82: Sq M | D82: 1 | E82: ='Flat Sizes'!D138 -> 3.47 | F82: ='Flat Sizes'!G138 -> 7.94 | G82: 1.2 | H82: =D82*E82 -> 3.47 | I82: =F82*G82*D82 -> 9.528 | J82: =E82*0.3*D82 -> 1.041 | K82: ='Flat Sizes'!$H$133 -> 28 | L82: =SUM(H82:I82)*K82 -> 363.944 | M82: =J82*K82 -> 29.148 | N82: Toilet Basecoat | O82: Toilet Brickbat
B83: ='Flat Sizes'!B139 -> Kitchen | C83: Sq M | D83: 1 | E83: =E77 -> 2.27 | F83: =F77 -> 6.2 | G83: 1.2 | H83: =D83*E83 -> 2.27 | I83: =F83*G83*D83 -> 7.44 | J83: =E83*0.3*D83 -> 0.681 | K83: ='Flat Sizes'!$H$133 -> 28 | L83: =SUM(H83:I83)*K83 -> 271.88 | M83: =J83*K83 -> 19.068 | N83: Kitchen Basecoat | O83: Kitchen Brickbat
B84: ='Flat Sizes'!B140 -> Utility | C84: Sq M | D84: 1 | E84: ='Flat Sizes'!D140 -> 2.27 | F84: ='Flat Sizes'!G140 -> 6.1 | G84: 1.2 | H84: =D84*E84 -> 2.27 | I84: =F84*G84*D84 -> 7.32 | J84: =E84*0.3*D84 -> 0.681 | K84: ='Flat Sizes'!$H$133 -> 28 | L84: =SUM(H84:I84)*K84 -> 268.52 | M84: =J84*K84 -> 19.068 | N84: Utility Basecoat | O84: Utility Brickbat
B85: ='Flat Sizes'!B141 -> Balcony | C85: Sq M | D85: 1 | E85: ='Flat Sizes'!D141 -> 2.6 | F85: ='Flat Sizes'!G141 -> 6.7 | G85: 1.2 | H85: =D85*E85 -> 2.6 | I85: =F85*G85*D85 -> 8.04 | J85: =E85*0.3*D85 -> 0.78 | K85: ='Flat Sizes'!$H$133 -> 28 | L85: =SUM(H85:I85)*K85 -> 297.92 | M85: =J85*K85 -> 21.84 | N85: Balcony Basecoat | O85: Balcony Brickbat
A86: 15 | B86: ='Flat Sizes'!B143 -> Flat 10, 2BHK
B87: ='Flat Sizes'!B146 -> M. Toilet | C87: Sq M | D87: 1 | E87: ='Flat Sizes'!D146 -> 3.46 | F87: ='Flat Sizes'!G146 -> 7.92 | G87: 1.2 | H87: =D87*E87 -> 3.46 | I87: =F87*G87*D87 -> 9.504 | J87: =E87*0.3*D87 -> 1.038 | K87: ='Flat Sizes'!$H$143 -> 28 | L87: =SUM(H87:I87)*K87 -> 362.992 | M87: =J87*K87 -> 29.064 | N87: Toilet Basecoat | O87: Toilet Brickbat
B88: ='Flat Sizes'!B148 -> C. Toilet | C88: Sq M | D88: 1 | E88: ='Flat Sizes'!D148 -> 3.35 | F88: ='Flat Sizes'!G148 -> 7.75 | G88: 1.2 | H88: =D88*E88 -> 3.35 | I88: =F88*G88*D88 -> 9.3 | J88: =E88*0.3*D88 -> 1.005 | K88: ='Flat Sizes'!$H$143 -> 28 | L88: =SUM(H88:I88)*K88 -> 354.2 | M88: =J88*K88 -> 28.14 | N88: Toilet Basecoat | O88: Toilet Brickbat
B89: ='Flat Sizes'!B149 -> Kitchen | C89: Sq M | D89: 1 | E89: =E83 -> 2.27 | F89: =F83 -> 6.2 | G89: 1.2 | H89: =D89*E89 -> 2.27 | I89: =F89*G89*D89 -> 7.44 | J89: =E89*0.3*D89 -> 0.681 | K89: ='Flat Sizes'!$H$143 -> 28 | L89: =SUM(H89:I89)*K89 -> 271.88 | M89: =J89*K89 -> 19.068 | N89: Kitchen Basecoat | O89: Kitchen Brickbat
B90: ='Flat Sizes'!B150 -> Utility | C90: Sq M | D90: 1 | E90: ='Flat Sizes'!D150 -> 2.61 | F90: ='Flat Sizes'!G150 -> 6.71 | G90: 1.2 | H90: =D90*E90 -> 2.61 | I90: =F90*G90*D90 -> 8.052 | J90: =E90*0.3*D90 -> 0.783 | K90: ='Flat Sizes'!$H$143 -> 28 | L90: =SUM(H90:I90)*K90 -> 298.536 | M90: =J90*K90 -> 21.924 | N90: Utility Basecoat | O90: Utility Brickbat
B91: ='Flat Sizes'!B151 -> Balcony | C91: Sq M | D91: 1 | E91: ='Flat Sizes'!D151 -> 2.6 | F91: ='Flat Sizes'!G151 -> 6.7 | G91: 1.2 | H91: =D91*E91 -> 2.6 | I91: =F91*G91*D91 -> 8.04 | J91: =E91*0.3*D91 -> 0.78 | K91: ='Flat Sizes'!$H$143 -> 28 | L91: =SUM(H91:I91)*K91 -> 297.92 | M91: =J91*K91 -> 21.84 | N91: Balcony Basecoat | O91: Balcony Brickbat
A92: C | B92: Terrace Floor & Refuge Areas
B93: Terrace Floor | C93: Sq M | D93: 1 | E93: =1446.87-363.55 -> 1083.32 | F93: =277.05+23.3+24.55+90.36+24.55+23.3 -> 463.11 | G93: 0.6 | K93: 1 | L93: =E93*K93 -> 1083.32 | N93: Terrace Waterproofing
B94: Podium Terrace | C94: Sq M | D94: 1 | E94: 1357.88 | F94: 189.77 | G94: 0.6 | K94: 1 | L94: =E94*K94 -> 1357.88 | N94: Podium Terrace Waterproofing
B95: Antiroot Waterproofing | C95: Sq M | D95: 1 | E95: =107.88+12.6+12.6 -> 133.08 | K95: 1 | L95: =E95*K95 -> 133.08 | N95: Antiroot Waterproofing
B96: OHT | C96: Sq M | D96: 1 | E96: ='Measurement Sheet'!D347*2 -> 92.54 | K96: 4 | L96: =E96*K96 -> 370.16 | N96: OHT Waterproofing
B97: L.M.R. Mumty Floor | C97: Sq M | D97: 1 | E97: ='Construction Area'!R43 -> 384.84 | K97: 1 | N97: Terrace Waterproofing
B98: LMR Mumty Roof | C98: Sq M | D98: 1 | E98: =E97 -> 384.84 | K98: 1 | N98: Terrace Waterproofing
B99: Refuge | C99: Sq M | D99: 1 | E99: 234.42 | K99: 4 | L99: =E99*K99 -> 937.68 | N99: Refuge Waterproofing
A100: D | B100: Chhajja / Service Slab
...

Sheet Infra
A1: Civil Infra
A2: Description | B2: Unit | C2: Area | D2: Rate | E2: Amount
A3: Road and Pathways | B3: Sq M | C3: 1803 | D3: 7500 | E3: =C3*D3 -> 13522500
A4: Boundary wall | B4: Rmt | C4: 602.91 | D4: 6500 | E4: =C4*D4 -> 3918915
A5: Gate & security Cabin | B5: LS | C5: 1 | D5: 1000000 | E5: 1000000
A6: Boom Barriers | B6: Nos. | C6: 2 | D6: 50000 | E6: =C6*D6 -> 100000 | K6: 60% Hardscape | L6: 40% Softscape
A7: Landscape & Signages | I7: Ground Floor | J7: =989.93+382.03 -> 1371.96 | K7: =J7*60% -> 823.176 | L7: =J7-K7 -> 548.784
A8: Gr. Floor, 6th Podium and Terrace | I8: 6th Podium | J8: =1357.92 -> 1357.92 | K8: =J8*60% -> 814.752 | L8: =J8-K8 -> 543.168
A9: Hard Scape | B9: Sq M | C9: =K10 -> 1652.928 | D9: =950*10.764 -> 10225.8 | E9: =C9*D9 -> 16902511 | I9: Terrace | J9: 25 | K9: =J9*60% -> 15 | L9: =J9-K9 -> 10
A10: Soft Scape | B10: Sq M | C10: =L10 -> 1101.952 | D10: =750*10.764 -> 8073 | E10: =C10*D10 -> 8896058.5 | K10: =SUM(K7:K9) -> 1652.928 | L10: =SUM(L7:L9) -> 1101.952
A11: Trees Plantation | B11: Nos | C11: 100 | D11: =7500 -> 7500 | E11: =C11*D11 -> 750000
A12: Miscellaneous works | B12: LS | E12: 1500000 | F12: considered LS safer side
E13: =SUM(E3:E12) -> 46589985

Sheet Amenities
A1: List of Amenities
A2: Sr. | B2: Particulars | C2: Unit | D2: Area | E2: Rate | F2: Amount
A4: # | B4: Gymnasium / Fitness Centre @ 4th Podium Double Ht.
B5: Finishing Works | C5: Sq M | D5: 186.29 | E5: =3000*10.764 -> 32292 | F5: =+D5*E5 -> 6015676.7
B6: Equipments | C6: LS | D6: 1 | E6: 700000 | F6: =+D6*E6 -> 700000
B7: Doors | C7: Nos. | D7: 1 | E7: 45000 | F7: =+D7*E7 -> 45000
A8: # | B8: Gymnasium / Fitness Centre @ 6th Podium
B9: Finishing Works | C9: Sq M | D9: 191.94 | E9: =3000*10.764 -> 32292 | F9: =+D9*E9 -> 6198126.5
B10: Equipments | C10: LS | D10: 1 | E10: 1000000 | F10: =+D10*E10 -> 1000000
B11: Doors | C11: Nos. | D11: 1 | E11: 45000 | F11: =+D11*E11 -> 45000
A12: # | B12: Swimming Pool
B13: Finishing Works | C13: Sq M | D13: 66.95 | E13: =3200*10.764 -> 34444.8 | F13: =+D13*E13 -> 2306079.4
A15: # | B15: Society Office
B16: Finishing Works | C16: Sq M | D16: 17.3 | E16: =2000*10.764 -> 21528 | F16: =+D16*E16 -> 372434.4
B17: Doors | C17: Nos. | D17: 1 | E17: 45000 | F17: =+D17*E17 -> 45000
A19: # | B19: Meter Room
B20: Finishing Works | C20: Sq M | D20: =22.33+12.38 -> 34.71 | E20: =1800*10.764 -> 19375.2 | F20: =+D20*E20 -> 672513.19
B21: Doors | C21: Nos. | D21: 1 | E21: 45000 | F21: =+D21*E21 -> 45000
A23: # | B23: Entrance Lobby @ Gr Floor
B24: Finishing Works | C24: Sq M | D24: =82.79*2 -> 165.58 | E24: =5000*10.764 -> 53820 | F24: =+D24*E24 -> 8911515.6
A26: # | B26: Entrance Lobby @ 6th Podium
B27: Finishing Works | C27: Sq M | D27: =79.38+130.82 -> 210.2 | E27: =5000*10.764 -> 53820 | F27: =+D27*E27 -> 11312964
B29: Total Amount | F29: =SUM(F3:F28) -> 37669310

Sheet Preliminary
A1: Preliminary
A2: Sr. No | B2: Description | C2: Qty | D2: Unit | E2: Rate | F2: Amount
A3: 1 | B3: Barrication | C3: =602.91*(30/3.28) -> 5514.4207 | D3: Sqm | E3: =135*10.764 -> 1453.14 | F3: =C3*E3 -> 8013225.3
A4: 2 | B4: Porta Cabin | C4: 1 | D4: No | E4: 400000 | F4: =C4*E4 -> 400000
A5: 3 | B5: Smog Gun | C5: 1 | D5: No | E5: 135000 | F5: =C5*E5 -> 135000
A6: 4 | B6: Air Monitory Control | C6: 1 | D6: No | E6: 65000 | F6: =C6*E6 -> 65000
A7: 5 | B7: Electricity | C7: 36 | D7: Month | E7: 36000 | F7: =C7*E7 -> 1296000
A8: 6 | B8: Borewell | C8: 1 | D8: No | E8: 110000 | F8: =C8*E8 -> 110000
A9: 7 | B9: CT / Water supply | C9: 1 | D9: LS | E9: 500000 | F9: =C9*E9 -> 500000
A10: 8 | B10: Site Establishment | C10: 36 | D10: Month | E10: 25000 | F10: =C10*E10 -> 900000
A11: 9 | B11: Portable Toilets | C11: 36 | D11: Month | E11: 25000 | F11: =C11*E11 -> 900000
E13: Total | F13: =SUM(F3:F12) -> 12319225

Sheet Internal Finishes Offices
C1: Height | D1: 3.6
A2: Sr. No. | B2: Particulars | C2: Area (Sq. M) | D2: Perimeter (M) | E2: Qty | F2: Deduction | G2: Net Qty | H2: Unit | I2: Specs | J2: B.Rate | K2: Total Rate | L2: Amount | N2: No. of Units | O2: Total Qty | P2: Total Amount | R2: Filters
A3: # | B3: ='Office Sizes'!B4 -> Office 1 | N3: 32
A4: # | B4: ='Office Sizes'!B5 -> Office | C4: ='Office Sizes'!D5 -> 33.47 | D4: ='Office Sizes'!G5 -> 19.39 | M4: =SUM(L5:L13)/C4/10.764 -> 258.75981
B5: ='Rate List - Office'!B6 -> Flooring | E5: =C4 -> 33.47 | G5: =E5+F5 -> 33.47 | H5: ='Rate List - Flats'!H6 -> Sq M | I5: ='Rate List - Office'!C6 -> 2'x2' Vitrified tiles | J5: ='Rate List - Flats'!E6 -> 45 | K5: ='Rate List - Flats'!G6 -> 1340.118 | L5: =G5*K5 -> 44853.749 | O5: =IF(I5="N.A",0,G5*$N$3) -> 1071.04 | P5: =L5*$N$3 -> 1435320 | R5: Vit Floor
B6: ='Rate List - Office'!B7 -> Skirting | E6: =D4 -> 19.39 | F6: =-(Doors!F130+'D&W Schedule'!C23) -> -6.95 | G6: =E6+F6 -> 12.44 | H6: ='Rate List - Flats'!H7 -> RM | I6: ='Rate List - Office'!C7 -> 2'x2' Vitrified tiles | J6: ='Rate List - Flats'!E7 -> 45 | K6: ='Rate List - Flats'!G7 -> 391.96 | L6: =G6*K6 -> 4875.9824 | O6: =IF(I6="N.A",0,G6*$N$3) -> 398.08 | P6: =L6*$N$3 -> 156031.44 | R6: Vit Skirt
B7: ='Rate List - Office'!B8 -> Dado | G7: =E7+F7 -> 0 | H7: ='Rate List - Flats'!H8 -> Sq M | I7: ='Rate List - Office'!C8 -> N.A. | L7: =G7*K7 -> 0 | O7: =IF(I7="N.A",0,G7*$N$3) -> 0 | P7: =L7*$N$3 -> 0
B8: ='Rate List - Office'!B9 -> Wall finishes plaster | E8: =D4*(D1-0.15) -> 66.8955 | F8: =-(Doors!H130+Doors!H131+Doors!H132+'D&W Schedule'!E23) -> -22.66 | G8: =E8+F8 -> 44.2355 | H8: ='Rate List - Flats'!H9 -> Sq M | I8: ='Rate List - Office'!C9 -> Gypsum Plaster | J8: ='Rate List - Flats'!E9 -> 32 | K8: ='Rate List - Flats'!G9 -> 344.448 | L8: =G8*K8 -> 15236.83 | O8: =IF(I8="N.A",0,G8*$N$3) -> 1415.536 | P8: =L8*$N$3 -> 487578.54 | R8: Gyp Wall
B9: ='Rate List - Office'!B10 -> Ceiling plaster | E9: =E5 -> 33.47 | G9: =E9+F9 -> 33.47 | H9: ='Rate List - Flats'!H10 -> Sq M | I9: ='Rate List - Office'!C10 -> Gypsum Plaster | J9: ='Rate List - Flats'!E10 -> 32 | K9: ='Rate List - Flats'!G10 -> 344.448 | L9: =G9*K9 -> 11528.675 | O9: =IF(I9="N.A",0,G9*$N$3) -> 1071.04 | P9: =L9*$N$3 -> 368917.59 | R9: Gyp Ceiling
B10: ='Rate List - Office'!B11 -> False ceiling | G10: =E10+F10 -> 0 | H10: ='Rate List - Flats'!H11 -> Sq M | I10: ='Rate List - Office'!C11 -> N.A. | L10: =G10*K10 -> 0 | O10: =IF(I10="N.A",0,G10*$N$3) -> 0 | P10: =L10*$N$3 -> 0
B11: ='Rate List - Office'!B12 -> Wall finishes Paint | E11: =E8 -> 66.8955 | F11: =F8 -> -22.66 | G11: =E11+F11 -> 44.2355 | H11: ='Rate List - Flats'!H12 -> Sq M | I11: ='Rate List - Office'!C12 -> Plastic paint | J11: ='Rate List - Flats'!E12 -> 20 | K11: ='Rate List - Flats'!G12 -> 215.28 | L11: =G11*K11 -> 9523.0184 | O11: =IF(I11="N.A",0,G11*$N$3) -> 1415.536 | P11: =L11*$N$3 -> 304736.59 | R11: Acr Paint Wall
B12: ='Rate List - Office'!B13 -> Ceiling Paint | E12: =E9 -> 33.47 | G12: =E12+F12 -> 33.47 | H12: ='Rate List - Flats'!H13 -> Sq M | I12: ='Rate List - Office'!C13 -> Plastic paint | J12: ='Rate List - Flats'!E13 -> 20 | K12: ='Rate List - Flats'!G13 -> 215.28 | L12: =G12*K12 -> 7205.4216 | O12: =IF(I12="N.A",0,G12*$N$3) -> 1071.04 | P12: =L12*$N$3 -> 230573.49 | R12: Acr Paint Ceiling
B13: ='Rate List - Office'!B14 -> Others | G13: =E13+F13 -> 0 | H13: ='Rate List - Flats'!H14 -> RM | I13: ='Rate List - Office'!C14 -> N.A. | L13: =G13*K13 -> 0 | O13: =IF(I13="N.A",0,G13*$N$3) -> 0 | P13: =L13*$N$3 -> 0
A14: # | B14: ='Office Sizes'!B6 -> Pantry | C14: ='Office Sizes'!D6 -> 2.07 | D14: ='Office Sizes'!G6 -> 6.04 | M14: =SUM(L15:L24)/C14/10.764 -> 854.97596
B15: ='Rate List - Office'!B31 -> Flooring | E15: =C14 -> 2.07 | G15: =E15+F15 -> 2.07 | H15: {='Rate List - Office'!H31:H42} -> Sq M | I15: ='Rate List - Office'!C31 -> ceramic tiles/vitrified anti-skid tiles | J15: ='Rate List - Office'!E31 -> 40 | K15: ='Rate List - Office'!G31 -> 1280.916 | L15: =G15*K15 -> 2651.4961 | O15: =IF(I15="N.A",0,G15*$N$3) -> 66.24 | P15: =L15*$N$3 -> 84847.876 | R15: Vit Floor
B16: ='Rate List - Office'!B32 -> Skirting | G16: =E16+F16 -> 0 | H16: RM | I16: ='Rate List - Office'!C32 -> N.A. | J16: ='Rate List - Office'!E32 -> 0 | K16: ='Rate List - Office'!G32 -> 0 | L16: =G16*K16 -> 0 | O16: =IF(I16="N.A",0,G16*$N$3) -> 0 | P16: =L16*$N$3 -> 0 | R16: Vit Skirt
B17: ='Rate List - Office'!B33 -> Dado | D17: 2.4 | E17: =E26*D17 -> 3.6 | G17: =E17+F17 -> 3.6 | H17: Sq M | I17: ='Rate List - Office'!C33 -> Vitrified tiles | J17: ='Rate List - Office'!E33 -> 40 | K17: ='Rate List - Office'!G33 -> 1334.736 | L17: =G17*K17 -> 4805.0496 | O17: =IF(I17="N.A",0,G17*$N$3) -> 115.2 | P17: =L17*$N$3 -> 153761.59 | R17: Vit Kitchen Dado
B18: ='Rate List - Office'!B34 -> Wall finishes plaster | E18: =D14*($D$1-0.15) -> 20.838 | F18: =-Doors!H131-E17-'D&W Schedule'!E19 -> -5.94 | G18: =E18+F18 -> 14.898 | H18: Sq M | I18: ='Rate List - Office'!C34 -> Gypsum Plaster | J18: ='Rate List - Office'!E34 -> 25 | K18: ='Rate List - Office'!G34 -> 376.74 | L18: =G18*K18 -> 5612.6725 | O18: =IF(I18="N.A",0,G18*$N$3) -> 476.736 | P18: =L18*$N$3 -> 179605.52 | R18: Gyp Wall
B19: ='Rate List - Office'!B35 -> Ceiling plaster | E19: =E15 -> 2.07 | G19: =E19+F19 -> 2.07 | H19: Sq M | I19: ='Rate List - Office'!C35 -> Gypsum Plaster | J19: ='Rate List - Office'!E35 -> 25 | K19: ='Rate List - Office'!G35 -> 269.1 | L19: =G19*K19 -> 557.037 | O19: =IF(I19="N.A",0,G19*$N$3) -> 66.24 | P19: =L19*$N$3 -> 17825.184 | R19: Gyp Ceiling
B20: ='Rate List - Office'!B36 -> False ceiling | G20: =E20+F20 -> 0 | H20: Sq M | I20: ='Rate List - Office'!C36 -> N.A. | J20: ='Rate List - Office'!E36 -> 0 | K20: ='Rate List - Office'!G36 -> 0 | L20: =G20*K20 -> 0 | O20: =IF(I20="N.A",0,G20*$N$3) -> 0 | P20: =L20*$N$3 -> 0
B21: ='Rate List - Office'!B37 -> Wall finishes Paint | E21: =E18 -> 20.838 | F21: =F18 -> -5.94 | G21: =E21+F21 -> 14.898 | H21: Sq M | I21: ='Rate List - Office'!C37 -> Plastic paint | J21: ='Rate List - Office'!E37 -> 20 | K21: ='Rate List - Office'!G37 -> 215.28 | L21: =G21*K21 -> 3207.2414 | O21: =IF(I21="N.A",0,G21*$N$3) -> 476.736 | P21: =L21*$N$3 -> 102631.73 | R21: Acr Paint Wall
B22: ='Rate List - Office'!B38 -> Ceiling Paint | E22: =E19 -> 2.07 | G22: =E22+F22 -> 2.07 | H22: Sq M | I22: ='Rate List - Office'!C38 -> Plastic paint | J22: ='Rate List - Office'!E38 -> 20 | K22: ='Rate List - Office'!G38 -> 215.28 | L22: =G22*K22 -> 445.6296 | O22: =IF(I22="N.A",0,G22*$N$3) -> 66.24 | P22: =L22*$N$3 -> 14260.147 | R22: Acr Paint Ceiling
B23: ='Rate List - Office'!B39 -> Door Frames | G23: =E23+F23 -> 0 | H23: Sq M | I23: ='Rate List - Office'!C39 -> N.A. | J23: ='Rate List - Office'!E39 -> 0 | K23: ='Rate List - Office'!G39 -> 0 | L23: =G23*K23 -> 0 | O23: =IF(I23="N.A",0,G23*$N$3) -> 0 | P23: =L23*$N$3 -> 0
B24: ='Rate List - Office'!B40 -> Window Frames - Internal | E24: =Windows!F153*2+Windows!G153*2 -> 2.7 | G24: =E24+F24 -> 2.7 | H24: RM | I24: ='Rate List - Office'!C40 -> Granite Window Frame | J24: ='Rate List - Office'!E40 -> 180 | K24: ='Rate List - Office'!G40 -> 655.9272 | L24: =G24*K24 -> 1771.0034 | O24: =IF(I24="N.A",0,G24*$N$3) -> 86.4 | P24: =L24*$N$3 -> 56672.11 | R24: Granite Window Frame
B25: ='Rate List - Office'!B41 -> Window Frames - External | E25: =E24 -> 2.7 | G25: =E25+F25 -> 2.7 | H25: RM | I25: ='Rate List - Office'!C41 -> Marble Window Frames with Sill | J25: ='Rate List - Office'!E41 -> 60 | K25: ='Rate List - Office'!G41 -> 399.0424 | L25: =G25*K25 -> 1077.4145 | O25: =IF(I25="N.A",0,G25*$N$3) -> 86.4 | P25: =L25*$N$3 -> 34477.263 | R25: Marble Window Frame
B26: ='Rate List - Office'!B42 -> Service Platform | E26: 1.5 | G26: =E26+F26 -> 1.5 | H26: RM | I26: ='Rate List - Office'!C42 -> Kitchen 1'6" Granite Main Counter | J26: ='Rate List - Office'!E42 -> 180 | K26: ='Rate List - Office'!G42 -> 7312.7984 | L26: =G26*K26 -> 10969.198 | O26: =IF(I26="N.A",0,G26*$N$3) -> 48 | P26: =L26*$N$3 -> 351014.32 | R26: Service Platform
A27: # | B27: ='Office Sizes'!B7 -> WC | C27: ='Office Sizes'!D7 -> 2.06 | D27: ='Office Sizes'!G7 -> 5.82 | M27: =SUM(L28:L39)/C27/10.764 -> 1592.4971
B28: ='Rate List - Office'!B17 -> Flooring | E28: =C27 -> 2.06 | G28: =E28+F28 -> 2.06 | H28: ='Rate List - Office'!H17 -> Sq M | I28: ='Rate List - Office'!C17 -> Ceramic tiles/vitrified anti-skid tiles | J28: ='Rate List - Office'!E17 -> 40 | K28: ='Rate List - Office'!G17 -> 1280.916 | L28: =G28*K28 -> 2638.687 | O28: =IF(I28="N.A",0,G28*$N$3) -> 65.92 | P28: =L28*$N$3 -> 84437.983 | R28: Vitr Flooring - Toilet
B29: ='Rate List - Office'!B18 -> Skirting | G29: =E29+F29 -> 0 | H29: ='Rate List - Office'!H18 -> RM | I29: ='Rate List - Office'!C18 -> N.A. | J29: ='Rate List - Office'!E18 -> 0 | K29: ='Rate List - Office'!G18 -> 0 | L29: =G29*K29 -> 0 | O29: =IF(I29="N.A",0,G29*$N$3) -> 0 | P29: =L29*$N$3 -> 0
B30: ='Rate List - Office'!B19 -> Dado | D30: =2.4 -> 2.4 | E30: =D27*D30 -> 13.968 | F30: =-Windows!$H$153-Doors!$H$132 -> -2.025 | G30: =E30+F30 -> 11.943 | H30: ='Rate List - Office'!H19 -> Sq M | I30: ='Rate List - Office'!C19 -> Vitrified tiles | J30: ='Rate List - Office'!E19 -> 40 | K30: ='Rate List - Office'!G19 -> 1356.264 | L30: =G30*K30 -> 16197.861 | O30: =IF(I30="N.A",0,G30*$N$3) -> 382.176 | P30: =L30*$N$3 -> 518331.55 | R30: Vitr Dado - Toilet
B31: ='Rate List - Office'!B20 -> Wall finishes plaster | D31: =D1-D30 -> 1.2 | E31: =D27*D31 -> 6.984 | G31: =E31+F31 -> 6.984 | H31: ='Rate List - Office'!H20 -> Sq M | I31: ='Rate List - Office'!C20 -> Gypsum Plaster | J31: ='Rate List - Office'!E20 -> 25 | K31: ='Rate List - Office'!G20 -> 269.1 | L31: =G31*K31 -> 1879.3944 | O31: =IF(I31="N.A",0,G31*$N$3) -> 223.488 | P31: =L31*$N$3 -> 60140.621 | R31: Gyp Wall
B32: ='Rate List - Office'!B21 -> Ceiling plaster | E32: =E28 -> 2.06 | G32: =E32+F32 -> 2.06 | H32: ='Rate List - Office'!H21 -> Sq M | I32: ='Rate List - Office'!C21 -> Gypsum Plaster | J32: ='Rate List - Office'!E21 -> 25 | K32: ='Rate List - Office'!G21 -> 269.1 | L32: =G32*K32 -> 554.346 | O32: =IF(I32="N.A",0,G32*$N$3) -> 65.92 | P32: =L32*$N$3 -> 17739.072 | R32: Gyp Ceiling
B33: ='Rate List - Office'!B22 -> False ceiling | G33: =E33+F33 -> 0 | H33: ='Rate List - Office'!H22 -> Sq M | I33: ='Rate List - Office'!C22 -> N.A. | J33: ='Rate List - Office'!E22 -> 0 | K33: ='Rate List - Office'!G22 -> 0 | L33: =G33*K33 -> 0 | O33: =IF(I33="N.A",0,G33*$N$3) -> 0 | P33: =L33*$N$3 -> 0
B34: ='Rate List - Office'!B23 -> Wall finishes Paint | E34: =E31 -> 6.984 | G34: =E34+F34 -> 6.984 | H34: ='Rate List - Office'!H23 -> Sq M | I34: ='Rate List - Office'!C23 -> Plastic paint | J34: ='Rate List - Office'!E23 -> 25 | K34: ='Rate List - Office'!G23 -> 269.1 | L34: =G34*K34 -> 1879.3944 | O34: =IF(I34="N.A",0,G34*$N$3) -> 223.488 | P34: =L34*$N$3 -> 60140.621 | R34: Acr Paint Wall
B35: ='Rate List - Office'!B24 -> Ceiling Paint | E35: =E32 -> 2.06 | G35: =E35+F35 -> 2.06 | H35: ='Rate List - Office'!H24 -> Sq M | I35: ='Rate List - Office'!C24 -> Plastic paint | J35: ='Rate List - Office'!E24 -> 25 | K35: ='Rate List - Office'!G24 -> 269.1 | L35: =G35*K35 -> 554.346 | O35: =IF(I35="N.A",0,G35*$N$3) -> 65.92 | P35: =L35*$N$3 -> 17739.072 | R35: Acr Paint Ceiling
B36: ='Rate List - Office'!B25 -> Door Frames | E36: =Doors!$F$132*4+Doors!$G$132*4 -> 11.4 | G36: =E36+F36 -> 11.4 | H36: ='Rate List - Office'!H25 -> RM | I36: ='Rate List - Office'!C25 -> Granite Frames | J36: ='Rate List - Office'!E25 -> 180 | K36: ='Rate List - Office'!G25 -> 655.9272 | L36: =G36*K36 -> 7477.5701 | O36: =IF(I36="N.A",0,G36*$N$3) -> 364.8 | P36: =L36*$N$3 -> 239282.24 | R36: Granite Door Frame
B37: ='Rate List - Office'!B26 -> Window Frames - Internal | E37: =$E$24 -> 2.7 | G37: =E37+F37 -> 2.7 | H37: ='Rate List - Office'!H26 -> RM | I37: ='Rate List - Office'!C26 -> Granite Window Frame | J37: ='Rate List - Office'!E26 -> 180 | K37: ='Rate List - Office'!G26 -> 655.9272 | L37: =G37*K37 -> 1771.0034 | O37: =IF(I37="N.A",0,G37*$N$3) -> 86.4 | P37: =L37*$N$3 -> 56672.11 | R37: Granite Window Frame
